Workbook
Name EFETIVO: #REF!
Name EFETIVO: #REF!
Name SSSSS: #REF!
Name SSSSS: #REF!
Name SSSSSS: #REF!
Name SSSSSS: #REF!
Name xxxxxxxxxxx: #REF!
Name xxxxxxxxxxx: #REF!

Sheet RESUMO-CURVA ACM
A3: PREV | B3: REAL | C3: Item | D3: Descrição | E3: CONTRATO | F3: ACUMULADO | H3: PERCENTUAL | I3: CONTRATO | J3: ACUMULADO
A4: 220 | B4: 221 | C4: 2.14 | D4: ="FERRAMENTAS - CIVIL " -> FERRAMENTAS - CIVIL | E4: =I4 -> 6965.42 | F4: =J4 -> 3935.0304 | G4: 20 | H4: =SUMIF('RESUMO-CURVA GRÁFICO'!$B$4:$B$261,'RESUMO-CURVA ACM'!B4,'RESUMO-CURVA GRÁFICO'!$Y$4:$Y$261) -> 0.56493799 | I4: =SUMIF('RESUMO-CURVA GRÁFICO'!$B$4:$B$261,'RESUMO-CURVA ACM'!A4,'RESUMO-CURVA GRÁFICO'!$X$4:$X$261) -> 6965.42 | J4: =SUMIF('RESUMO-CURVA GRÁFICO'!$B$4:$B$261,'RESUMO-CURVA ACM'!B4,'RESUMO-CURVA GRÁFICO'!$X$4:$X$261) -> 3935.0304
A5: 212 | B5: 213 | C5: 2.12 | D5: ="INSTRUMENTOS - ELÉTRICA" -> INSTRUMENTOS - ELÉTRICA | E5: =I5 -> 14304 | F5: =J5 -> 2791.7333 | G5: 19 | H5: =SUMIF('RESUMO-CURVA GRÁFICO'!$B$4:$B$261,'RESUMO-CURVA ACM'!B5,'RESUMO-CURVA GRÁFICO'!$Y$4:$Y$261) -> 0.19517151 | I5: =SUMIF('RESUMO-CURVA GRÁFICO'!$B$4:$B$261,'RESUMO-CURVA ACM'!A5,'RESUMO-CURVA GRÁFICO'!$X$4:$X$261) -> 14304 | J5: =SUMIF('RESUMO-CURVA GRÁFICO'!$B$4:$B$261,'RESUMO-CURVA ACM'!B5,'RESUMO-CURVA GRÁFICO'!$X$4:$X$261) -> 2791.7333
A6: 228 | B6: 229 | C6: 2.16 | D6: ="MOBILIZAÇÃO E DESMOBILIZAÇÃO " -> MOBILIZAÇÃO E DESMOBILIZAÇÃO | E6: =I6 -> 16308.35 | F6: =J6 -> 8154.175 | G6: 18 | H6: =SUMIF('RESUMO-CURVA GRÁFICO'!$B$4:$B$261,'RESUMO-CURVA ACM'!B6,'RESUMO-CURVA GRÁFICO'!$Y$4:$Y$261) -> 0.5 | I6: =SUMIF('RESUMO-CURVA GRÁFICO'!$B$4:$B$261,'RESUMO-CURVA ACM'!A6,'RESUMO-CURVA GRÁFICO'!$X$4:$X$261) -> 16308.35 | J6: =SUMIF('RESUMO-CURVA GRÁFICO'!$B$4:$B$261,'RESUMO-CURVA ACM'!B6,'RESUMO-CURVA GRÁFICO'!$X$4:$X$261) -> 8154.175
A7: 234 | B7: 235 | C7: 2.17 | D7: ="FRENTES MÓVEIS" -> FRENTES MÓVEIS | E7: =I7 -> 70204 | F7: =J7 -> 39782.267 | G7: 17 | H7: =SUMIF('RESUMO-CURVA GRÁFICO'!$B$4:$B$261,'RESUMO-CURVA ACM'!B7,'RESUMO-CURVA GRÁFICO'!$Y$4:$Y$261) -> 0.56666667 | I7: =SUMIF('RESUMO-CURVA GRÁFICO'!$B$4:$B$261,'RESUMO-CURVA ACM'!A7,'RESUMO-CURVA GRÁFICO'!$X$4:$X$261) -> 70204 | J7: =SUMIF('RESUMO-CURVA GRÁFICO'!$B$4:$B$261,'RESUMO-CURVA ACM'!B7,'RESUMO-CURVA GRÁFICO'!$X$4:$X$261) -> 39782.267
A8: 196 | B8: 197 | C8: 2.8 | D8: ="MATERIAL DE CONSUMO - ELÉTRICO" -> MATERIAL DE CONSUMO - ELÉTRICO | E8: =I8 -> 83279.41 | F8: =J8 -> 39574.542 | G8: 16 | H8: =SUMIF('RESUMO-CURVA GRÁFICO'!$B$4:$B$261,'RESUMO-CURVA ACM'!B8,'RESUMO-CURVA GRÁFICO'!$Y$4:$Y$261) -> 0.475202 | I8: =SUMIF('RESUMO-CURVA GRÁFICO'!$B$4:$B$261,'RESUMO-CURVA ACM'!A8,'RESUMO-CURVA GRÁFICO'!$X$4:$X$261) -> 83279.41 | J8: =SUMIF('RESUMO-CURVA GRÁFICO'!$B$4:$B$261,'RESUMO-CURVA ACM'!B8,'RESUMO-CURVA GRÁFICO'!$X$4:$X$261) -> 39574.542
A9: 200 | B9: 201 | C9: 2.9 | D9: ="FERRAMENTAS ELÉTRICA" -> FERRAMENTAS ELÉTRICA | E9: =I9 -> 96713.2 | F9: =J9 -> 31392.959 | G9: 15 | H9: =SUMIF('RESUMO-CURVA GRÁFICO'!$B$4:$B$261,'RESUMO-CURVA ACM'!B9,'RESUMO-CURVA GRÁFICO'!$Y$4:$Y$261) -> 0.32459849 | I9: =SUMIF('RESUMO-CURVA GRÁFICO'!$B$4:$B$261,'RESUMO-CURVA ACM'!A9,'RESUMO-CURVA GRÁFICO'!$X$4:$X$261) -> 96713.2 | J9: =SUMIF('RESUMO-CURVA GRÁFICO'!$B$4:$B$261,'RESUMO-CURVA ACM'!B9,'RESUMO-CURVA GRÁFICO'!$X$4:$X$261) -> 31392.959
A10: 96 | B10: 97 | C10: 2.2 | D10: ="EQUIPAMENTOS DE INFORMÁTICA" -> EQUIPAMENTOS DE INFORMÁTICA | E10: =I10 -> 138086.16 | F10: =J10 -> 78248.824 | G10: 14 | H10: =SUMIF('RESUMO-CURVA GRÁFICO'!$B$4:$B$261,'RESUMO-CURVA ACM'!B10,'RESUMO-CURVA GRÁFICO'!$Y$4:$Y$261) -> 0.56666667 | I10: =SUMIF('RESUMO-CURVA GRÁFICO'!$B$4:$B$261,'RESUMO-CURVA ACM'!A10,'RESUMO-CURVA GRÁFICO'!$X$4:$X$261) -> 138086.16 | J10: =SUMIF('RESUMO-CURVA GRÁFICO'!$B$4:$B$261,'RESUMO-CURVA ACM'!B10,'RESUMO-CURVA GRÁFICO'!$X$4:$X$261) -> 78248.824
A11: 216 | B11: 217 | C11: 2.13 | D11: ="MANUTENÇÃO CIVIL - MATERIAIS CONSUMÍVEIS" -> MANUTENÇÃO CIVIL - MATERIAIS CONSUMÍVEIS | E11: =I11 -> 237025.32 | F11: =J11 -> 145430.81 | G11: 13 | H11: =SUMIF('RESUMO-CURVA GRÁFICO'!$B$4:$B$261,'RESUMO-CURVA ACM'!B11,'RESUMO-CURVA GRÁFICO'!$Y$4:$Y$261) -> 0.61356658 | I11: =SUMIF('RESUMO-CURVA GRÁFICO'!$B$4:$B$261,'RESUMO-CURVA ACM'!A11,'RESUMO-CURVA GRÁFICO'!$X$4:$X$261) -> 237025.32 | J11: =SUMIF('RESUMO-CURVA GRÁFICO'!$B$4:$B$261,'RESUMO-CURVA ACM'!B11,'RESUMO-CURVA GRÁFICO'!$X$4:$X$261) -> 145430.81
A12: 224 | B12: 225 | C12: 2.15 | D12: ="TRANSPORTE DE EQUIPAMENTOS" -> TRANSPORTE DE EQUIPAMENTOS | E12: =I12 -> 270788.7 | F12: =J12 -> 0 | G12: 12 | H12: =SUMIF('RESUMO-CURVA GRÁFICO'!$B$4:$B$261,'RESUMO-CURVA ACM'!B12,'RESUMO-CURVA GRÁFICO'!$Y$4:$Y$261) -> 0 | I12: =SUMIF('RESUMO-CURVA GRÁFICO'!$B$4:$B$261,'RESUMO-CURVA ACM'!A12,'RESUMO-CURVA GRÁFICO'!$X$4:$X$261) -> 270788.7 | J12: =SUMIF('RESUMO-CURVA GRÁFICO'!$B$4:$B$261,'RESUMO-CURVA ACM'!B12,'RESUMO-CURVA GRÁFICO'!$X$4:$X$261) -> 0
A13: 256 | B13: 257 | C13: 3 | D13: ="DESPESAS REEMBOLSÁVEIS" -> DESPESAS REEMBOLSÁVEIS | E13: =I13 -> 337157.91 | F13: =J13 -> 169515.73 | G13: 11 | H13: =SUMIF('RESUMO-CURVA GRÁFICO'!$B$4:$B$261,'RESUMO-CURVA ACM'!B13,'RESUMO-CURVA GRÁFICO'!$Y$4:$Y$261) -> 0.50277845 | I13: =SUMIF('RESUMO-CURVA GRÁFICO'!$B$4:$B$261,'RESUMO-CURVA ACM'!A13,'RESUMO-CURVA GRÁFICO'!$X$4:$X$261) -> 337157.91 | J13: =SUMIF('RESUMO-CURVA GRÁFICO'!$B$4:$B$261,'RESUMO-CURVA ACM'!B13,'RESUMO-CURVA GRÁFICO'!$X$4:$X$261) -> 169515.73
A14: 84 | B14: 85 | C14: 2.1 | D14: ="VIAGENS" -> VIAGENS | E14: =I14 -> 382021.68 | F14: =J14 -> 94516.99 | G14: 10 | H14: =SUMIF('RESUMO-CURVA GRÁFICO'!$B$4:$B$261,'RESUMO-CURVA ACM'!B14,'RESUMO-CURVA GRÁFICO'!$Y$4:$Y$261) -> 0.24741263 | I14: =SUMIF('RESUMO-CURVA GRÁFICO'!$B$4:$B$261,'RESUMO-CURVA ACM'!A14,'RESUMO-CURVA GRÁFICO'!$X$4:$X$261) -> 382021.68 | J14: =SUMIF('RESUMO-CURVA GRÁFICO'!$B$4:$B$261,'RESUMO-CURVA ACM'!B14,'RESUMO-CURVA GRÁFICO'!$X$4:$X$261) -> 94516.99
A15: 204 | B15: 205 | C15: 2.10 | D15: ="SOBRESSALENTES - ELÉTRICA" -> SOBRESSALENTES - ELÉTRICA | E15: =I15 -> 426502.25 | F15: =J15 -> 77900.75 | G15: 9 | H15: =SUMIF('RESUMO-CURVA GRÁFICO'!$B$4:$B$261,'RESUMO-CURVA ACM'!B15,'RESUMO-CURVA GRÁFICO'!$Y$4:$Y$261) -> 0.18265027 | I15: =SUMIF('RESUMO-CURVA GRÁFICO'!$B$4:$B$261,'RESUMO-CURVA ACM'!A15,'RESUMO-CURVA GRÁFICO'!$X$4:$X$261) -> 426502.25 | J15: =SUMIF('RESUMO-CURVA GRÁFICO'!$B$4:$B$261,'RESUMO-CURVA ACM'!B15,'RESUMO-CURVA GRÁFICO'!$X$4:$X$261) -> 77900.75
A16: 208 | B16: 209 | C16: 2.11 | D16: ="SOBRESSALENTES - LINHA DE TRANSMISSÃO" -> SOBRESSALENTES - LINHA DE TRANSMISSÃO | E16: =I16 -> 469086.46 | F16: =J16 -> 3220.1303 | G16: 8 | H16: =SUMIF('RESUMO-CURVA GRÁFICO'!$B$4:$B$261,'RESUMO-CURVA ACM'!B16,'RESUMO-CURVA GRÁFICO'!$Y$4:$Y$261) -> 0.006864684 | I16: =SUMIF('RESUMO-CURVA GRÁFICO'!$B$4:$B$261,'RESUMO-CURVA ACM'!A16,'RESUMO-CURVA GRÁFICO'!$X$4:$X$261) -> 469086.46 | J16: =SUMIF('RESUMO-CURVA GRÁFICO'!$B$4:$B$261,'RESUMO-CURVA ACM'!B16,'RESUMO-CURVA GRÁFICO'!$X$4:$X$261) -> 3220.1303
A17: 126 | B17: 127 | C17: 2.4 | D17: ="ESCRITÓRIO" -> ESCRITÓRIO | E17: =I17 -> 518209.68 | F17: =J17 -> 293425.62 | G17: 7 | H17: =SUMIF('RESUMO-CURVA GRÁFICO'!$B$4:$B$261,'RESUMO-CURVA ACM'!B17,'RESUMO-CURVA GRÁFICO'!$Y$4:$Y$261) -> 0.56622953 | I17: =SUMIF('RESUMO-CURVA GRÁFICO'!$B$4:$B$261,'RESUMO-CURVA ACM'!A17,'RESUMO-CURVA GRÁFICO'!$X$4:$X$261) -> 518209.68 | J17: =SUMIF('RESUMO-CURVA GRÁFICO'!$B$4:$B$261,'RESUMO-CURVA ACM'!B17,'RESUMO-CURVA GRÁFICO'!$X$4:$X$261) -> 293425.62
A18: 142 | B18: 143 | C18: 2.5 | D18: ="SISTEMA DE RÁDIO COMUNICAÇÃO" -> SISTEMA DE RÁDIO COMUNICAÇÃO | E18: =I18 -> 528013.08 | F18: =J18 -> 278959.32 | G18: 6 | H18: =SUMIF('RESUMO-CURVA GRÁFICO'!$B$4:$B$261,'RESUMO-CURVA ACM'!B18,'RESUMO-CURVA GRÁFICO'!$Y$4:$Y$261) -> 0.52831897 | I18: =SUMIF('RESUMO-CURVA GRÁFICO'!$B$4:$B$261,'RESUMO-CURVA ACM'!A18,'RESUMO-CURVA GRÁFICO'!$X$4:$X$261) -> 528013.08 | J18: =SUMIF('RESUMO-CURVA GRÁFICO'!$B$4:$B$261,'RESUMO-CURVA ACM'!B18,'RESUMO-CURVA GRÁFICO'!$X$4:$X$261) -> 278959.32
A19: 158 | B19: 159 | C19: 2.6 | D19: ="INSTALAÇÃO DA EQUIPE" -> INSTALAÇÃO DA EQUIPE | E19: =I19 -> 685215 | F19: =J19 -> 388288.5 | G19: 5 | H19: =SUMIF('RESUMO-CURVA GRÁFICO'!$B$4:$B$261,'RESUMO-CURVA ACM'!B19,'RESUMO-CURVA GRÁFICO'!$Y$4:$Y$261) -> 0.56666667 | I19: =SUMIF('RESUMO-CURVA GRÁFICO'!$B$4:$B$261,'RESUMO-CURVA ACM'!A19,'RESUMO-CURVA GRÁFICO'!$X$4:$X$261) -> 685215 | J19: =SUMIF('RESUMO-CURVA GRÁFICO'!$B$4:$B$261,'RESUMO-CURVA ACM'!B19,'RESUMO-CURVA GRÁFICO'!$X$4:$X$261) -> 388288.5
A20: 166 | B20: 167 | C20: 2.7 | D20: ="EQUIPAMENTOS PARA MANUTENÇÃO ELÉTRICA" -> EQUIPAMENTOS PARA MANUTENÇÃO ELÉTRICA | E20: =I20 -> 4591811.1 | F20: =J20 -> 2717231.3 | G20: 4 | H20: =SUMIF('RESUMO-CURVA GRÁFICO'!$B$4:$B$261,'RESUMO-CURVA ACM'!B20,'RESUMO-CURVA GRÁFICO'!$Y$4:$Y$261) -> 0.5917559 | I20: =SUMIF('RESUMO-CURVA GRÁFICO'!$B$4:$B$261,'RESUMO-CURVA ACM'!A20,'RESUMO-CURVA GRÁFICO'!$X$4:$X$261) -> 4591811.1 | J20: =SUMIF('RESUMO-CURVA GRÁFICO'!$B$4:$B$261,'RESUMO-CURVA ACM'!B20,'RESUMO-CURVA GRÁFICO'!$X$4:$X$261) -> 2717231.3
A21: 112 | B21: 113 | C21: 2.3 | D21: ="VEÍCULOS, COMBUSTÍVEL E MANUTENÇÃO" -> VEÍCULOS, COMBUSTÍVEL E MANUTENÇÃO | E21: =I21 -> 3783418.9 | F21: =J21 -> 2109858.5 | G21: 3 | H21: =SUMIF('RESUMO-CURVA GRÁFICO'!$B$4:$B$261,'RESUMO-CURVA ACM'!B21,'RESUMO-CURVA GRÁFICO'!$Y$4:$Y$261) -> 0.55765924 | I21: =SUMIF('RESUMO-CURVA GRÁFICO'!$B$4:$B$261,'RESUMO-CURVA ACM'!A21,'RESUMO-CURVA GRÁFICO'!$X$4:$X$261) -> 3783418.9 | J21: =SUMIF('RESUMO-CURVA GRÁFICO'!$B$4:$B$261,'RESUMO-CURVA ACM'!B21,'RESUMO-CURVA GRÁFICO'!$X$4:$X$261) -> 2109858.5
A22: 78 | B22: 79 | C22: 1 | D22: ="RESUMO DA MÃO DE OBRA" -> RESUMO DA MÃO DE OBRA | E22: =I22 -> 18310884 | F22: =J22 -> 9407553.8 | G22: 1 | H22: =SUMIF('RESUMO-CURVA GRÁFICO'!$B$4:$B$261,'RESUMO-CURVA ACM'!B22,'RESUMO-CURVA GRÁFICO'!$Y$4:$Y$261) -> 0.51376841 | I22: =SUMIF('RESUMO-CURVA GRÁFICO'!$B$4:$B$261,'RESUMO-CURVA ACM'!A22,'RESUMO-CURVA GRÁFICO'!$X$4:$X$261) -> 18310884 | J22: =SUMIF('RESUMO-CURVA GRÁFICO'!$B$4:$B$261,'RESUMO-CURVA ACM'!B22,'RESUMO-CURVA GRÁFICO'!$X$4:$X$261) -> 9407553.8
A23: 249 | B23: 250 | C23: 2 | D23: ="CUSTOS DIRETOS" -> CUSTOS DIRETOS | E23: =I23 -> 12317953 | F23: =J23 -> 6312711.5 | G23: 2 | H23: =SUMIF('RESUMO-CURVA GRÁFICO'!$B$4:$B$261,'RESUMO-CURVA ACM'!B23,'RESUMO-CURVA GRÁFICO'!$Y$4:$Y$261) -> 0.51248057 | I23: =SUMIF('RESUMO-CURVA GRÁFICO'!$B$4:$B$261,'RESUMO-CURVA ACM'!A23,'RESUMO-CURVA GRÁFICO'!$X$4:$X$261) -> 12317953 | J23: =SUMIF('RESUMO-CURVA GRÁFICO'!$B$4:$B$261,'RESUMO-CURVA ACM'!B23,'RESUMO-CURVA GRÁFICO'!$X$4:$X$261) -> 6312711.5
E24: =SUM(E4:E12,E14:E21,E22,E13) -> 30965995 | F24: =SUM(F4:F12,F14:F21,F22,F13) -> 15889781 | H24: =F24/E24 -> 0.51313646 | I24: =SUM(I4:I12,I14:I21,I22,I13) -> 30965995 | J24: =SUM(J4:J12,J14:J21,J22,J13) -> 15889781
E25: =E24-I24 -> 0 | F25: =F24-J24 -> 0 | I25: =I24-'Evolução Mensal'!AR12 -> 7.3425472e-06 | J25: =J24-'Evolução Mensal'!AR13 -> 0

Sheet RESUMO-CURVA PREV
A3: PREV | B3: REAL | C3: Item | D3: Descrição | E3: CONTRATO | F3: PREVISÃO | H3: PERCENTUAL | I3: CONTRATO | J3: PREVISÃO
A4: 220 | B4: 221 | C4: 2.14 | D4: ="FERRAMENTAS - CIVIL " -> FERRAMENTAS - CIVIL | E4: =I4 -> 6965.42 | F4: =J4 -> 6965.42 | G4: 20 | H4: =SUMIF('RESUMO-CURVA GRÁFICO'!$B$4:$B$261,'RESUMO-CURVA PREV'!B4,'RESUMO-CURVA GRÁFICO'!$AD$4:$AD$261) -> 1 | I4: =SUMIF('RESUMO-CURVA GRÁFICO'!$B$4:$B$261,'RESUMO-CURVA PREV'!A4,'RESUMO-CURVA GRÁFICO'!$X$4:$X$261) -> 6965.42 | J4: =SUMIF('RESUMO-CURVA GRÁFICO'!$B$4:$B$261,'RESUMO-CURVA PREV'!B4,'RESUMO-CURVA GRÁFICO'!$AC$4:$AC$261) -> 6965.42
A5: 212 | B5: 213 | C5: 2.12 | D5: ="INSTRUMENTOS - ELÉTRICA" -> INSTRUMENTOS - ELÉTRICA | E5: =I5 -> 14304 | F5: =J5 -> 4971.36 | G5: 19 | H5: =SUMIF('RESUMO-CURVA GRÁFICO'!$B$4:$B$261,'RESUMO-CURVA PREV'!B5,'RESUMO-CURVA GRÁFICO'!$AD$4:$AD$261) -> 0.34755034 | I5: =SUMIF('RESUMO-CURVA GRÁFICO'!$B$4:$B$261,'RESUMO-CURVA PREV'!A5,'RESUMO-CURVA GRÁFICO'!$X$4:$X$261) -> 14304 | J5: =SUMIF('RESUMO-CURVA GRÁFICO'!$B$4:$B$261,'RESUMO-CURVA PREV'!B5,'RESUMO-CURVA GRÁFICO'!$AC$4:$AC$261) -> 4971.36
A6: 228 | B6: 229 | C6: 2.16 | D6: ="MOBILIZAÇÃO E DESMOBILIZAÇÃO " -> MOBILIZAÇÃO E DESMOBILIZAÇÃO | E6: =I6 -> 16308.35 | F6: =J6 -> 8154.175 | G6: 18 | H6: =SUMIF('RESUMO-CURVA GRÁFICO'!$B$4:$B$261,'RESUMO-CURVA PREV'!B6,'RESUMO-CURVA GRÁFICO'!$AD$4:$AD$261) -> 0.5 | I6: =SUMIF('RESUMO-CURVA GRÁFICO'!$B$4:$B$261,'RESUMO-CURVA PREV'!A6,'RESUMO-CURVA GRÁFICO'!$X$4:$X$261) -> 16308.35 | J6: =SUMIF('RESUMO-CURVA GRÁFICO'!$B$4:$B$261,'RESUMO-CURVA PREV'!B6,'RESUMO-CURVA GRÁFICO'!$AC$4:$AC$261) -> 8154.175
A7: 234 | B7: 235 | C7: 2.17 | D7: ="FRENTES MÓVEIS" -> FRENTES MÓVEIS | E7: =I7 -> 70204 | F7: =J7 -> 70204 | G7: 17 | H7: =SUMIF('RESUMO-CURVA GRÁFICO'!$B$4:$B$261,'RESUMO-CURVA PREV'!B7,'RESUMO-CURVA GRÁFICO'!$AD$4:$AD$261) -> 1 | I7: =SUMIF('RESUMO-CURVA GRÁFICO'!$B$4:$B$261,'RESUMO-CURVA PREV'!A7,'RESUMO-CURVA GRÁFICO'!$X$4:$X$261) -> 70204 | J7: =SUMIF('RESUMO-CURVA GRÁFICO'!$B$4:$B$261,'RESUMO-CURVA PREV'!B7,'RESUMO-CURVA GRÁFICO'!$AC$4:$AC$261) -> 70204
A8: 196 | B8: 197 | C8: 2.8 | D8: ="MATERIAL DE CONSUMO - ELÉTRICO" -> MATERIAL DE CONSUMO - ELÉTRICO | E8: =I8 -> 83279.41 | F8: =J8 -> 73584.516 | G8: 16 | H8: =SUMIF('RESUMO-CURVA GRÁFICO'!$B$4:$B$261,'RESUMO-CURVA PREV'!B8,'RESUMO-CURVA GRÁFICO'!$AD$4:$AD$261) -> 0.88358595 | I8: =SUMIF('RESUMO-CURVA GRÁFICO'!$B$4:$B$261,'RESUMO-CURVA PREV'!A8,'RESUMO-CURVA GRÁFICO'!$X$4:$X$261) -> 83279.41 | J8: =SUMIF('RESUMO-CURVA GRÁFICO'!$B$4:$B$261,'RESUMO-CURVA PREV'!B8,'RESUMO-CURVA GRÁFICO'!$AC$4:$AC$261) -> 73584.516
A9: 200 | B9: 201 | C9: 2.9 | D9: ="FERRAMENTAS ELÉTRICA" -> FERRAMENTAS ELÉTRICA | E9: =I9 -> 96713.2 | F9: =J9 -> 55670.23 | G9: 15 | H9: =SUMIF('RESUMO-CURVA GRÁFICO'!$B$4:$B$261,'RESUMO-CURVA PREV'!B9,'RESUMO-CURVA GRÁFICO'!$AD$4:$AD$261) -> 0.57562184 | I9: =SUMIF('RESUMO-CURVA GRÁFICO'!$B$4:$B$261,'RESUMO-CURVA PREV'!A9,'RESUMO-CURVA GRÁFICO'!$X$4:$X$261) -> 96713.2 | J9: =SUMIF('RESUMO-CURVA GRÁFICO'!$B$4:$B$261,'RESUMO-CURVA PREV'!B9,'RESUMO-CURVA GRÁFICO'!$AC$4:$AC$261) -> 55670.23
A10: 96 | B10: 97 | C10: 2.2 | D10: ="EQUIPAMENTOS DE INFORMÁTICA" -> EQUIPAMENTOS DE INFORMÁTICA | E10: =I10 -> 138086.16 | F10: =J10 -> 138086.16 | G10: 14 | H10: =SUMIF('RESUMO-CURVA GRÁFICO'!$B$4:$B$261,'RESUMO-CURVA PREV'!B10,'RESUMO-CURVA GRÁFICO'!$AD$4:$AD$261) -> 1 | I10: =SUMIF('RESUMO-CURVA GRÁFICO'!$B$4:$B$261,'RESUMO-CURVA PREV'!A10,'RESUMO-CURVA GRÁFICO'!$X$4:$X$261) -> 138086.16 | J10: =SUMIF('RESUMO-CURVA GRÁFICO'!$B$4:$B$261,'RESUMO-CURVA PREV'!B10,'RESUMO-CURVA GRÁFICO'!$AC$4:$AC$261) -> 138086.16
A11: 216 | B11: 217 | C11: 2.13 | D11: ="MANUTENÇÃO CIVIL - MATERIAIS CONSUMÍVEIS" -> MANUTENÇÃO CIVIL - MATERIAIS CONSUMÍVEIS | E11: =I11 -> 237025.32 | F11: =J11 -> 237025.32 | G11: 13 | H11: =SUMIF('RESUMO-CURVA GRÁFICO'!$B$4:$B$261,'RESUMO-CURVA PREV'!B11,'RESUMO-CURVA GRÁFICO'!$AD$4:$AD$261) -> 1 | I11: =SUMIF('RESUMO-CURVA GRÁFICO'!$B$4:$B$261,'RESUMO-CURVA PREV'!A11,'RESUMO-CURVA GRÁFICO'!$X$4:$X$261) -> 237025.32 | J11: =SUMIF('RESUMO-CURVA GRÁFICO'!$B$4:$B$261,'RESUMO-CURVA PREV'!B11,'RESUMO-CURVA GRÁFICO'!$AC$4:$AC$261) -> 237025.32
A12: 224 | B12: 225 | C12: 2.15 | D12: ="TRANSPORTE DE EQUIPAMENTOS" -> TRANSPORTE DE EQUIPAMENTOS | E12: =I12 -> 270788.7 | F12: =J12 -> 0 | G12: 12 | H12: =SUMIF('RESUMO-CURVA GRÁFICO'!$B$4:$B$261,'RESUMO-CURVA PREV'!B12,'RESUMO-CURVA GRÁFICO'!$AD$4:$AD$261) -> 0 | I12: =SUMIF('RESUMO-CURVA GRÁFICO'!$B$4:$B$261,'RESUMO-CURVA PREV'!A12,'RESUMO-CURVA GRÁFICO'!$X$4:$X$261) -> 270788.7 | J12: =SUMIF('RESUMO-CURVA GRÁFICO'!$B$4:$B$261,'RESUMO-CURVA PREV'!B12,'RESUMO-CURVA GRÁFICO'!$AC$4:$AC$261) -> 0
A13: 253 | B13: 254 | C13: 3 | D13: ="DESPESAS REEMBOLSÁVEIS" -> DESPESAS REEMBOLSÁVEIS | E13: =I13 -> 337157.91 | F13: =J13 -> 290598.39 | G13: 11 | H13: =SUMIF('RESUMO-CURVA GRÁFICO'!$B$4:$B$261,'RESUMO-CURVA PREV'!B13,'RESUMO-CURVA GRÁFICO'!$AD$4:$AD$261) -> 0.86190591 | I13: =SUMIF('RESUMO-CURVA GRÁFICO'!$B$4:$B$261,'RESUMO-CURVA PREV'!A13,'RESUMO-CURVA GRÁFICO'!$X$4:$X$261) -> 337157.91 | J13: =SUMIF('RESUMO-CURVA GRÁFICO'!$B$4:$B$261,'RESUMO-CURVA PREV'!B13,'RESUMO-CURVA GRÁFICO'!$AC$4:$AC$261) -> 290598.39
A14: 84 | B14: 85 | C14: 2.1 | D14: ="VIAGENS" -> VIAGENS | E14: =I14 -> 382021.68 | F14: =J14 -> 95210.78 | G14: 10 | H14: =SUMIF('RESUMO-CURVA GRÁFICO'!$B$4:$B$261,'RESUMO-CURVA PREV'!B14,'RESUMO-CURVA GRÁFICO'!$AD$4:$AD$261) -> 0.24922873 | I14: =SUMIF('RESUMO-CURVA GRÁFICO'!$B$4:$B$261,'RESUMO-CURVA PREV'!A14,'RESUMO-CURVA GRÁFICO'!$X$4:$X$261) -> 382021.68 | J14: =SUMIF('RESUMO-CURVA GRÁFICO'!$B$4:$B$261,'RESUMO-CURVA PREV'!B14,'RESUMO-CURVA GRÁFICO'!$AC$4:$AC$261) -> 95210.78
A15: 204 | B15: 205 | C15: 2.10 | D15: ="SOBRESSALENTES - ELÉTRICA" -> SOBRESSALENTES - ELÉTRICA | E15: =I15 -> 426502.25 | F15: =J15 -> 155801.5 | G15: 9 | H15: =SUMIF('RESUMO-CURVA GRÁFICO'!$B$4:$B$261,'RESUMO-CURVA PREV'!B15,'RESUMO-CURVA GRÁFICO'!$AD$4:$AD$261) -> 0.36530053 | I15: =SUMIF('RESUMO-CURVA GRÁFICO'!$B$4:$B$261,'RESUMO-CURVA PREV'!A15,'RESUMO-CURVA GRÁFICO'!$X$4:$X$261) -> 426502.25 | J15: =SUMIF('RESUMO-CURVA GRÁFICO'!$B$4:$B$261,'RESUMO-CURVA PREV'!B15,'RESUMO-CURVA GRÁFICO'!$AC$4:$AC$261) -> 155801.5
A16: 208 | B16: 209 | C16: 2.11 | D16: ="SOBRESSALENTES - LINHA DE TRANSMISSÃO" -> SOBRESSALENTES - LINHA DE TRANSMISSÃO | E16: =I16 -> 469086.46 | F16: =J16 -> 5393.04 | G16: 8 | H16: =SUMIF('RESUMO-CURVA GRÁFICO'!$B$4:$B$261,'RESUMO-CURVA PREV'!B16,'RESUMO-CURVA GRÁFICO'!$AD$4:$AD$261) -> 0.0114969 | I16: =SUMIF('RESUMO-CURVA GRÁFICO'!$B$4:$B$261,'RESUMO-CURVA PREV'!A16,'RESUMO-CURVA GRÁFICO'!$X$4:$X$261) -> 469086.46 | J16: =SUMIF('RESUMO-CURVA GRÁFICO'!$B$4:$B$261,'RESUMO-CURVA PREV'!B16,'RESUMO-CURVA GRÁFICO'!$AC$4:$AC$261) -> 5393.04
A17: 126 | B17: 127 | C17: 2.4 | D17: ="ESCRITÓRIO" -> ESCRITÓRIO | E17: =I17 -> 518209.68 | F17: =J17 -> 518209.68 | G17: 7 | H17: =SUMIF('RESUMO-CURVA GRÁFICO'!$B$4:$B$261,'RESUMO-CURVA PREV'!B17,'RESUMO-CURVA GRÁFICO'!$AD$4:$AD$261) -> 1 | I17: =SUMIF('RESUMO-CURVA GRÁFICO'!$B$4:$B$261,'RESUMO-CURVA PREV'!A17,'RESUMO-CURVA GRÁFICO'!$X$4:$X$261) -> 518209.68 | J17: =SUMIF('RESUMO-CURVA GRÁFICO'!$B$4:$B$261,'RESUMO-CURVA PREV'!B17,'RESUMO-CURVA GRÁFICO'!$AC$4:$AC$261) -> 518209.68
A18: 142 | B18: 143 | C18: 2.5 | D18: ="SISTEMA DE RÁDIO COMUNICAÇÃO" -> SISTEMA DE RÁDIO COMUNICAÇÃO | E18: =I18 -> 528013.08 | F18: =J18 -> 492055.56 | G18: 6 | H18: =SUMIF('RESUMO-CURVA GRÁFICO'!$B$4:$B$261,'RESUMO-CURVA PREV'!B18,'RESUMO-CURVA GRÁFICO'!$AD$4:$AD$261) -> 0.93190032 | I18: =SUMIF('RESUMO-CURVA GRÁFICO'!$B$4:$B$261,'RESUMO-CURVA PREV'!A18,'RESUMO-CURVA GRÁFICO'!$X$4:$X$261) -> 528013.08 | J18: =SUMIF('RESUMO-CURVA GRÁFICO'!$B$4:$B$261,'RESUMO-CURVA PREV'!B18,'RESUMO-CURVA GRÁFICO'!$AC$4:$AC$261) -> 492055.56
A19: 158 | B19: 159 | C19: 2.6 | D19: ="INSTALAÇÃO DA EQUIPE" -> INSTALAÇÃO DA EQUIPE | E19: =I19 -> 685215 | F19: =J19 -> 685214.34 | G19: 5 | H19: =SUMIF('RESUMO-CURVA GRÁFICO'!$B$4:$B$261,'RESUMO-CURVA PREV'!B19,'RESUMO-CURVA GRÁFICO'!$AD$4:$AD$261) -> 0.99999905 | I19: =SUMIF('RESUMO-CURVA GRÁFICO'!$B$4:$B$261,'RESUMO-CURVA PREV'!A19,'RESUMO-CURVA GRÁFICO'!$X$4:$X$261) -> 685215 | J19: =SUMIF('RESUMO-CURVA GRÁFICO'!$B$4:$B$261,'RESUMO-CURVA PREV'!B19,'RESUMO-CURVA GRÁFICO'!$AC$4:$AC$261) -> 685214.34
A20: 166 | B20: 167 | C20: 2.7 | D20: ="EQUIPAMENTOS PARA MANUTENÇÃO ELÉTRICA" -> EQUIPAMENTOS PARA MANUTENÇÃO ELÉTRICA | E20: =I20 -> 4591811.1 | F20: =J20 -> 4591811.1 | G20: 4 | H20: =SUMIF('RESUMO-CURVA GRÁFICO'!$B$4:$B$261,'RESUMO-CURVA PREV'!B20,'RESUMO-CURVA GRÁFICO'!$AD$4:$AD$261) -> 1 | I20: =SUMIF('RESUMO-CURVA GRÁFICO'!$B$4:$B$261,'RESUMO-CURVA PREV'!A20,'RESUMO-CURVA GRÁFICO'!$X$4:$X$261) -> 4591811.1 | J20: =SUMIF('RESUMO-CURVA GRÁFICO'!$B$4:$B$261,'RESUMO-CURVA PREV'!B20,'RESUMO-CURVA GRÁFICO'!$AC$4:$AC$261) -> 4591811.1
A21: 112 | B21: 113 | C21: 2.3 | D21: ="VEÍCULOS, COMBUSTÍVEL E MANUTENÇÃO" -> VEÍCULOS, COMBUSTÍVEL E MANUTENÇÃO | E21: =I21 -> 3783418.9 | F21: =J21 -> 3720309.9 | G21: 3 | H21: =SUMIF('RESUMO-CURVA GRÁFICO'!$B$4:$B$261,'RESUMO-CURVA PREV'!B21,'RESUMO-CURVA GRÁFICO'!$AD$4:$AD$261) -> 0.98331958 | I21: =SUMIF('RESUMO-CURVA GRÁFICO'!$B$4:$B$261,'RESUMO-CURVA PREV'!A21,'RESUMO-CURVA GRÁFICO'!$X$4:$X$261) -> 3783418.9 | J21: =SUMIF('RESUMO-CURVA GRÁFICO'!$B$4:$B$261,'RESUMO-CURVA PREV'!B21,'RESUMO-CURVA GRÁFICO'!$AC$4:$AC$261) -> 3720309.9
A22: 78 | B22: 79 | C22: 1 | D22: ="RESUMO DA MÃO DE OBRA" -> RESUMO DA MÃO DE OBRA | E22: =I22 -> 18310884 | F22: =J22 -> 16541555 | G22: 1 | H22: =SUMIF('RESUMO-CURVA GRÁFICO'!$B$4:$B$261,'RESUMO-CURVA PREV'!B22,'RESUMO-CURVA GRÁFICO'!$AD$4:$AD$261) -> 0.90337283 | I22: =SUMIF('RESUMO-CURVA GRÁFICO'!$B$4:$B$261,'RESUMO-CURVA PREV'!A22,'RESUMO-CURVA GRÁFICO'!$X$4:$X$261) -> 18310884 | J22: =SUMIF('RESUMO-CURVA GRÁFICO'!$B$4:$B$261,'RESUMO-CURVA PREV'!B22,'RESUMO-CURVA GRÁFICO'!$AC$4:$AC$261) -> 16541555
A23: 249 | B23: 250 | C23: 2 | D23: ="CUSTOS DIRETOS" -> CUSTOS DIRETOS | E23: =I23 -> 12317953 | F23: =J23 -> 10858667 | G23: 2 | H23: =SUMIF('RESUMO-CURVA GRÁFICO'!$B$4:$B$261,'RESUMO-CURVA PREV'!B23,'RESUMO-CURVA GRÁFICO'!$AD$4:$AD$261) -> 0.88153181 | I23: =SUMIF('RESUMO-CURVA GRÁFICO'!$B$4:$B$261,'RESUMO-CURVA PREV'!A23,'RESUMO-CURVA GRÁFICO'!$X$4:$X$261) -> 12317953 | J23: =SUMIF('RESUMO-CURVA GRÁFICO'!$B$4:$B$261,'RESUMO-CURVA PREV'!B23,'RESUMO-CURVA GRÁFICO'!$AC$4:$AC$261) -> 10858667
E24: =SUM(E4:E12,E14:E21,E22,E13) -> 30965995 | F24: =SUM(F4:F12,F14:F21,F22,F13) -> 27690821 | H24: =F24/E24 -> 0.89423321 | I24: =SUM(I4:I12,I14:I21,I22,I13) -> 30965995 | J24: =SUM(J4:J12,J14:J21,J22,J13) -> 27690821
E25: =E24-I24 -> 0 | F25: =F24-J24 -> 0 | I25: =I24-'Evolução Mensal'!AR12 -> 7.3425472e-06 | J25: =J24-'Evolução Mensal'!AR13 -> 11801040

Sheet GRÁFICO

Sheet Evolução Mensal
AD2: EVOLUÇÃO MENSAL DO CONTRATO POR TIPO DE DESPESA
AD3: 2025 / 2026
E4: 1 | F4: 2 | G4: 3 | H4: 4 | I4: 5 | J4: 6 | K4: 7 | L4: 8 | M4: 9 | N4: 10 | O4: 11 | P4: 12 | Q4: 24.1 | R4: 25 | S4: 26 | T4: 27 | U4: 28 | V4: 29 | W4: 30 | X4: 31 | Y4: 32 | Z4: 33 | AA4: 34 | AB4: 35 | AC4: 36 | AD4: 36.1 | AE4: 37 | AF4: 38 | AG4: 39 | AH4: 40 | AI4: 41 | AJ4: 42 | AK4: 43 | AL4: 44 | AM4: 45 | AN4: 46 | AO4: 47 | AP4: 48 | AQ4: 49
B5: ITEM | E5: 44774 | F5: 44805 | G5: 44835 | H5: 44866 | I5: 44896 | J5: 44927 | K5: 44958 | L5: 44986 | M5: 45017 | N5: 45047 | O5: 45078 | P5: 45108 | Q5: 45474 | R5: 45505 | S5: 45536 | T5: 45566 | U5: 45597 | V5: 45627 | W5: 45658 | X5: 45689 | Y5: 45717 | Z5: 45748 | AA5: 45778 | AB5: 45809 | AC5: 45839 | AD5: 45839 | AE5: 45870 | AF5: 45901 | AG5: 45931 | AH5: 45962 | AI5: 45992 | AJ5: 46023 | AK5: 46054 | AL5: 46082 | AM5: 46113 | AN5: 46143 | AO5: 46174 | AP5: 46204 | AQ5: 46235
B6: MÃO DE OBRA | C6: P | D6: PREVISTO | E6: 1037503.2 | F6: 1556254.8 | G6: 1556254.8 | H6: 1556254.8 | I6: 1556254.8 | J6: 1556254.8 | K6: 1556254.8 | L6: 1556254.8 | M6: 1556254.8 | N6: 1556254.8 | O6: 1556254.8 | P6: =1556254.78727273/30*10 -> 518751.6 | Q6: 1269132.2 | R6: 1586415.3 | S6: 1586415.3 | T6: 1586415.3 | U6: =$AO6 -> 1525907 | V6: 1586415.3 | W6: 1586415.3 | X6: 1586415.3 | Y6: 1586415.3 | Z6: 1586415.3 | AA6: 1586415.3 | AB6: 1586415.3 | AC6: 317283.06 | AD6: 1220725.6 | AE6: 1525907 | AF6: =$AT6 -> 1525907 | AG6: 1525907 | AH6: 1525907 | AI6: 1525907 | AJ6: 1525907 | AK6: =$AT6 -> 1525907 | AL6: =$AT6 -> 1525907 | AM6: =$AT6 -> 1525907 | AN6: =$AT6 -> 1525907 | AO6: =$AT6 -> 1525907 | AP6: =$AU$6 -> 305181.4 | AR6: =SUM(AD6:AP6) -> 18310884 | AS6: 18310884 | AT6: =AS6/12 -> 1525907 | AU6: =AT6/30*6 -> 305181.4 | AV6: =AT6/30*24 -> 1220725.6 | AW6: =SUM(AU6:AV6) -> 1525907
C7: R | D7: REALIZADO | E7: 46913.72 | F7: 406924.85 | G7: 463411.74 | H7: 529425.99 | I7: 549858.83 | J7: 595088.38 | K7: 1199430.9 | L7: 1362135.9 | M7: 1460872.3 | N7: 1319827.1 | O7: 1270484.2 | P7: ='[1]Preços e Quantidades'!$G$152 -> 1432552.8 | Q7: 996036.25 | R7: 1250732.7 | S7: 1280533.1 | T7: 1282102 | U7: 1283823.9 | V7: 1213630.5 | W7: 1231114.9 | X7: 1290820.6 | Y7: 1233378.5 | Z7: 1246962.9 | AA7: 1351334.4 | AB7: 1290728 | AC7: 274952.27 | AD7: 1036060.1 | AE7: 1403557.9 | AF7: ='[1]Preços e Quantidades'!$G$152 -> 1432552.8 | AG7: 1439360.9 | AH7: 1411640.5 | AI7: 1361814.4 | AJ7: 1322567.1 | AR7: =SUM(AD7:AP7) -> 9407553.8
B8: CUSTO DIRETO | C8: P | D8: PREVISTO | E8: 489032.69 | F8: 733549.04 | G8: 733549.04 | H8: 733549.04 | I8: 733549.04 | J8: 733549.04 | K8: 733549.04 | L8: 733549.04 | M8: 733549.04 | N8: 733549.04 | O8: 733549.04 | P8: =733549.038763636/30*10 -> 244516.35 | Q8: 755607.11 | R8: 944508.88 | S8: 944508.88 | T8: 944508.88 | U8: 944508.88 | V8: 944508.88 | W8: 944508.88 | X8: 944508.88 | Y8: 944508.88 | Z8: 944508.88 | AA8: 944508.88 | AB8: 944508.88 | AC8: 188901.78 | AD8: 821196.85 | AE8: 1026496.1 | AF8: =$AT8 -> 1026496.1 | AG8: 1026496.1 | AH8: 1026496.1 | AI8: 1026496.1 | AJ8: 1026496.1 | AK8: =$AT8 -> 1026496.1 | AL8: =$AT8 -> 1026496.1 | AM8: =$AT8 -> 1026496.1 | AN8: =$AT8 -> 1026496.1 | AO8: =$AT8 -> 1026496.1 | AP8: =$AU$8 -> 205299.21 | AR8: =SUM(AD8:AP8) -> 12317953 | AS8: 12317953 | AT8: =AS8/12 -> 1026496.1 | AU8: =AT8/30*6 -> 205299.21 | AV8: =AT8/30*24 -> 821196.85 | AW8: =SUM(AU8:AV8) -> 1026496.1
C9: R | D9: REALIZADO | E9: 116828.3 | F9: 201832.13 | G9: 228734.68 | H9: 227639.39 | I9: 230252.11 | J9: 237781.55 | K9: 330763.36 | L9: 369581.69 | M9: 396822.38 | N9: 407746.22 | O9: 406407.33 | P9: ='[1]Preços e Quantidades'!$G$153 -> 907395.95 | Q9: 613563.97 | R9: 758419.44 | S9: 873330.12 | T9: 796004.1 | U9: 802132.21 | V9: 792488.11 | W9: 817526.81 | X9: 810848.35 | Y9: 789206.22 | Z9: 793343.79 | AA9: 798539.9 | AB9: 836013.31 | AC9: 161912.89 | AD9: 720189.1 | AE9: 970056.98 | AF9: ='[1]Preços e Quantidades'!$G$153 -> 907395.95 | AG9: 994206.55 | AH9: 898971.07 | AI9: 919039.37 | AJ9: 902852.48 | AR9: =SUM(AD9:AP9) -> 6312711.5
B10: DESPESAS REEMBOLSÁVEIS | C10: P | D10: PREVISTO | E10: 20433.813 | F10: 30650.719 | G10: 30650.719 | H10: 30650.719 | I10: 30650.719 | J10: 30650.719 | K10: 30650.719 | L10: 30650.719 | M10: 30650.719 | N10: 30650.719 | O10: 30650.719 | P10: =30650.7190909091/30*10 -> 10216.906 | Q10: 22477.194 | R10: 28096.493 | S10: 28096.493 | T10: 28096.493 | U10: 28096.493 | V10: 28096.493 | W10: 28096.493 | X10: 28096.493 | Y10: 28096.493 | Z10: 28096.493 | AA10: 28096.493 | AB10: 28096.493 | AC10: 5619.2985 | AD10: 22477.194 | AE10: 28096.493 | AF10: =$AT10 -> 28096.493 | AG10: 28096.493 | AH10: 28096.493 | AI10: 28096.493 | AJ10: 28096.493 | AK10: =$AT10 -> 28096.493 | AL10: =$AT10 -> 28096.493 | AM10: =$AT10 -> 28096.493 | AN10: =$AT10 -> 28096.493 | AO10: =$AT10 -> 28096.493 | AP10: =$AU$10 -> 5619.2985 | AR10: =SUM(AD10:AP10) -> 337157.91 | AS10: 337157.91 | AT10: =AS10/12 -> 28096.493 | AU10: =AT10/30*6 -> 5619.2985 | AV10: =AT10/30*24 -> 22477.194 | AW10: =SUM(AU10:AV10) -> 28096.493
C11: R | D11: REALIZADO | E11: 0 | F11: 0 | G11: 0 | H11: 0 | I11: 3713.87 | J11: 62182.99 | K11: 2726.21 | L11: 14037.6 | M11: 96542.9 | N11: 604 | O11: 66515.35 | P11: ='[1]Preços e Quantidades'!$G$154 -> 78759.74 | Q11: 800 | R11: 0 | S11: 48628.64 | T11: 112440 | U11: 138841.77 | V11: 0 | W11: 0 | X11: 0 | Y11: 8366.53 | Z11: 14783.48 | AA11: 7150 | AB11: 6068.25 | AC11: 0 | AD11: 0 | AE11: 0 | AF11: ='[1]Preços e Quantidades'!$G$154 -> 78759.74 | AG11: 6211.55 | AH11: 38256.14 | AI11: 38488.3 | AJ11: 7800 | AR11: =SUM(AD11:AP11) -> 169515.73
B12: TOTAL MENSAL | C12: P | D12: PREVISTO | E12: =SUM(E10,E8,E6) -> 1546969.7 | F12: =SUM(F10,F8,F6) -> 2320454.5 | G12: =SUM(G10,G8,G6) -> 2320454.5 | H12: =SUM(H10,H8,H6) -> 2320454.5 | I12: =SUM(I10,I8,I6) -> 2320454.5 | J12: =SUM(J10,J8,J6) -> 2320454.5 | K12: =SUM(K10,K8,K6) -> 2320454.5 | L12: =SUM(L10,L8,L6) -> 2320454.5 | ... AP12: =SUM(AP10,AP8,AP6) -> 516099.91 | AR12: =SUM(AD12:AP12) -> 30965995
C13: R | D13: REALIZADO | E13: =SUM(E11,E9,E7) -> 163742.02 | F13: =SUM(F11,F9,F7) -> 608756.98 | G13: =SUM(G11,G9,G7) -> 692146.42 | H13: =SUM(H11,H9,H7) -> 757065.38 | I13: =SUM(I11,I9,I7) -> 783824.8 | J13: =SUM(J11,J9,J7) -> 895052.92 | K13: =SUM(K11,K9,K7) -> 1532920.5 | L13: =SUM(L11,L9,L7) -> 1745755.2 | ... AP13: =SUM(AP11,AP9,AP7) -> 0 | AR13: =SUM(AD13:AP13) -> 15889781
B14: TOTAL ACUMULADO | C14: P | D14: PREVISTO | E14: =SUM(E10,E8,E6) -> 1546969.7 | F14: =SUM(F10,F8,F6)+E14 -> 3867424.2 | G14: =SUM(G10,G8,G6)+F14 -> 6187878.8 | H14: =SUM(H10,H8,H6)+G14 -> 8508333.3 | I14: =SUM(I10,I8,I6)+H14 -> 10828788 | J14: =SUM(J10,J8,J6)+I14 -> 13149242 | K14: =SUM(K10,K8,K6)+J14 -> 15469697 | L14: =SUM(L10,L8,L6)+K14 -> 17790152 | M14: =SUM(M10,M8,M6)+L14 -> 20110606 | ... P14: =SUM(P10,P8,P6)+O14 -> 25525000 | Q14: =SUM(Q10,Q8,Q6) -> 2047216.5 | R14: =SUM(R10,R8,R6)+Q14 -> 4606237.2 | S14: =SUM(S10,S8,S6)+R14 -> 7165257.9 | T14: =SUM(T10,T8,T6)+S14 -> 9724278.5 | U14: =SUM(U10,U8,U6)+T14 -> 12222791 | V14: =SUM(V10,V8,V6)+U14 -> 14781812 | W14: =SUM(W10,W8,W6)+V14 -> 17340832 | X14: =SUM(X10,X8,X6)+W14 -> 19899853 | Y14: =SUM(Y10,Y8,Y6)+X14 -> 22458874 | ... AC14: =SUM(AC10,AC8,AC6)+AB14 -> 30647740 | AD14: =SUM(AD10,AD8,AD6) -> 2064399.6 | AE14: =SUM(AE10,AE8,AE6)+AD14 -> 4644899.2 | AF14: =SUM(AF10,AF8,AF6)+AE14 -> 7225398.8 | AG14: =SUM(AG10,AG8,AG6)+AF14 -> 9805898.3 | AH14: =SUM(AH10,AH8,AH6)+AG14 -> 12386398 | AI14: =SUM(AI10,AI8,AI6)+AH14 -> 14966897 | AJ14: =SUM(AJ10,AJ8,AJ6)+AI14 -> 17547397 | AK14: =SUM(AK10,AK8,AK6)+AJ14 -> 20127897 | AL14: =SUM(AL10,AL8,AL6)+AK14 -> 22708396 | ... AP14: =SUM(AP10,AP8,AP6)+AO14 -> 30965995
C15: R | D15: REALIZADO | E15: =SUM(E11,E9,E7) -> 163742.02 | F15: =E15+F13 -> 772499 | G15: =F15+G13 -> 1464645.4 | H15: =G15+H13 -> 2221710.8 | I15: =H15+I13 -> 3005535.6 | J15: =I15+J13 -> 3900588.5 | K15: =J15+K13 -> 5433509 | L15: =K15+L13 -> 7179264.1 | M15: =L15+M13 -> 9133501.7 | ... P15: =O15+P13 -> 15023794 | Q15: =Q13 -> 1610400.2 | R15: =Q15+R13 -> 3619552.4 | S15: =R15+S13 -> 5822044.3 | T15: =S15+T13 -> 8012590.3 | U15: =T15+U13 -> 10237388 | V15: =U15+V13 -> 12243507 | W15: =V15+W13 -> 14292149 | X15: =W15+X13 -> 16393817 | Y15: =X15+Y13 -> 18424769 | ... AC15: =AB15+AC13 -> 25206558 | AD15: =AD13 -> 1756249.2 | AE15: =AD15+AE13 -> 4129864.1 | AF15: =AE15+AF13 -> 6548572.6 | AG15: =AF15+AG13 -> 8988351.6 | AH15: =AG15+AH13 -> 11337219 | AI15: =AH15+AI13 -> 13656561 | AJ15: =AI15+AJ13 -> 15889781
R48: Previsto Mensal | U48: Realizado Mensal | X48: Previsto Acumulado | AB48: Realizado Acumulado
U53: 10178229
U54: =U53-V15 -> -2065277.8

Sheet RESUMO-CURVA GRÁFICO
D1: PLANILHA REFERENCIAL DE PREÇOS - RESUMO (COM DESONERAÇÃO) | Z1: NÃO MEDIDOS
D2: Item | E2: Descrição | F2: Classe | H2: % | I2: Meses | V2: Quantidade | W2: Preço Unitário | X2: Preço Total | Y2: PERCENTUAL MEDIDO | Z2: =SUM(Z5:Z258) -> 3228614.5 | AB2: Média Mensal | AC2: Projeção R$ | AD2: Projeção %
I3: 36.1 | J3: 37 | K3: 38 | L3: 39 | M3: 40 | N3: 41 | O3: 42 | P3: 43 | Q3: 44 | R3: 45 | S3: 46 | T3: 47 | U3: 48 | AB3: x 12 meses | AC3: 12 meses | AD3: 12 meses
I4: jul | J4: ago | K4: set | L4: out | M4: nov | N4: dez | O4: jan | P4: fev | Q4: mar | R4: abr | S4: mai | T4: jun | U4: jul
B5: 1 | C5: PREV | D5: 1 | E5: RESUMO DA MÃO DE OBRA | Y5: =Y6 -> 0.51376841
B6: 2 | C6: REAL | D6: 1 | E6: RESUMO DA MÃO DE OBRA | Y6: =Y83 -> 0.51376841 | AC6: =SUM(AC8:AC80) -> 16541555 | AD6: =AC6/X82 -> 0.90337283 | AE6: 1 | AF6: 1 | AG6: 1 | AH6: 1
B7: 3 | C7: PREV | D7: 1.1 | E7: Consultor Especializado | F7: P8060 | G7: =C7&E7 -> PREVConsultor Especializado | H7: =Y7 | I7: 0.4 | J7: 0.5 | K7: 0.5 | L7: 0.5 | M7: 0.5 | N7: 0.5 | O7: 0.5 | P7: 0.5 | Q7: 0.5 | R7: 0.5 | S7: 0.5 | T7: 0.5 | U7: 0.1 | V7: =SUM(I7:U7) -> 6 | W7: 24703.45 | X7: =W7*V7 -> 148220.7 | AL7: Consultor Especializado
B8: 4 | C8: REAL | D8: 1.1 | E8: Consultor Especializado | F8: P8060 | G8: =C8&E8 -> REALConsultor Especializado | H8: =Y8 -> 0 | I8: 0 | J8: 0 | K8: 0 | L8: 0 | M8: 0 | N8: 0 | O8: 0 | V8: =SUM(I8:U8) -> 0 | W8: 24703.45 | X8: =W8*V8 -> 0 | Y8: =X8/X7 -> 0 | Z8: =X7-AC8 -> 148220.7 | AB8: =ROUND((AVERAGE(J8:T8)*12),1) -> 0 | AC8: =IF(AB8*W8>X7,X7,AB8*W8) -> 0 | AD8: =AC8/X7 -> 0 | AL8: Almoxarife
B9: 5 | C9: PREV | D9: 1.2 | E9: Almoxarife | F9: P9803 | G9: =C9&E9 -> PREVAlmoxarife | H9: =Y9 | I9: 1.6 | J9: 2 | K9: 2 | L9: 2 | M9: 2 | N9: 2 | O9: 2 | P9: 2 | Q9: 2 | R9: 2 | S9: 2 | T9: 2 | U9: 0.4 | V9: =SUM(I9:U9) -> 24 | W9: 5580.99 | X9: =W9*V9 -> 133943.76 | AL9: Auxiliar Administrativo
B10: 6 | C10: REAL | D10: 1.2 | E10: Almoxarife | F10: P9803 | G10: =C10&E10 -> REALAlmoxarife | H10: =Y10 -> 0.24166667 | I10: 0.8 | J10: 0.066666667 | K10: 0.93333333 | L10: 1 | M10: 1 | N10: 1 | O10: 1 | V10: =SUM(I10:U10) -> 5.8 | W10: 5580.99 | X10: =W10*V10 -> 32369.742 | Y10: =X10/X9 -> 0.24166667 | Z10: =X9-AC10 -> 78133.86 | AB10: =ROUND((AVERAGE(J10:T10)*12),1) -> 10 | AC10: =IF(AB10*W10>X9,X9,AB10*W10) -> 55809.9 | AD10: =AC10/X9 -> 0.41666667 | AL10: Técnico Administrativo
B11: 7 | C11: PREV | D11: 1.3 | E11: Auxiliar Administrativo | F11: P9806 | G11: =C11&E11 -> PREVAuxiliar Administrativo | H11: =Y11 | I11: 0.8 | J11: 1 | K11: 1 | L11: 1 | M11: 1 | N11: 1 | O11: 1 | P11: 1 | Q11: 1 | R11: 1 | S11: 1 | T11: 1 | U11: 0.2 | V11: =SUM(I11:U11) -> 12 | W11: 4487.35 | X11: =W11*V11 -> 53848.2 | AL11: Técnico Pleno - Encarregado - Com Periculosidade
B12: 8 | C12: REAL | D12: 1.3 | E12: Auxiliar Administrativo | F12: P9806 | G12: =C12&E12 -> REALAuxiliar Administrativo | H12: =Y12 -> 0.56666667 | I12: 0.8 | J12: 1 | K12: 1 | L12: 1 | M12: 1 | N12: 1 | O12: 1 | V12: =SUM(I12:U12) -> 6.8 | W12: 4487.35 | X12: =W12*V12 -> 30513.98 | Y12: =X12/X11 -> 0.56666667 | Z12: =X11-AC12 -> 0 | AB12: =ROUND((AVERAGE(J12:T12)*12),1) -> 12 | AC12: =IF(AB12*W12>X11,X11,AB12*W12) -> 53848.2 | AD12: =AC12/X11 -> 1 | AL12: Engenheiro Pleno - Eletricista - Telecomunicações - Com Periculosidade
B13: 9 | C13: PREV | D13: 1.4 | E13: Técnico Administrativo | F13: P9809 | G13: =C13&E13 -> PREVTécnico Administrativo | H13: =Y13 | I13: 1.6 | J13: 2 | K13: 2 | L13: 2 | M13: 2 | N13: 2 | O13: 2 | P13: 2 | Q13: 2 | R13: 2 | S13: 2 | T13: 2 | U13: 0.4 | V13: =SUM(I13:U13) -> 24 | W13: 7072.06 | X13: =W13*V13 -> 169729.44 | AL13: Engenheiro Sênior - Proteção e Controle / Eletricista - Coord - Com Periculosidade
B14: 10 | C14: REAL | D14: 1.4 | E14: Técnico Administrativo | F14: P9809 | G14: =C14&E14 -> REALTécnico Administrativo | H14: =Y14 -> 0.51388889 | I14: 0.83333333 | J14: 2 | K14: 2 | L14: 2 | M14: 2 | N14: 2 | O14: 1.5 | V14: =SUM(I14:U14) -> 12.333333 | W14: 7072.06 | X14: =W14*V14 -> 87222.073 | Y14: =X14/X13 -> 0.51388889 | Z14: =X13-AC14 -> 7072.06 | AB14: =ROUND((AVERAGE(J14:T14)*12),1) -> 23 | AC14: =IF(AB14*W14>X13,X13,AB14*W14) -> 162657.38 | AD14: =AC14/X13 -> 0.95833333 | AL14: Vigia (12X36) - Diurno
B15: 11 | C15: PREV | D15: 1.5 | E15: Técnico Pleno - Encarregado - Com Periculosidade | F15: P9811 (*) | G15: =C15&E15 -> PREVTécnico Pleno - Encarregado - Com Periculosidade | H15: =Y15 | I15: 3.2 | J15: 4 | K15: 4 | L15: 4 | M15: 4 | N15: 4 | O15: 4 | P15: 4 | Q15: 4 | R15: 4 | S15: 4 | T15: 4 | U15: 0.8 | V15: =SUM(I15:U15) -> 48 | W15: 7821.94 | X15: =W15*V15 -> 375453.12 | AL15: Vigia (12x36) - Noturno
B16: 12 | C16: REAL | D16: 1.5 | E16: Técnico Pleno - Encarregado - Com Periculosidade | F16: P9811 (*) | G16: =C16&E16 -> REALTécnico Pleno - Encarregado - Com Periculosidade | H16: =Y16 -> 0.63402778 | I16: 4 | J16: 5 | K16: 5 | L16: 3.9666667 | M16: 4.5333333 | N16: 3.9666667 | O16: 3.9666667 | V16: =SUM(I16:U16) -> 30.433333 | W16: 7821.94 | X16: =W16*V16 -> 238047.71 | Y16: =X16/X15 -> 0.63402778 | Z16: =X15-AC16 -> 0 | AB16: =ROUND((AVERAGE(J16:T16)*12),1) -> 52.9 | AC16: =IF(AB16*W16>X15,X15,AB16*W16) -> 375453.12 | AD16: =AC16/X15 -> 1 | AL16: Eletromecânico - Montador - Com Periculosidade
B17: 13 | C17: PREV | D17: 1.6 | E17: Engenheiro Pleno - Eletricista - Telecomunicações - Com Periculosidade | F17: P9812 (*) | G17: =C17&E17 -> PREVEngenheiro Pleno - Eletricista - Telecomunicações - Com Periculosidade | H17: =Y17 | I17: 1.6 | J17: 2 | K17: 2 | L17: 2 | M17: 2 | N17: 2 | O17: 2 | P17: 2 | Q17: 2 | R17: 2 | S17: 2 | T17: 2 | U17: 0.4 | V17: =SUM(I17:U17) -> 24 | W17: 27055.66 | X17: =W17*V17 -> 649335.84 | AL17: Médico
B18: 14 | C18: REAL | D18: 1.6 | E18: Engenheiro Pleno - Eletricista - Telecomunicações - Com Periculosidade | F18: P9812 (*) | G18: =C18&E18 -> REALEngenheiro Pleno - Eletricista - Telecomunicações - Com Periculosidade | H18: =Y18 -> 0.53055556 | I18: 1.1333333 | J18: 2 | K18: 2 | L18: 2 | M18: 2 | N18: 2 | O18: 1.6 | V18: =SUM(I18:U18) -> 12.733333 | W18: 27055.66 | X18: =W18*V18 -> 344508.74 | Y18: =X18/X17 -> 0.53055556 | Z18: =X17-AC18 -> 21644.528 | AB18: =ROUND((AVERAGE(J18:T18)*12),1) -> 23.2 | AC18: =IF(AB18*W18>X17,X17,AB18*W18) -> 627691.31 | AD18: =AC18/X17 -> 0.96666667 | AL18: Engenheiro Pleno - Segurança do Trabalho
B19: 15 | C19: PREV | D19: 1.8 | E19: Engenheiro Sênior - Proteção e Controle / Eletricista - Coord - Com Periculosidade | F19: P9819 (*) | G19: =C19&E19 -> PREVEngenheiro Sênior - Proteção e Controle / Eletricista - Coord - Com Periculosidade | H19: =Y19 | I19: 4 | J19: 5 | K19: 5 | L19: 5 | M19: 5 | N19: 5 | O19: 5 | P19: 5 | Q19: 5 | R19: 5 | S19: 5 | T19: 5 | U19: 1 | V19: =SUM(I19:U19) -> 60 | W19: 27055.66 | X19: =W19*V19 -> 1623339.6 | AL19: Técnico Sênior - TI / Eletrotécnico (12X36) - Diurno
B20: 16 | C20: REAL | D20: 1.8 | E20: Engenheiro Sênior - Proteção e Controle / Eletricista - Coord - Com Periculosidade | F20: P9819 (*) | G20: =C20&E20 -> REALEngenheiro Sênior - Proteção e Controle / Eletricista - Coord - Com Periculosidade | H20: =Y20 -> 0.47847233 | I20: 2.4 | J20: 4.3666667 | K20: 4.7683346 | L20: 4.7683346 | M20: 4.4683346 | N20: 4.5683346 | O20: 3.3683346 | V20: =SUM(I20:U20) -> 28.70834 | W20: 27055.66 | X20: =W20*V20 -> 776723.07 | Y20: =X20/X19 -> 0.47847233 | Z20: =X19-AC20 -> 200211.88 | AB20: =ROUND((AVERAGE(J20:T20)*12),1) -> 52.6 | AC20: =IF(AB20*W20>X19,X19,AB20*W20) -> 1423127.7 | AD20: =AC20/X19 -> 0.87666667 | AL20: Técnico Sênior - Eletrotécnico / Operador de Subest (12X36) - Diurno / Técnico Pleno - Eletromecânico/ Telecomunicações / Eletrotécnico / Eletrônico - Com Periculosidade
B21: 17 | C21: PREV | D21: 1.9 | E21: Vigia (12X36) - Diurno | F21: P9827 | G21: =C21&E21 -> PREVVigia (12X36) - Diurno | H21: =Y21 | I21: 9.6 | J21: 12 | K21: 12 | L21: 12 | M21: 12 | N21: 12 | O21: 12 | P21: 12 | Q21: 12 | R21: 12 | S21: 12 | T21: 12 | U21: 2.4 | V21: =SUM(I21:U21) -> 144 | W21: 4015.53 | X21: =W21*V21 -> 578236.32 | AL21: Técnico Sênior - Eletrotécnico - Noturno / Técnico Pleno - Operador de Subest (12X36) - Noturno
B22: 18 | C22: REAL | D22: 1.9 | E22: Vigia (12X36) - Diurno | F22: P9827 | G22: =C22&E22 -> REALVigia (12X36) - Diurno | H22: =Y22 -> 0.39583333 | I22: 8 | J22: 9 | K22: 8 | L22: 8 | M22: 7.3666667 | N22: 7.7 | O22: 8.9333333 | V22: =SUM(I22:U22) -> 57 | W22: 4015.53 | X22: =W22*V22 -> 228885.21 | Y22: =X22/X21 -> 0.39583333 | Z22: =X21-AC22 -> 184714.38 | AB22: =ROUND((AVERAGE(J22:T22)*12),1) -> 98 | AC22: =IF(AB22*W22>X21,X21,AB22*W22) -> 393521.94 | AD22: =AC22/X21 -> 0.68055556 | AL22: Técnico Sênior - Segurança
B23: 19 | C23: PREV | D23: 1.10 | E23: Vigia (12x36) - Noturno | F23: P9827N | G23: =C23&E23 -> PREVVigia (12x36) - Noturno | H23: =Y23 | I23: 9.6 | J23: 12 | K23: 12 | L23: 12 | M23: 12 | N23: 12 | O23: 12 | P23: 12 | Q23: 12 | R23: 12 | S23: 12 | T23: 12 | U23: 2.4 | V23: =SUM(I23:U23) -> 144 | W23: 5965.92 | X23: =W23*V23 -> 859092.48 | AL23: Secretária
B24: 20 | C24: REAL | D24: 1.10 | E24: Vigia (12x36) - Noturno | F24: P9827N | G24: =C24&E24 -> REALVigia (12x36) - Noturno | H24: =Y24 -> 0.52407407 | I24: 8 | J24: 11 | K24: 12 | L24: 12 | M24: 11.066667 | N24: 11 | O24: 10.4 | V24: =SUM(I24:U24) -> 75.466667 | W24: 5965.92 | X24: =W24*V24 -> 450228.1 | Y24: =X24/X23 -> 0.52407407 | Z24: =X23-AC24 -> 54289.872 | AB24: =ROUND((AVERAGE(J24:T24)*12),1) -> 134.9 | AC24: =IF(AB24*W24>X23,X23,AB24*W24) -> 804802.61 | AD24: =AC24/X23 -> 0.93680556 | AL24: Chefe de Escritório
B25: 21 | C25: PREV | D25: 1.11 | E25: Eletromecânico - Montador - Com Periculosidade | F25: P9830 (*) | G25: =C25&E25 -> PREVEletromecânico - Montador - Com Periculosidade | H25: =Y25 | I25: 6.4 | J25: 8 | K25: 8 | L25: 8 | M25: 8 | N25: 8 | O25: 8 | P25: 8 | Q25: 8 | R25: 8 | S25: 8 | T25: 8 | U25: 1.6 | V25: =SUM(I25:U25) -> 96 | W25: 8508.7 | X25: =W25*V25 -> 816835.2 | AL25: Comprador
B26: 22 | C26: REAL | D26: 1.11 | E26: Eletromecânico - Montador - Com Periculosidade | F26: P9830 (*) | G26: =C26&E26 -> REALEletromecânico - Montador - Com Periculosidade | H26: =Y26 -> 0.44895833 | I26: 4.5 | J26: 5.6 | K26: 7 | L26: 6.5 | M26: 7 | N26: 6.4333333 | O26: 6.0666667 | V26: =SUM(I26:U26) -> 43.1 | W26: 8508.7 | X26: =W26*V26 -> 366724.97 | Y26: =X26/X25 -> 0.44895833 | Z26: =X25-AC26 -> 159963.56 | AB26: =ROUND((AVERAGE(J26:T26)*12),1) -> 77.2 | AC26: =IF(AB26*W26>X25,X25,AB26*W26) -> 656871.64 | AD26: =AC26/X25 -> 0.80416667 | AL26: Eletricista - Com Periculosidade
B27: 23 | C27: PREV | D27: 1.12 | E27: Médico | F27: P9851 | G27: =C27&E27 -> PREVMédico | H27: =Y27 | I27: 0.8 | J27: 1 | K27: 1 | L27: 1 | M27: 1 | N27: 1 | O27: 1 | P27: 1 | Q27: 1 | R27: 1 | S27: 1 | T27: 1 | U27: 0.2 | V27: =SUM(I27:U27) -> 12 | W27: 19815.81 | X27: =W27*V27 -> 237789.72 | AL27: Engenheiro Júnior - Eletricista - Com Periculosidade
B28: 24 | C28: REAL | D28: 1.12 | E28: Médico | F28: P9851 | G28: =C28&E28 -> REALMédico | H28: =Y28 -> 0.4067211 | I28: 0.49823106 | J28: 0.62278882 | K28: 0.75192666 | L28: 0.75192666 | M28: 0.75192666 | N28: 0.75192666 | O28: 0.75192666 | V28: =SUM(I28:U28) -> 4.8806532 | W28: 19815.81 | X28: =W28*V28 -> 96714.096 | Y28: =X28/X27 -> 0.4067211 | Z28: =X27-AC28 -> 63410.592 | AB28: =ROUND((AVERAGE(J28:T28)*12),1) -> 8.8 | AC28: =IF(AB28*W28>X27,X27,AB28*W28) -> 174379.13 | AD28: =AC28/X27 -> 0.73333333 | AL28: Motorista
B29: 25 | C29: PREV | D29: 1.13 | E29: Engenheiro Pleno - Segurança do Trabalho | F29: P9864 (*) | G29: =C29&E29 -> PREVEngenheiro Pleno - Segurança do Trabalho | H29: =Y29 | I29: 0.8 | J29: 1 | K29: 1 | L29: 1 | M29: 1 | N29: 1 | O29: 1 | P29: 1 | Q29: 1 | R29: 1 | S29: 1 | T29: 1 | U29: 0.2 | V29: =SUM(I29:U29) -> 12 | W29: 25688.39 | X29: =W29*V29 -> 308260.68 | AL29: Motorista (12x36) - Noturno
B30: 26 | C30: REAL | D30: 1.13 | E30: Engenheiro Pleno - Segurança do Trabalho | F30: P9864 (*) | G30: =C30&E30 -> REALEngenheiro Pleno - Segurança do Trabalho | H30: =Y30 -> 0.51666667 | I30: 0.8 | J30: 1 | K30: 1 | L30: 0.83333333 | M30: 1 | N30: 1 | O30: 0.56666667 | V30: =SUM(I30:U30) -> 6.2 | W30: 25688.39 | X30: =W30*V30 -> 159268.02 | Y30: =X30/X29 -> 0.51666667 | Z30: =X29-AC30 -> 30826.068 | AB30: =ROUND((AVERAGE(J30:T30)*12),1) -> 10.8 | AC30: =IF(AB30*W30>X29,X29,AB30*W30) -> 277434.61 | AD30: =AC30/X29 -> 0.9 | AL30: Oficial - Pedreiro/Armador/Carpinteiro - Com Periculosidade
B31: 27 | C31: PREV | D31: 1.14 | E31: Técnico Sênior - TI / Eletrotécnico (12X36) - Diurno | F31: P9867 | G31: =C31&E31 -> PREVTécnico Sênior - TI / Eletrotécnico (12X36) - Diurno | H31: =Y31 | I31: 1.6 | J31: 2 | K31: 2 | L31: 2 | M31: 2 | N31: 2 | O31: 2 | P31: 2 | Q31: 2 | R31: 2 | S31: 2 | T31: 2 | U31: 0.4 | V31: =SUM(I31:U31) -> 24 | W31: 6328.66 | X31: =W31*V31 -> 151887.84 | AL31: Servente / Zelador
B32: 28 | C32: REAL | D32: 1.14 | E32: Técnico Sênior - TI / Eletrotécnico (12X36) - Diurno | F32: P9867 | G32: =C32&E32 -> REALTécnico Sênior - TI / Eletrotécnico (12X36) - Diurno | H32: =Y32 -> 0.2625 | I32: 0.8 | J32: 1 | K32: 1 | L32: 0.5 | M32: 1 | N32: 1 | O32: 1 | V32: =SUM(I32:U32) -> 6.3 | W32: 6328.66 | X32: =W32*V32 -> 39870.558 | Y32: =X32/X31 -> 0.2625 | Z32: =X31-AC32 -> 82272.58 | AB32: =ROUND((AVERAGE(J32:T32)*12),1) -> 11 | AC32: =IF(AB32*W32>X31,X31,AB32*W32) -> 69615.26 | AD32: =AC32/X31 -> 0.45833333 | AL32: Servente - Com Periculosidade
B33: 29 | C33: PREV | D33: 1.15 | E33: Técnico Sênior - Eletrotécnico / Operador de Subest (12X36) - Diurno / Técnico Pleno - Eletromecânico/ Telecomunicações / Eletrotécnico / Eletrônico - Com Periculosidade | F33: P9867 (*) | G33: =C33&E33 -> PREVTécnico Sênior - Eletrotécnico / Operador de Subest (12X36) - Diurno / Técnico Pleno - Eletromecânico/ Telecomunicações / Eletrotécnico / Eletrônico - Com Periculosidade | H33: =Y33 | I33: 48 | J33: 60 | K33: 60 | L33: 60 | M33: 60 | N33: 60 | O33: 60 | P33: 60 | Q33: 60 | R33: 60 | S33: 60 | T33: 60 | U33: 12 | V33: =SUM(I33:U33) -> 720 | W33: 8227.26 | X33: =W33*V33 -> 5923627.2 | AL33: Engenheiro Coordenador
B34: 30 | C34: REAL | D34: 1.15 | E34: Técnico Sênior - Eletrotécnico / Operador de Subest (12X36) - Diurno / Técnico Pleno - Eletromecânico/ Telecomunicações / Eletrotécnico / Eletrônico - Com Periculosidade | F34: P9867 (*) | G34: =C34&E34 -> REALTécnico Sênior - Eletrotécnico / Operador de Subest (12X36) - Diurno / Técnico Pleno - Eletromecânico/ Telecomunicações / Eletrotécnico / Eletrônico - Com Periculosidade | H34: =Y34 -> 0.55274738 | I34: 42.373335 | J34: 58.10667 | K34: 59.117146 | L34: 62.561908 | M34: 60.580956 | N34: 56.20286 | O34: 59.035241 | V34: =SUM(I34:U34) -> 397.97812 | W34: 8227.26 | X34: =W34*V34 -> 3274269.4 | Y34: =X34/X33 -> 0.55274738 | Z34: =X33-AC34 -> 72399.888 | AB34: =ROUND((AVERAGE(J34:T34)*12),1) -> 711.2 | AC34: =IF(AB34*W34>X33,X33,AB34*W34) -> 5851227.3 | AD34: =AC34/X33 -> 0.98777778 | AL34: Previsão de Horas Extras - Eletromecânico - Montador
B35: 31 | C35: PREV | D35: 1.17 | E35: Técnico Sênior - Eletrotécnico - Noturno / Técnico Pleno - Operador de Subest (12X36) - Noturno | F35: P9867N (*) | G35: =C35&E35 -> PREVTécnico Sênior - Eletrotécnico - Noturno / Técnico Pleno - Operador de Subest (12X36) - Noturno | H35: =Y35 | I35: 3.2 | J35: 4 | K35: 4 | L35: 4 | M35: 4 | N35: 4 | O35: 4 | P35: 4 | Q35: 4 | R35: 4 | S35: 4 | T35: 4 | U35: 0.8 | V35: =SUM(I35:U35) -> 48 | W35: 12223.36 | X35: =W35*V35 -> 586721.28 | AL35: Previsão de Horas Extras - Eletromecânico - Montador
B36: 32 | C36: REAL | D36: 1.17 | E36: Técnico Sênior - Eletrotécnico - Noturno / Técnico Pleno - Operador de Subest (12X36) - Noturno | F36: P9867N (*) | G36: =C36&E36 -> REALTécnico Sênior - Eletrotécnico - Noturno / Técnico Pleno - Operador de Subest (12X36) - Noturno | H36: =Y36 -> 0.56666667 | I36: 3.2 | J36: 4 | K36: 4 | L36: 4 | M36: 4 | N36: 4 | O36: 4 | V36: =SUM(I36:U36) -> 27.2 | W36: 12223.36 | X36: =W36*V36 -> 332475.39 | Y36: =X36/X35 -> 0.56666667 | Z36: =X35-AC36 -> 0 | AB36: =ROUND((AVERAGE(J36:T36)*12),1) -> 48 | AC36: =IF(AB36*W36>X35,X35,AB36*W36) -> 586721.28 | AD36: =AC36/X35 -> 1 | AL36: Previsão de Horas Sobreaviso - Técnico Sênior Eletromecânico/Eletrotécnico/Eletrônico
B37: 33 | C37: PREV | D37: 1.18 | E37: Técnico Sênior - Segurança | F37: P9876 (*) | G37: =C37&E37 -> PREVTécnico Sênior - Segurança | H37: =Y37 | I37: 1.6 | J37: 2 | K37: 2 | L37: 2 | M37: 2 | N37: 2 | O37: 2 | P37: 2 | Q37: 2 | R37: 2 | S37: 2 | T37: 2 | U37: 0.4 | V37: =SUM(I37:U37) -> 24 | W37: 8433.02 | X37: =W37*V37 -> 202392.48 | AL37: Previsão de Horas Extras - Técnico Sênior Eletromecânico/Eletrotécnico/Eletrônico
B38: 34 | C38: REAL | D38: 1.18 | E38: Técnico Sênior - Segurança | F38: P9876 (*) | G38: =C38&E38 -> REALTécnico Sênior - Segurança | H38: =Y38 -> 0.56666667 | I38: 1.6 | J38: 2 | K38: 2 | L38: 2 | M38: 2 | N38: 2 | O38: 2 | V38: =SUM(I38:U38) -> 13.6 | W38: 8433.02 | X38: =W38*V38 -> 114689.07 | Y38: =X38/X37 -> 0.56666667 | Z38: =X37-AC38 -> 0 | AB38: =ROUND((AVERAGE(J38:T38)*12),1) -> 24 | AC38: =IF(AB38*W38>X37,X37,AB38*W38) -> 202392.48 | AD38: =AC38/X37 -> 1 | AL38: Previsão de Horas Extras - Técnico Sênior Eletromecânico/Eletrotécnico/Eletrônico
B39: 35 | C39: PREV | D39: 1.19 | E39: Secretária | F39: P9878 | G39: =C39&E39 -> PREVSecretária | H39: =Y39 | I39: 0.8 | J39: 1 | K39: 1 | L39: 1 | M39: 1 | N39: 1 | O39: 1 | P39: 1 | Q39: 1 | R39: 1 | S39: 1 | T39: 1 | U39: 0.2 | V39: =SUM(I39:U39) -> 12 | W39: 6370.42 | X39: =W39*V39 -> 76445.04 | AL39: Previsão de Horas Sobreaviso ‐ Motorista
B40: 36 | C40: REAL | D40: 1.19 | E40: Secretária | F40: P9878 | G40: =C40&E40 -> REALSecretária | H40: =Y40 -> 0.56666667 | I40: 0.8 | J40: 1 | K40: 1 | L40: 1 | M40: 1 | N40: 1 | O40: 1 | V40: =SUM(I40:U40) -> 6.8 | W40: 6370.42 | X40: =W40*V40 -> 43318.856 | Y40: =X40/X39 -> 0.56666667 | Z40: =X39-AC40 -> 0 | AB40: =ROUND((AVERAGE(J40:T40)*12),1) -> 12 | AC40: =IF(AB40*W40>X39,X39,AB40*W40) -> 76445.04 | AD40: =AC40/X39 -> 1 | AL40: Previsão de Horas Extras - Motorista
B41: 37 | C41: PREV | D41: 1.20 | E41: Chefe de Escritório | F41: P9883 | G41: =C41&E41 -> PREVChefe de Escritório | H41: =Y41 | I41: 1.6 | J41: 2 | K41: 2 | L41: 2 | M41: 2 | N41: 2 | O41: 2 | P41: 2 | Q41: 2 | R41: 2 | S41: 2 | T41: 2 | U41: 0.4 | V41: =SUM(I41:U41) -> 24 | W41: 7072.07 | X41: =W41*V41 -> 169729.68 | AL41: Previsão de Horas Extras - Motorista
B42: 38 | C42: REAL | D42: 1.20 | E42: Chefe de Escritório | F42: P9883 | G42: =C42&E42 -> REALChefe de Escritório | H42: =Y42 -> 0.53888889 | I42: 1.6 | J42: 2 | K42: 2 | L42: 2 | M42: 1.6666667 | N42: 1.6666667 | O42: 2 | V42: =SUM(I42:U42) -> 12.933333 | W42: 7072.07 | X42: =W42*V42 -> 91465.439 | Y42: =X42/X41 -> 0.53888889 | Z42: =X41-AC42 -> 9193.691 | AB42: =ROUND((AVERAGE(J42:T42)*12),1) -> 22.7 | AC42: =IF(AB42*W42>X41,X41,AB42*W42) -> 160535.99 | AD42: =AC42/X41 -> 0.94583333 | AL42: Previsão de Horas Extras - Eletromecânico - Montador
B43: 39 | C43: PREV | D43: 1.21 | E43: Comprador | F43: P9900 | G43: =C43&E43 -> PREVComprador | H43: =Y43 | I43: 0.8 | J43: 1 | K43: 1 | L43: 1 | M43: 1 | N43: 1 | O43: 1 | P43: 1 | Q43: 1 | R43: 1 | S43: 1 | T43: 1 | U43: 0.2 | V43: =SUM(I43:U43) -> 12 | W43: 6365.63 | X43: =W43*V43 -> 76387.56 | AL43: Previsão de Horas Extras - Eletromecânico - Montador
B44: 40 | C44: REAL | D44: 1.21 | E44: Comprador | F44: P9900 | G44: =C44&E44 -> REALComprador | H44: =Y44 -> 0.41666667 | I44: 0 | J44: 1 | K44: 0 | L44: 1 | M44: 1 | N44: 1 | O44: 1 | V44: =SUM(I44:U44) -> 5 | W44: 6365.63 | X44: =W44*V44 -> 31828.15 | Y44: =X44/X43 -> 0.41666667 | Z44: =X43-AC44 -> 12731.26 | AB44: =ROUND((AVERAGE(J44:T44)*12),1) -> 10 | AC44: =IF(AB44*W44>X43,X43,AB44*W44) -> 63656.3 | AD44: =AC44/X43 -> 0.83333333 | AL44: Viagens Aéreas - 1 trecho (ida)
B45: 41 | C45: PREV | D45: 1.22 | E45: Eletricista - Com Periculosidade | F45: P9930 (*) | G45: =C45&E45 -> PREVEletricista - Com Periculosidade | H45: =Y45 | I45: 8.8 | J45: 11 | K45: 11 | L45: 11 | M45: 11 | N45: 11 | O45: 11 | P45: 11 | Q45: 11 | R45: 11 | S45: 11 | T45: 11 | U45: 2.2 | V45: =SUM(I45:U45) -> 132 | W45: 7104.43 | X45: =W45*V45 -> 937784.76 | AL45: Viagens Aéreas - 1 trecho (volta)
B46: 42 | C46: REAL | D46: 1.22 | E46: Eletricista - Com Periculosidade | F46: P9930 (*) | G46: =C46&E46 -> REALEletricista - Com Periculosidade | H46: =Y46 -> 0.39570707 | I46: 6.1 | J46: 8.3666667 | K46: 8.4 | L46: 6.5333333 | M46: 7.2333333 | N46: 7.3666667 | O46: 8.2333333 | V46: =SUM(I46:U46) -> 52.233333 | W46: 7104.43 | X46: =W46*V46 -> 371088.06 | Y46: =X46/X45 -> 0.39570707 | Z46: =X45-AC46 -> 282045.87 | AB46: =ROUND((AVERAGE(J46:T46)*12),1) -> 92.3 | AC46: =IF(AB46*W46>X45,X45,AB46*W46) -> 655738.89 | AD46: =AC46/X45 -> 0.69924242 | AL46: Viagens Terrestres - 1 trecho (ida)
B47: 43 | C47: PREV | D47: 1.23 | E47: Engenheiro Júnior - Eletricista - Com Periculosidade | F47: P9946 (*) | G47: =C47&E47 -> PREVEngenheiro Júnior - Eletricista - Com Periculosidade | H47: =Y47 | I47: 0.8 | J47: 1 | K47: 1 | L47: 1 | M47: 1 | N47: 1 | O47: 1 | P47: 1 | Q47: 1 | R47: 1 | S47: 1 | T47: 1 | U47: 0.2 | V47: =SUM(I47:U47) -> 12 | W47: 25568.86 | X47: =W47*V47 -> 306826.32 | AL47: Viagens Terrestres - 1 trecho (volta)
B48: 44 | C48: REAL | D48: 1.23 | E48: Engenheiro Júnior - Eletricista - Com Periculosidade | F48: P9946 (*) | G48: =C48&E48 -> REALEngenheiro Júnior - Eletricista - Com Periculosidade | H48: =Y48 -> 0.29876511 | I48: 0.8 | J48: 0.4641969 | K48: 0.4641969 | L48: 0.4641969 | M48: 0.4641969 | N48: 0.4641969 | O48: 0.4641969 | V48: =SUM(I48:U48) -> 3.5851814 | W48: 25568.86 | X48: =W48*V48 -> 91669.001 | Y48: =X48/X47 -> 0.29876511 | Z48: =X47-AC48 -> 163640.7 | AB48: =ROUND((AVERAGE(J48:T48)*12),1) -> 5.6 | AC48: =IF(AB48*W48>X47,X47,AB48*W48) -> 143185.62 | AD48: =AC48/X47 -> 0.46666667 | AL48: Diárias Nacionais
B49: 45 | C49: PREV | D49: 1.24 | E49: Motorista | F49: P9948 | G49: =C49&E49 -> PREVMotorista | H49: =Y49 | I49: 15.2 | J49: 19 | K49: 19 | L49: 19 | M49: 19 | N49: 19 | O49: 19 | P49: 19 | Q49: 19 | R49: 19 | S49: 19 | T49: 19 | U49: 3.8 | V49: =SUM(I49:U49) -> 228 | W49: 5099.23 | X49: =W49*V49 -> 1162624.4 | AL49: Aluguel Notebook ‐ com software ‐ tipo 2 (i7, HD 1Tb, Memória RAM 8Gb, Tela 15,6" + Sist. Operacional Windows 10)
B50: 46 | C50: REAL | D50: 1.24 | E50: Motorista | F50: P9948 | G50: =C50&E50 -> REALMotorista | H50: =Y50 -> 0.62149123 | I50: 14.3 | J50: 20.2 | K50: 22.8 | L50: 22.433333 | M50: 22.433333 | N50: 21.966667 | O50: 17.566667 | V50: =SUM(I50:U50) -> 141.7 | W50: 5099.23 | X50: =W50*V50 -> 722560.89 | Y50: =X50/X49 -> 0.62149123 | Z50: =X49-AC50 -> 0 | AB50: =ROUND((AVERAGE(J50:T50)*12),1) -> 254.8 | AC50: =IF(AB50*W50>X49,X49,AB50*W50) -> 1162624.4 | AD50: =AC50/X49 -> 1 | AL50: Aluguel de Impressora A3
B51: 47 | C51: PREV | D51: 1.25 | E51: Motorista (12x36) - Noturno | F51: P9948N | G51: =C51&E51 -> PREVMotorista (12x36) - Noturno | H51: =Y51 | I51: 6.4 | J51: 8 | K51: 8 | L51: 8 | M51: 8 | N51: 8 | O51: 8 | P51: 8 | Q51: 8 | R51: 8 | S51: 8 | T51: 8 | U51: 1.6 | V51: =SUM(I51:U51) -> 96 | W51: 7575.99 | X51: =W51*V51 -> 727295.04 | AL51: Aluguel de Servidor
B52: 48 | C52: REAL | D52: 1.25 | E52: Motorista (12x36) - Noturno | F52: P9948N | G52: =C52&E52 -> REALMotorista (12x36) - Noturno | H52: =Y52 -> 0.58402778 | I52: 6.2333333 | J52: 9.8333333 | K52: 8 | L52: 8 | M52: 8 | N52: 8 | O52: 8 | V52: =SUM(I52:U52) -> 56.066667 | W52: 7575.99 | X52: =W52*V52 -> 424760.51 | Y52: =X52/X51 -> 0.58402778 | Z52: =X51-AC52 -> 0 | AB52: =ROUND((AVERAGE(J52:T52)*12),1) -> 99.7 | AC52: =IF(AB52*W52>X51,X51,AB52*W52) -> 727295.04 | AD52: =AC52/X51 -> 1 | AL52: Aluguel de Plotter
B53: 49 | C53: PREV | D53: 1.26 | E53: Oficial - Pedreiro/Armador/Carpinteiro - Com Periculosidade | F53: P9952 (*) | G53: =C53&E53 -> PREVOficial - Pedreiro/Armador/Carpinteiro - Com Periculosidade | H53: =Y53 | I53: 1.6 | J53: 2 | K53: 2 | L53: 2 | M53: 2 | N53: 2 | O53: 2 | P53: 2 | Q53: 2 | R53: 2 | S53: 2 | T53: 2 | U53: 0.4 | V53: =SUM(I53:U53) -> 24 | W53: 7296.61 | X53: =W53*V53 -> 175118.64 | AL53: Veículo - caminhonete 4x4 cabine dupla
B54: 50 | C54: REAL | D54: 1.26 | E54: Oficial - Pedreiro/Armador/Carpinteiro - Com Periculosidade | F54: P9952 (*) | G54: =C54&E54 -> REALOficial - Pedreiro/Armador/Carpinteiro - Com Periculosidade | H54: =Y54 -> 0.48333333 | I54: 1.6 | J54: 2 | K54: 1 | L54: 2 | M54: 1.5333333 | N54: 1.4666667 | O54: 2 | V54: =SUM(I54:U54) -> 11.6 | W54: 7296.61 | X54: =W54*V54 -> 84640.676 | Y54: =X54/X53 -> 0.48333333 | Z54: =X53-AC54 -> 29186.44 | AB54: =ROUND((AVERAGE(J54:T54)*12),1) -> 20 | AC54: =IF(AB54*W54>X53,X53,AB54*W54) -> 145932.2 | AD54: =AC54/X53 -> 0.83333333 | AL54: Veículo - caminhonete 4x4 cabine dupla c/ motorista
B55: 51 | C55: PREV | D55: 1.27 | E55: Servente / Zelador | F55: P9954 | G55: =C55&E55 -> PREVServente / Zelador | H55: =Y55 | I55: 3.2 | J55: 4 | K55: 4 | L55: 4 | M55: 4 | N55: 4 | O55: 4 | P55: 4 | Q55: 4 | R55: 4 | S55: 4 | T55: 4 | U55: 0.8 | V55: =SUM(I55:U55) -> 48 | W55: 3767.94 | X55: =W55*V55 -> 180861.12 | AL55: Veículo - pick up 4x4 (E8891) - Operativo + Improdutivo
B56: 52 | C56: REAL | D56: 1.27 | E56: Servente / Zelador | F56: P9954 | G56: =C56&E56 -> REALServente / Zelador | H56: =Y56 -> 0.58055556 | I56: 4.8 | J56: 4 | K56: 4 | L56: 4 | M56: 3.5 | N56: 4 | O56: 3.5666667 | V56: =SUM(I56:U56) -> 27.866667 | W56: 3767.94 | X56: =W56*V56 -> 104999.93 | Y56: =X56/X55 -> 0.58055556 | Z56: =X55-AC56 -> 7159.086 | AB56: =ROUND((AVERAGE(J56:T56)*12),1) -> 46.1 | AC56: =IF(AB56*W56>X55,X55,AB56*W56) -> 173702.03 | AD56: =AC56/X55 -> 0.96041667 | AL56: Veículo - sedan 1.6 flex - 115CV (E8889) - Operativo + Improdutivo
B57: 53 | C57: PREV | D57: 1.28 | E57: Servente - Com Periculosidade | F57: P9954 (*) | G57: =C57&E57 -> PREVServente - Com Periculosidade | H57: =Y57 | I57: 17.6 | J57: 22 | K57: 22 | L57: 22 | M57: 22 | N57: 22 | O57: 22 | P57: 22 | Q57: 22 | R57: 22 | S57: 22 | T57: 22 | U57: 4.4 | V57: =SUM(I57:U57) -> 264 | W57: 4898.32 | X57: =W57*V57 -> 1293156.5 | AL57: Veículo - van com motorista tipo furgão (E8887) - Operativo + Improdutivo
B58: 54 | C58: REAL | D58: 1.28 | E58: Servente - Com Periculosidade | F58: P9954 (*) | G58: =C58&E58 -> REALServente - Com Periculosidade | H58: =Y58 -> 0.50290404 | I58: 17.266667 | J58: 20.033333 | K58: 20.566667 | L58: 20.433333 | M58: 18.666667 | N58: 17 | O58: 18.8 | V58: =SUM(I58:U58) -> 132.76667 | W58: 4898.32 | X58: =W58*V58 -> 650333.62 | Y58: =X58/X57 -> 0.50290404 | Z58: =X57-AC58 -> 161644.56 | AB58: =ROUND((AVERAGE(J58:T58)*12),1) -> 231 | AC58: =IF(AB58*W58>X57,X57,AB58*W58) -> 1131511.9 | AD58: =AC58/X57 -> 0.875 | AL58: Ônibus com 45 lugares - 218CV (com motorista - incluindo combustível e manutenção)
B59: 55 | C59: PREV | D59: 1.29 | E59: Engenheiro Coordenador | F59: P9955 (*) | G59: =C59&E59 -> PREVEngenheiro Coordenador | H59: =Y59 | I59: 0.8 | J59: 1 | K59: 1 | L59: 1 | M59: 1 | N59: 1 | O59: 1 | P59: 1 | Q59: 1 | R59: 1 | S59: 1 | T59: 1 | U59: 0.2 | V59: =SUM(I59:U59) -> 12 | W59: 32114.49 | X59: =W59*V59 -> 385373.88 | AL59: Imóvel Comercial - Escritório + Almox (B8951) - 150 m²
B60: 56 | C60: REAL | D60: 1.29 | E60: Engenheiro Coordenador | F60: P9955 (*) | G60: =C60&E60 -> REALEngenheiro Coordenador | H60: =Y60 -> 0.56666667 | I60: 0.8 | J60: 1 | K60: 1 | L60: 1 | M60: 1 | N60: 1 | O60: 1 | V60: =SUM(I60:U60) -> 6.8 | W60: 32114.49 | X60: =W60*V60 -> 218378.53 | Y60: =X60/X59 -> 0.56666667 | Z60: =X59-AC60 -> 0 | AB60: =ROUND((AVERAGE(J60:T60)*12),1) -> 12 | AC60: =IF(AB60*W60>X59,X59,AB60*W60) -> 385373.88 | AD60: =AC60/X59 -> 1 | AL60: Mobiliário para escritório (B8953)
B61: 57 | C61: PREV | D61: 1.30 | E61: Previsão de Horas Extras - Eletromecânico - Montador | F61: P9830h (*) | G61: =C61&E61 -> PREVPrevisão de Horas Extras - Eletromecânico - Montador | H61: =Y61 | U61: 1 | V61: =SUM(I61:U61) -> 1 | W61: 58.005 | X61: =W61*V61 -> 58.005 | AL61: Custos Diversos - Escritório (B8959)
B62: 58 | C62: REAL | D62: 1.30 | E62: Previsão de Horas Extras - Eletromecânico - Montador | F62: P9830h (*) | G62: =C62&E62 -> REALPrevisão de Horas Extras - Eletromecânico - Montador | H62: =Y62 -> 0 | I62: 0 | J62: 0 | K62: 0 | L62: 0 | M62: 0 | N62: 0 | O62: 0 | V62: =SUM(I62:U62) -> 0 | W62: 58.005 | X62: =W62*V62 -> 0 | Y62: =X62/X61 -> 0 | Z62: =X61-AC62 -> 58.005 | AB62: =ROUND((AVERAGE(J62:T62)*12),1) -> 0 | AC62: =IF(AB62*W62>X61,X61,AB62*W62) -> 0 | AD62: =AC62/X61 -> 0 | AL62: GPS de Navegação
B63: 59 | C63: PREV | D63: 1.31 | E63: Previsão de Horas Extras - Eletromecânico - Montador | F63: P9830Nh (*) | G63: =C63&E63 -> PREVPrevisão de Horas Extras - Eletromecânico - Montador | H63: =Y63 | U63: 1 | V63: =SUM(I63:U63) -> 1 | W63: 86.175 | X63: =W63*V63 -> 86.175 | AL63: Câmera fotográfica
B64: 60 | C64: REAL | D64: 1.31 | E64: Previsão de Horas Extras - Eletromecânico - Montador | F64: P9830Nh (*) | G64: =C64&E64 -> REALPrevisão de Horas Extras - Eletromecânico - Montador | H64: =Y64 -> 0 | I64: 0 | J64: 0 | K64: 0 | L64: 0 | M64: 0 | N64: 0 | O64: 0 | V64: =SUM(I64:U64) -> 0 | W64: 86.175 | X64: =W64*V64 -> 0 | Y64: =X64/X63 -> 0 | Z64: =X63-AC64 -> 86.175 | AB64: =ROUND((AVERAGE(J64:T64)*12),1) -> 0 | AC64: =IF(AB64*W64>X63,X63,AB64*W64) -> 0 | AD64: =AC64/X63 -> 0 | AL64: Câmera fotografica profissional DSLR, 18 MP, vídeos em Full HD, lente EF-S 18-55mm f/3.5-5.6 III e bateria
B65: 61 | C65: PREV | D65: 1.32 | E65: Previsão de Horas Sobreaviso - Técnico Sênior Eletromecânico/Eletrotécnico/Eletrônico | F65: P9867h | G65: =C65&E65 -> PREVPrevisão de Horas Sobreaviso - Técnico Sênior Eletromecânico/Eletrotécnico/Eletrônico | H65: =Y65 | U65: 1 | V65: =SUM(I65:U65) -> 1 | W65: 11.43 | X65: =W65*V65 -> 11.43 | AL65: Binóculo Profissional Ampliação 8 à 24x 50mm
B66: 62 | C66: REAL | D66: 1.32 | E66: Previsão de Horas Sobreaviso - Técnico Sênior Eletromecânico/Eletrotécnico/Eletrônico | F66: P9867h | G66: =C66&E66 -> REALPrevisão de Horas Sobreaviso - Técnico Sênior Eletromecânico/Eletrotécnico/Eletrônico | H66: =Y66 -> 0 | I66: 0 | J66: 0 | K66: 0 | L66: 0 | M66: 0 | N66: 0 | O66: 0 | V66: =SUM(I66:U66) -> 0 | W66: 11.43 | X66: =W66*V66 -> 0 | Y66: =X66/X65 -> 0 | Z66: =X65-AC66 -> 11.43 | AB66: =ROUND((AVERAGE(J66:T66)*12),1) -> 0 | AC66: =IF(AB66*W66>X65,X65,AB66*W66) -> 0 | AD66: =AC66/X65 -> 0 | AL66: Sistema de repetidoras VHF interligadas com link UHF - 4 antenas
B67: 63 | C67: PREV | D67: 1.33 | E67: Previsão de Horas Extras - Técnico Sênior Eletromecânico/Eletrotécnico/Eletrônico | F67: P9867h (*) | G67: =C67&E67 -> PREVPrevisão de Horas Extras - Técnico Sênior Eletromecânico/Eletrotécnico/Eletrônico | H67: =Y67 | U67: 1 | V67: =SUM(I67:U67) -> 1 | W67: 66.9 | X67: =W67*V67 -> 66.9 | AL67: Sistema de repetidoras VHF interligadas com link UHF - 2 antenas
B68: 64 | C68: REAL | D68: 1.33 | E68: Previsão de Horas Extras - Técnico Sênior Eletromecânico/Eletrotécnico/Eletrônico | F68: P9867h (*) | G68: =C68&E68 -> REALPrevisão de Horas Extras - Técnico Sênior Eletromecânico/Eletrotécnico/Eletrônico | H68: =Y68 -> 0 | I68: 0 | J68: 0 | K68: 0 | L68: 0 | M68: 0 | N68: 0 | O68: 0 | V68: =SUM(I68:U68) -> 0 | W68: 66.9 | X68: =W68*V68 -> 0 | Y68: =X68/X67 -> 0 | Z68: =X67-AC68 -> 66.9 | AB68: =ROUND((AVERAGE(J68:T68)*12),1) -> 0 | AC68: =IF(AB68*W68>X67,X67,AB68*W68) -> 0 | AD68: =AC68/X67 -> 0 | AL68: Rádio VHF portátil EP 450
B69: 65 | C69: PREV | D69: 1.34 | E69: Previsão de Horas Extras - Técnico Sênior Eletromecânico/Eletrotécnico/Eletrônico | F69: P9867Nh (*) | G69: =C69&E69 -> PREVPrevisão de Horas Extras - Técnico Sênior Eletromecânico/Eletrotécnico/Eletrônico | H69: =Y69 | U69: 1 | V69: =SUM(I69:U69) -> 1 | W69: 99.390003 | X69: =W69*V69 -> 99.390003 | AL69: Rádio VHF móvel digital para viatura
B70: 66 | C70: REAL | D70: 1.34 | E70: Previsão de Horas Extras - Técnico Sênior Eletromecânico/Eletrotécnico/Eletrônico | F70: P9867Nh (*) | G70: =C70&E70 -> REALPrevisão de Horas Extras - Técnico Sênior Eletromecânico/Eletrotécnico/Eletrônico | H70: =Y70 -> 0 | I70: 0 | J70: 0 | K70: 0 | L70: 0 | M70: 0 | N70: 0 | O70: 0 | V70: =SUM(I70:U70) -> 0 | W70: 99.390003 | X70: =W70*V70 -> 0 | Y70: =X70/X69 -> 0 | Z70: =X69-AC70 -> 99.390003 | AB70: =ROUND((AVERAGE(J70:T70)*12),1) -> 0 | AC70: =IF(AB70*W70>X69,X69,AB70*W70) -> 0 | AD70: =AC70/X69 -> 0 | AL70: Rádio VHF para instalação nas SEs, composto por rádio base e sistema irradiante
B71: 67 | C71: PREV | D71: 1.35 | E71: Previsão de Horas Sobreaviso ‐ Motorista | F71: P9870h | G71: =C71&E71 -> PREVPrevisão de Horas Sobreaviso ‐ Motorista | H71: =Y71 | U71: 1 | V71: =SUM(I71:U71) -> 1 | W71: 9.2166667 | X71: =W71*V71 -> 9.2166667 | AL71: Serviço de instalação e configuração de sistema de repetidoras e infraestrutura - 4 antenas
B72: 68 | C72: REAL | D72: 1.35 | E72: Previsão de Horas Sobreaviso ‐ Motorista | F72: P9870h | G72: =C72&E72 -> REALPrevisão de Horas Sobreaviso ‐ Motorista | H72: =Y72 -> 0 | I72: 0 | J72: 0 | K72: 0 | L72: 0 | M72: 0 | N72: 0 | O72: 0 | V72: =SUM(I72:U72) -> 0 | W72: 9.2166667 | X72: =W72*V72 -> 0 | Y72: =X72/X71 -> 0 | Z72: =X71-AC72 -> 9.2166667 | AB72: =ROUND((AVERAGE(J72:T72)*12),1) -> 0 | AC72: =IF(AB72*W72>X71,X71,AB72*W72) -> 0 | AD72: =AC72/X71 -> 0 | AL72: Serviço de instalação e configuração de sistema de repetidoras e infraestrutura - 2 antenas
B73: 69 | C73: PREV | D73: 1.36 | E73: Previsão de Horas Extras - Motorista | F73: P9870h | G73: =C73&E73 -> PREVPrevisão de Horas Extras - Motorista | H73: =Y73 | U73: 1 | V73: 1 | W73: 41.475003 | X73: =W73*V73 -> 41.475003 | AL73: Imóvel Residencial (B8952)
B74: 70 | C74: REAL | D74: 1.36 | E74: Previsão de Horas Extras - Motorista | F74: P9870h | G74: =C74&E74 -> REALPrevisão de Horas Extras - Motorista | H74: =Y74 -> 0 | I74: 0 | J74: 0 | K74: 0 | L74: 0 | M74: 0 | N74: 0 | O74: 0 | V74: =SUM(I74:U74) -> 0 | W74: 41.475003 | X74: =W74*V74 -> 0 | Y74: =X74/X73 -> 0 | Z74: =X73-AC74 -> 41.475003 | AB74: =ROUND((AVERAGE(J74:T74)*12),1) -> 0 | AC74: =IF(AB74*W74>X73,X73,AB74*W74) -> 0 | AD74: =AC74/X73 -> 0 | AL74: Mobiliário para Residência (B8954)
B75: 71 | C75: PREV | D75: 1.37 | E75: Previsão de Horas Extras - Motorista | F75: P9870Nh | G75: =C75&E75 -> PREVPrevisão de Horas Extras - Motorista | H75: =Y75 | U75: 1 | V75: 1 | W75: 61.635001 | X75: =W75*V75 -> 61.635001 | AL75: Custos Diversos - Residência (B8960)
B76: 72 | C76: REAL | D76: 1.37 | E76: Previsão de Horas Extras - Motorista | F76: P9870Nh | G76: =C76&E76 -> REALPrevisão de Horas Extras - Motorista | H76: =Y76 -> 0 | I76: 0 | J76: 0 | K76: 0 | L76: 0 | M76: 0 | N76: 0 | O76: 0 | V76: =SUM(I76:U76) -> 0 | W76: 61.635001 | X76: =W76*V76 -> 0 | Y76: =X76/X75 -> 0 | Z76: =X75-AC76 -> 61.635001 | AB76: =ROUND((AVERAGE(J76:T76)*12),1) -> 0 | AC76: =IF(AB76*W76>X75,X75,AB76*W76) -> 0 | AD76: =AC76/X75 -> 0 | AL76: Caminhão carroceria com guindauto com capacidade de 20 t.m - 136 kW
B77: 73 | C77: PREV | D77: 1.38 | E77: Previsão de Horas Extras - Eletromecânico - Montador | F77: P9930h (*) | G77: =C77&E77 -> PREVPrevisão de Horas Extras - Eletromecânico - Montador | H77: =Y77 | U77: 1 | V77: =SUM(I77:U77) -> 1 | W77: 48.42 | X77: =W77*V77 -> 48.42 | AL77: Caminhão carroceria com guindauto e cesto aéreo com capacidade de 10 t.m - 136 kW
B78: 74 | C78: REAL | D78: 1.38 | E78: Previsão de Horas Extras - Eletromecânico - Montador | F78: P9930h (*) | G78: =C78&E78 -> REALPrevisão de Horas Extras - Eletromecânico - Montador | H78: =Y78 -> 0 | I78: 0 | J78: 0 | K78: 0 | L78: 0 | M78: 0 | N78: 0 | O78: 0 | V78: =SUM(I78:U78) -> 0 | W78: 48.42 | X78: =W78*V78 -> 0 | Y78: =X78/X77 -> 0 | Z78: =X77-AC78 -> 48.42 | AB78: =ROUND((AVERAGE(J78:T78)*12),1) -> 0 | AC78: =IF(AB78*W78>X77,X77,AB78*W78) -> 0 | AD78: =AC78/X77 -> 0 | AL78: Caminhão carroceria com capacidade de 15 t - 188 kW -c/Cabine auxiliar (horas produtivas)
B79: 75 | C79: PREV | D79: 1.39 | E79: Previsão de Horas Extras - Eletromecânico - Montador | F79: P9930Nh (*) | G79: =C79&E79 -> PREVPrevisão de Horas Extras - Eletromecânico - Montador | H79: =Y79 | U79: 1 | V79: =SUM(I79:U79) -> 1 | W79: 84.6 | X79: =W79*V79 -> 84.6 | AL79: Caminhão carroceria com capacidade de 15 t - 188 kW -c/Cabine auxiliar (horas improdutivas)
B80: 76 | C80: REAL | D80: 1.39 | E80: Previsão de Horas Extras - Eletromecânico - Montador | F80: P9930Nh (*) | G80: =C80&E80 -> REALPrevisão de Horas Extras - Eletromecânico - Montador | H80: =Y80 -> 0 | I80: 0 | J80: 0 | K80: 0 | L80: 0 | M80: 0 | N80: 0 | O80: 0 | V80: =SUM(I80:U80) -> 0 | W80: 84.6 | X80: =W80*V80 -> 0 | Y80: =X80/X79 -> 0 | Z80: =X79-AC80 -> 84.6 | AB80: =ROUND((AVERAGE(J80:T80)*12),1) -> 0 | AC80: =IF(AB80*W80>X79,X79,AB80*W80) -> 0 | AD80: =AC80/X79 -> 0 | AL80: Cavalo mecânico com semirreboque com capacidade de 22 t - 240 kW (horas produtivas)
B81: 77 | AL81: Cavalo mecânico com semirreboque com capacidade de 22 t - 240 kW (horas improdutivas)
B82: 78 | C82: PREV | D82: TOTAL - MÃO DE OBRA | I82: 166.5 | J82: 166.5 | K82: 166.5 | L82: 166.5 | M82: 166.5 | N82: 166.5 | O82: 166.5 | P82: 166.5 | Q82: 166.5 | R82: 166.5 | S82: 166.5 | T82: 166.5 | U82: 166.5 | V82: =SUMIF($C$7:$C$60,$C$82,V7:V60) -> 2286 | X82: =SUMIF($C$7:$C$80,$C$82,X7:X80)+0.01 -> 18310884 | Y82: =X82/$X$260 -> 0.59132233 | AL82: Caminhão tanque com capacidade de 10.000 l - 188 kW (horas produtivas)
B83: 79 | C83: REAL | D83: TOTAL - MÃO DE OBRA | I83: =SUMIF($C$7:$C$60,$C$83,I7:I60) -> 134.03823 | J83: =SUMIF($C$7:$C$60,$C$83,J7:J60) -> 176.66032 | K83: =SUMIF($C$7:$C$60,$C$83,K7:K60) -> 179.8016 | L83: =SUMIF($C$7:$C$60,$C$83,L7:L60) -> 180.74637 | M83: =SUMIF($C$7:$C$60,$C$83,M7:M60) -> 176.26541 | N83: =SUMIF($C$7:$C$60,$C$83,N7:N60) -> 169.55399 | O83: =SUMIF($C$7:$C$60,$C$83,O7:O60) -> 168.8197 | P83: =SUMIF($C$7:$C$60,$C$83,P7:P60) -> 0 | ... V83: =SUMIF($C$7:$C$60,$C$83,V7:V60) -> 1185.8856 | X83: =SUMIF($C$7:$C$60,$C$83,X7:X60) -> 9407553.8 | Y83: =X83/X82 -> 0.51376841 | AA83: =SUM(Z8:Z80) -> 1769328.8 | AC83: =SUM(AC10:AC80) -> 16541555 | AD83: =AC83/X82 -> 0.90337283 | AL83: Caminhão tanque com capacidade de 10.000 l - 188 kW (horas improdutivas)
B84: 80 | C84: PREV | E84: (*) com periculosidade | AL84: Caminhão basculante com capacidade de 10 m³ - 188 kW (horas produtivas)
B85: 81 | C85: REAL | E85: (*) com periculosidade | AL85: Caminhão basculante com capacidade de 10 m³ - 188 kW (horas improdutivas)
B86: 82 | C86: PREV | D86: 2 | E86: CUSTOS DIRETOS | Y86: =Y87 -> 0.51248057 | AL86: Motoniveladora - 93 kW (horas produtivas)
B87: 83 | C87: REAL | D87: 2 | E87: CUSTOS DIRETOS | Y87: =Y252 -> 0.51248057 | AL87: Motoniveladora - 93 kW (horas improdutivas)
B88: 84 | C88: PREV | D88: 2.1 | E88: VIAGENS | X88: =SUMIF($C89:$C98,$C88,X89:X98) -> 382021.68 | AA88: =SUM(Z90:Z99) -> 286810.9 | AL88: Retroescavadeira de pneus com capacidade de 0,76 m³ - 58 kW (horas produtivas)
B89: 85 | C89: REAL | D89: 2.1 | E89: VIAGENS | I89: =SUMIF($C90:$C99,$C89,I90:I99) -> 0 | J89: =SUMIF($C90:$C99,$C89,J90:J99) -> 86 | K89: =SUMIF($C90:$C99,$C89,K90:K99) -> 30.5 | L89: =SUMIF($C90:$C99,$C89,L90:L99) -> 117 | M89: =SUMIF($C90:$C99,$C89,M90:M99) -> 36.5 | N89: =SUMIF($C90:$C99,$C89,N90:N99) -> 88 | O89: =SUMIF($C90:$C99,$C89,O90:O99) -> 3 | P89: =SUMIF($C90:$C99,$C89,P90:P99) -> 0 | ... U89: =SUMIF($C90:$C99,$C89,U90:U99) -> 0 | X89: =SUMIF($C90:$C99,$C89,X90:X99) -> 94516.99 | Y89: =X89/X88 -> 0.24741263 | AC89: =SUM(AC91:AC99) -> 95210.78 | AD89: =AC89/X88 -> 0.24922873 | AL89: Retroescavadeira de pneus com capacidade de 0,76 m³ - 58 kW (horas improdutivas)
B90: 86 | C90: PREV | D90: 2.1.1 | E90: Viagens Aéreas - 1 trecho (ida) | F90: und | G90: =C90&E90 -> PREVViagens Aéreas - 1 trecho (ida) | H90: =Y90 | I90: 7.5 | J90: 7.5 | K90: 7.5 | L90: 7.5 | M90: 7.5 | N90: 7.5 | O90: 7.5 | P90: 7.5 | Q90: 7.5 | R90: 7.5 | S90: 7.5 | T90: 7.5 | V90: =SUM(I90:U90) -> 90 | W90: 693.79 | X90: =W90*V90 -> 62441.1 | AL90: MATERIAL DE CONSUMO ELÉTRICO
B91: 87 | C91: REAL | D91: 2.1.1 | E91: Viagens Aéreas - 1 trecho (ida) | F91: und | G91: =C91&E91 -> REALViagens Aéreas - 1 trecho (ida) | H91: =Y91 -> 0.011111111 | I91: 0 | J91: 1 | K91: 0 | L91: 0 | M91: 0 | N91: 0 | O91: 0 | V91: =SUM(I91:U91) -> 1 | W91: 693.79 | X91: =W91*V91 -> 693.79 | Y91: =X91/X90 -> 0.011111111 | Z91: =X90-AC91 -> 61053.52 | AB91: =ROUND((AVERAGE(J91:T91)*12),1) -> 2 | AC91: =IF(AB91*W91>X90,X90,AB91*W91) -> 1387.58 | AD91: =AC91/X90 -> 0.022222222 | AL91: FERRAMENTAS ELÉTRICA
B92: 88 | C92: PREV | D92: 2.1.2 | E92: Viagens Aéreas - 1 trecho (volta) | F92: und | G92: =C92&E92 -> PREVViagens Aéreas - 1 trecho (volta) | H92: =Y92 | J92: 7.5 | K92: 7.5 | L92: 7.5 | M92: 7.5 | N92: 7.5 | O92: 7.5 | P92: 7.5 | Q92: 7.5 | R92: 7.5 | S92: 7.5 | T92: 7.5 | U92: 7.5 | V92: =SUM(I92:U92) -> 90 | W92: 693.79 | X92: =W92*V92 -> 62441.1 | AL92: SOBRESSALENTES - ELÉTRICA
B93: 89 | C93: REAL | D93: 2.1.2 | E93: Viagens Aéreas - 1 trecho (volta) | F93: und | G93: =C93&E93 -> REALViagens Aéreas - 1 trecho (volta) | H93: =Y93 -> 0 | I93: 0 | J93: 0 | K93: 0 | L93: 0 | M93: 0 | N93: 0 | O93: 0 | V93: =SUM(I93:U93) -> 0 | W93: 693.79 | X93: =W93*V93 -> 0 | Y93: =X93/X92 -> 0 | Z93: =X92-AC93 -> 62441.1 | AB93: =ROUND((AVERAGE(J93:T93)*12),1) -> 0 | AC93: =IF(AB93*W93>X92,X92,AB93*W93) -> 0 | AD93: =AC93/X92 -> 0 | AL93: SOBRESSALENTES - LINHA DE TRANSMISSÃO
B94: 90 | C94: PREV | D94: 2.1.3 | E94: Viagens Terrestres - 1 trecho (ida) | F94: und | G94: =C94&E94 -> PREVViagens Terrestres - 1 trecho (ida) | H94: =Y94 | I94: 37.166667 | J94: 37.166667 | K94: 37.166667 | L94: 37.166667 | M94: 37.166667 | N94: 37.166667 | O94: 37.166667 | P94: 37.166667 | Q94: 37.166667 | R94: 37.166667 | S94: 37.166667 | T94: 37.166667 | U94: 0 | V94: =SUM(I94:U94) -> 446 | W94: 183.09 | X94: =W94*V94 -> 81658.14 | AL94: INSTRUMENTOS - ELÉTRICA
B95: 91 | C95: REAL | D95: 2.1.3 | E95: Viagens Terrestres - 1 trecho (ida) | F95: und | G95: =C95&E95 -> REALViagens Terrestres - 1 trecho (ida) | H95: =Y95 -> 0 | I95: 0 | J95: 0 | K95: 0 | L95: 0 | M95: 0 | N95: 0 | O95: 0 | V95: =SUM(I95:U95) -> 0 | W95: 183.09 | X95: =W95*V95 -> 0 | Y95: =X95/X94 -> 0 | Z95: =X94-AC95 -> 81658.14 | AB95: =ROUND((AVERAGE(J95:T95)*12),1) -> 0 | AC95: =IF(AB95*W95>X94,X94,AB95*W95) -> 0 | AD95: =AC95/X94 -> 0 | AL95: MANUTENÇÃO CIVIL - MATERIAIS CONSUMÍVEIS
B96: 92 | C96: PREV | D96: 2.1.4 | E96: Viagens Terrestres - 1 trecho (volta) | F96: und | G96: =C96&E96 -> PREVViagens Terrestres - 1 trecho (volta) | H96: =Y96 | J96: 37.166667 | K96: 37.166667 | L96: 37.166667 | M96: 37.166667 | N96: 37.166667 | O96: 37.166667 | P96: 37.166667 | Q96: 37.166667 | R96: 37.166667 | S96: 37.166667 | T96: 37.166667 | U96: 37.166667 | V96: =SUM(I96:U96) -> 446 | W96: 183.09 | X96: =W96*V96 -> 81658.14 | AL96: FERRAMENTAS - CIVIL
B97: 93 | C97: REAL | D97: 2.1.4 | E97: Viagens Terrestres - 1 trecho (volta) | F97: und | G97: =C97&E97 -> REALViagens Terrestres - 1 trecho (volta) | H97: =Y97 -> 0 | I97: 0 | J97: 0 | K97: 0 | L97: 0 | M97: 0 | N97: 0 | O97: 0 | V97: =SUM(I97:U97) -> 0 | W97: 183.09 | X97: =W97*V97 -> 0 | Y97: =X97/X96 -> 0 | Z97: =X96-AC97 -> 81658.14 | AB97: =ROUND((AVERAGE(J97:T97)*12),1) -> 0 | AC97: =IF(AB97*W97>X96,X96,AB97*W97) -> 0 | AD97: =AC97/X96 -> 0 | AL97: Transporte de componentes e equipamentos de elétrica
B98: 94 | C98: PREV | D98: 2.1.5 | E98: Diárias Nacionais | F98: und | G98: =C98&E98 -> PREVDiárias Nacionais | H98: =Y98 | I98: 24 | J98: 30 | K98: 30 | L98: 30 | M98: 30 | N98: 30 | O98: 30 | P98: 30 | Q98: 30 | R98: 30 | S98: 30 | T98: 30 | U98: =T98*0.2 -> 6 | V98: =SUM(I98:U98) -> 360 | W98: 260.62 | X98: =W98*V98 -> 93823.2 | AL98: Mobilização e Desmobilização dos equipamentos - eixo norte
B99: 95 | C99: REAL | D99: 2.1.5 | E99: Diárias Nacionais | F99: und | G99: =C99&E99 -> REALDiárias Nacionais | H99: =Y99 -> 1 | I99: 0 | J99: 85 | K99: 30.5 | L99: 117 | M99: 36.5 | N99: 88 | O99: 3 | V99: =SUM(I99:U99) -> 360 | W99: 260.62 | X99: =W99*V99 -> 93823.2 | Y99: =X99/X98 -> 1 | Z99: =X98-AC99 -> 0 | AB99: =ROUND((AVERAGE(J99:T99)*12),1) -> 720 | AC99: =IF(AB99*W99>X98,X98,AB99*W99) -> 93823.2 | AD99: =AC99/X98 -> 1 | AL99: Mobilização e Desmobilização dos equipamentos - eixo leste
B100: 96 | C100: PREV | D100: 2.2 | E100: EQUIPAMENTOS DE INFORMÁTICA E PROGRAMAS | X100: =SUMIF($C101:$C108,$C100,X101:X108) -> 138086.16 | AA100: =SUM(Z102:Z109) -> 0 | AL100: Locação de Container 2,30x6,00m, alt.2,50m, s/div. int e s/sanitários
...

Sheet CUSTO DIRETO- P x R
C1: PLANILHA REFERENCIAL DE PREÇOS - CUSTOS DIRETOS (COM DESONERAÇÃO)
C2: Item | D2: Descrição | H2: Unidade | I2: Meses | V2: Quantidade | W2: Preço Unitário | X2: Total | Y2: PERCENTUAL MEDIDO
I3: 24.1 | J3: 25 | K3: 26 | L3: 27 | M3: 28 | N3: 29 | O3: 30 | P3: 31 | Q3: 32 | R3: 33 | S3: 34 | T3: 35 | U3: 36
I4: jul | J4: ago | K4: set | L4: out | M4: nov | N4: dez | O4: jan | P4: fev | Q4: mar | R4: abr | S4: mai | T4: jun | U4: jul
A5: 1 | B5: PREV | C5: 1 | D5: GESTÃO DO CONTRATO
A6: 2 | B6: REAL | C6: 1 | D6: GESTÃO DO CONTRATO
A7: 3 | B7: PREV | C7: 1.1 | D7: VEÍCULOS | V7: 0 | W7: 0 | X7: =SUMIF(B9:B18,B7,X9:X18) -> 1396536.1
A8: 4 | B8: REAL | C8: 1.1 | D8: VEÍCULOS | G8: % | X8: =SUMIF(B9:B18,B8,X9:X18) -> 442236.44 | Y8: =X8/X7 -> 0.31666667
A9: 5 | B9: PREV | C9: 1.1.1 | D9: Veículo ‐ caminhonete 4x4 cabine dupla c/ motorista | E9: 2.3.2 | F9: =B9&D9 -> PREVVeículo ‐ caminhonete 4x4 cabine dupla c/ motorista | H9: und x mês | I9: 1.6 | J9: 2 | K9: 2 | L9: 2 | M9: 2 | N9: 2 | O9: 2 | P9: 2 | Q9: 2 | R9: 2 | S9: 2 | T9: 2 | U9: 0.4 | V9: =SUM(I9:U9) -> 24 | W9: 12971.63 | X9: =W9*V9 -> 311319.12
A10: 6 | B10: REAL | C10: 1.1.1 | D10: Veículo ‐ caminhonete 4x4 cabine dupla c/ motorista | E10: 2.3.2 | F10: =B10&D10 -> REALVeículo ‐ caminhonete 4x4 cabine dupla c/ motorista | G10: =Y10 -> 0.31666667 | H10: und x mês | I10: 1.6 | J10: 2 | K10: 2 | L10: 2 | V10: =SUM(I10:U10) -> 7.6 | W10: 12971.63 | X10: =W10*V10 -> 98584.388 | Y10: =X10/X9 -> 0.31666667 | AB10: =AA10*I10 -> 0
A11: 7 | B11: PREV | C11: 1.1.2 | D11: Veículo ‐ caminhonete 4x4 cabine dupla | E11: 2.3.1 | F11: =B11&D11 -> PREVVeículo ‐ caminhonete 4x4 cabine dupla | H11: und x mês | I11: 0.8 | J11: 1 | K11: 1 | L11: 1 | M11: 1 | N11: 1 | O11: 1 | P11: 1 | Q11: 1 | R11: 1 | S11: 1 | T11: 1 | U11: 0.2 | V11: =SUM(I11:U11) -> 12 | W11: 7919.19 | X11: =W11*V11 -> 95030.28
A12: 8 | B12: REAL | C12: 1.1.2 | D12: Veículo ‐ caminhonete 4x4 cabine dupla | E12: 2.3.1 | F12: =B12&D12 -> REALVeículo ‐ caminhonete 4x4 cabine dupla | G12: =Y12 -> 0.31666667 | H12: und x mês | I12: 0.8 | J12: 1 | K12: 1 | L12: 1 | V12: =SUM(I12:U12) -> 3.8 | W12: 7919.19 | X12: =W12*V12 -> 30092.922 | Y12: =X12/X11 -> 0.31666667 | Z12: 84 | AA12: =V11/Z12 -> 0.14285714 | AB12: =AA12*I12 -> 0.11428571
A13: 9 | B13: PREV | C13: 1.1.3 | D13: Veículo ‐ pick up 4x4 (E8891) ‐ Operativo + Improdutivo | E13: 2.3.3 | F13: =B13&D13 -> PREVVeículo ‐ pick up 4x4 (E8891) ‐ Operativo + Improdutivo | H13: und x mês | I13: 2.4 | J13: 3 | K13: 3 | L13: 3 | M13: 3 | N13: 3 | O13: 3 | P13: 3 | Q13: 3 | R13: 3 | S13: 3 | T13: 3 | U13: 0.6 | V13: =SUM(I13:U13) -> 36 | W13: 7459.55 | X13: =W13*V13 -> 268543.8
A14: 10 | B14: REAL | C14: 1.1.3 | D14: Veículo ‐ pick up 4x4 (E8891) ‐ Operativo + Improdutivo | E14: 2.3.3 | F14: =B14&D14 -> REALVeículo ‐ pick up 4x4 (E8891) ‐ Operativo + Improdutivo | G14: =Y14 -> 0.31666667 | H14: und x mês | I14: 2.4 | J14: 3 | K14: 3 | L14: 3 | V14: =SUM(I14:U14) -> 11.4 | W14: 7459.55 | X14: =W14*V14 -> 85038.87 | Y14: =X14/X13 -> 0.31666667 | Z14: 108 | AA14: =V13/Z14 -> 0.33333333 | AB14: =AA14*I14 -> 0.8
A15: 11 | B15: PREV | C15: 1.1.4 | D15: Veículo ‐ sedan 1.6 flex ‐ 115CV (E8889) ‐ Operativo + Improdutivo | E15: 2.3.4 | F15: =B15&D15 -> PREVVeículo ‐ sedan 1.6 flex ‐ 115CV (E8889) ‐ Operativo + Improdutivo | H15: und x mês | I15: 3.2 | J15: 4 | K15: 4 | L15: 4 | M15: 4 | N15: 4 | O15: 4 | P15: 4 | Q15: 4 | R15: 4 | S15: 4 | T15: 4 | U15: 0.8 | V15: =SUM(I15:U15) -> 48 | W15: 3155.45 | X15: =W15*V15 -> 151461.6
A16: 12 | B16: REAL | C16: 1.1.4 | D16: Veículo ‐ sedan 1.6 flex ‐ 115CV (E8889) ‐ Operativo + Improdutivo | E16: 2.3.4 | F16: =B16&D16 -> REALVeículo ‐ sedan 1.6 flex ‐ 115CV (E8889) ‐ Operativo + Improdutivo | G16: =Y16 -> 0.31666667 | H16: und x mês | I16: 3.2 | J16: 4 | K16: 4 | L16: 4 | V16: =SUM(I16:U16) -> 15.2 | W16: 3155.45 | X16: =W16*V16 -> 47962.84 | Y16: =X16/X15 -> 0.31666667 | Z16: 180 | AA16: =V15/Z16 -> 0.26666667
A17: 13 | B17: PREV | C17: 1.1.5 | D17: Ônibus com 45 lugares ‐ 218CV (com motorista ‐ incluindo combustível e manutenção) | E17: 2.3.6 | F17: =B17&D17 -> PREVÔnibus com 45 lugares ‐ 218CV (com motorista ‐ incluindo combustível e manutenção) | H17: und x mês | I17: 2.4 | J17: 3 | K17: 3 | L17: 3 | M17: 3 | N17: 3 | O17: 3 | P17: 3 | Q17: 3 | R17: 3 | S17: 3 | T17: 3 | U17: 0.6 | V17: =SUM(I17:U17) -> 36 | W17: 15838.37 | X17: =W17*V17 -> 570181.32
A18: 14 | B18: REAL | C18: 1.1.5 | D18: Ônibus com 45 lugares ‐ 218CV (com motorista ‐ incluindo combustível e manutenção) | E18: 2.3.6 | F18: =B18&D18 -> REALÔnibus com 45 lugares ‐ 218CV (com motorista ‐ incluindo combustível e manutenção) | G18: =Y18 -> 0.31666667 | H18: und x mês | I18: 2.4 | J18: 3 | K18: 3 | L18: 3 | V18: =SUM(I18:U18) -> 11.4 | W18: 15838.37 | X18: =W18*V18 -> 180557.42 | Y18: =X18/X17 -> 0.31666667 | AB18: =AA18*I18 -> 0
A19: 15 | B19: PREV | C19: 1.2 | D19: ESCRITÓRIO | E19: 2.4 | V19: 0 | W19: 0 | X19: =SUMIF(B21:B66,B19,X21:X66) -> 1512510.2
A20: 16 | B20: REAL | C20: 1.2 | D20: ESCRITÓRIO | E20: 2.4 | X20: =SUMIF(B21:B66,B20,X21:X66) -> 406928.63 | Y20: =X20/X19 -> 0.2690419
A21: 17 | B21: PREV | C21: 1.2.1 | D21: Aluguel de Impressora A3 | E21: 2.2.2 | F21: =B21&D21 -> PREVAluguel de Impressora A3 | H21: und x mês | I21: 0.8 | J21: 1 | K21: 1 | L21: 1 | M21: 1 | N21: 1 | O21: 1 | P21: 1 | Q21: 1 | R21: 1 | S21: 1 | T21: 1 | U21: 0.2 | V21: =SUM(I21:U21) -> 12 | W21: 177.77 | X21: =W21*V21 -> 2133.24
A22: 18 | B22: REAL | C22: 1.2.1 | D22: Aluguel de Impressora A3 | E22: 2.2.2 | F22: =B22&D22 -> REALAluguel de Impressora A3 | G22: =Y22 -> 0.31666667 | H22: und x mês | I22: 0.8 | J22: 1 | K22: 1 | L22: 1 | V22: =SUM(I22:U22) -> 3.8 | W22: 177.77 | X22: =W22*V22 -> 675.526 | Y22: =X22/X21 -> 0.31666667 | Z22: 36
A23: 19 | B23: PREV | C23: 1.2.2 | D23: Aluguel de Servidor | E23: 2.2.3 | F23: =B23&D23 -> PREVAluguel de Servidor | H23: und x mês | I23: 1.6 | J23: 2 | K23: 2 | L23: 2 | M23: 2 | N23: 2 | O23: 2 | P23: 2 | Q23: 2 | R23: 2 | S23: 2 | T23: 2 | U23: 0.4 | V23: =SUM(I23:U23) -> 24 | W23: 1350.87 | X23: =W23*V23 -> 32420.88
A24: 20 | B24: REAL | C24: 1.2.2 | D24: Aluguel de Servidor | E24: 2.2.3 | F24: =B24&D24 -> REALAluguel de Servidor | G24: =Y24 -> 0.31666667 | H24: und x mês | I24: 1.6 | J24: 2 | K24: 2 | L24: 2 | V24: =SUM(I24:U24) -> 7.6 | W24: 1350.87 | X24: =W24*V24 -> 10266.612 | Y24: =X24/X23 -> 0.31666667
A25: 21 | B25: PREV | C25: 1.2.3 | D25: Aluguel de Plotter | E25: 2.2.4 | F25: =B25&D25 -> PREVAluguel de Plotter | H25: und x mês | I25: 0.8 | J25: 1 | K25: 1 | L25: 1 | M25: 1 | N25: 1 | O25: 1 | P25: 1 | Q25: 1 | R25: 1 | S25: 1 | T25: 1 | U25: 0.2 | V25: =SUM(I25:U25) -> 12 | W25: 116.18 | X25: =W25*V25 -> 1394.16
A26: 22 | B26: REAL | C26: 1.2.3 | D26: Aluguel de Plotter | E26: 2.2.4 | F26: =B26&D26 -> REALAluguel de Plotter | G26: =Y26 -> 0.31666667 | H26: und x mês | I26: 0.8 | J26: 1 | K26: 1 | L26: 1 | V26: =SUM(I26:U26) -> 3.8 | W26: 116.18 | X26: =W26*V26 -> 441.484 | Y26: =X26/X25 -> 0.31666667
A27: 23 | B27: PREV | C27: 1.2.4 | D27: Câmera fotografica profissional DSLR, 18 MP, vídeos em Full HD, lente EF‐S 18‐ 55mm f/3.5‐5.6 III e bateria | E27: 2.4.6 | F27: =B27&D27 -> PREVCâmera fotografica profissional DSLR, 18 MP, vídeos em Full HD, lente EF‐S 18‐ 55mm f/3.5‐5.6 III e bateria | H27: und x mês | I27: 1.6 | J27: 2 | K27: 2 | L27: 2 | M27: 2 | N27: 2 | O27: 2 | P27: 2 | Q27: 2 | R27: 2 | S27: 2 | T27: 2 | U27: 0.4 | V27: =SUM(I27:U27) -> 24 | W27: 20.19 | X27: =W27*V27 -> 484.56
A28: 24 | B28: REAL | C28: 1.2.4 | D28: Câmera fotografica profissional DSLR, 18 MP, vídeos em Full HD, lente EF‐S 18‐ 55mm f/3.5‐5.6 III e bateria | E28: 2.4.6 | F28: =B28&D28 -> REALCâmera fotografica profissional DSLR, 18 MP, vídeos em Full HD, lente EF‐S 18‐ 55mm f/3.5‐5.6 III e bateria | G28: =Y28 -> 0.31666667 | H28: und x mês | I28: 1.6 | J28: 2 | K28: 2 | L28: 2 | V28: =SUM(I28:U28) -> 7.6 | W28: 20.19 | X28: =W28*V28 -> 153.444 | Y28: =X28/X27 -> 0.31666667
A29: 25 | B29: PREV | C29: 1.2.5 | D29: Binóculo Profissional Ampliação 8 à 24x 50mm | E29: 2.4.7 | F29: =B29&D29 -> PREVBinóculo Profissional Ampliação 8 à 24x 50mm | H29: und x mês | I29: 1.6 | J29: 2 | K29: 2 | L29: 2 | M29: 2 | N29: 2 | O29: 2 | P29: 2 | Q29: 2 | R29: 2 | S29: 2 | T29: 2 | U29: 0.4 | V29: =SUM(I29:U29) -> 24 | W29: 24.34 | X29: =W29*V29 -> 584.16
A30: 26 | B30: REAL | C30: 1.2.5 | D30: Binóculo Profissional Ampliação 8 à 24x 50mm | E30: 2.4.7 | F30: =B30&D30 -> REALBinóculo Profissional Ampliação 8 à 24x 50mm | G30: =Y30 -> 0.31666667 | H30: und x mês | I30: 1.6 | J30: 2 | K30: 2 | L30: 2 | V30: =SUM(I30:U30) -> 7.6 | W30: 24.34 | X30: =W30*V30 -> 184.984 | Y30: =X30/X29 -> 0.31666667
A31: 27 | B31: PREV | C31: 1.2.6 | D31: Imóvel Comercial ‐ Escritório + Almox (B8951) ‐ 150 m² | E31: 2.4.1 | F31: =B31&D31 -> PREVImóvel Comercial ‐ Escritório + Almox (B8951) ‐ 150 m² | H31: und x mês | I31: 1.6 | J31: 2 | K31: 2 | L31: 2 | M31: 2 | N31: 2 | O31: 2 | P31: 2 | Q31: 2 | R31: 2 | S31: 2 | T31: 2 | U31: 0.4 | V31: =SUM(I31:U31) -> 24 | W31: 7471.5 | X31: =W31*V31 -> 179316
A32: 28 | B32: REAL | C32: 1.2.6 | D32: Imóvel Comercial ‐ Escritório + Almox (B8951) ‐ 150 m² | E32: 2.4.1 | F32: =B32&D32 -> REALImóvel Comercial ‐ Escritório + Almox (B8951) ‐ 150 m² | G32: =Y32 -> 0.475 | H32: und x mês | I32: 2.4 | J32: 3 | K32: 3 | L32: 3 | V32: =SUM(I32:U32) -> 11.4 | W32: 7471.5 | X32: =W32*V32 -> 85175.1 | Y32: =X32/X31 -> 0.475
A33: 29 | B33: PREV | C33: 1.2.7 | D33: Mobiliário para escritório (B8953) | E33: 2.4.2 | F33: =B33&D33 -> PREVMobiliário para escritório (B8953) | H33: ocupante x mês | I33: 19.2 | J33: 24 | K33: 24 | L33: 24 | M33: 24 | N33: 24 | O33: 24 | P33: 24 | Q33: 24 | R33: 24 | S33: 24 | T33: 24 | U33: 4.8 | V33: =SUM(I33:U33) -> 288 | W33: 677.68 | X33: =W33*V33 -> 195171.84
A34: 30 | B34: REAL | C34: 1.2.7 | D34: Mobiliário para escritório (B8953) | E34: 2.4.2 | F34: =B34&D34 -> REALMobiliário para escritório (B8953) | G34: =Y34 -> 0.31666667 | H34: ocupante x mês | I34: 19.2 | J34: 24 | K34: 24 | L34: 24 | V34: =SUM(I34:U34) -> 91.2 | W34: 677.68 | X34: =W34*V34 -> 61804.416 | Y34: =X34/X33 -> 0.31666667
A35: 31 | B35: PREV | C35: 1.2.8 | D35: Custos Diversos ‐ Escritório (B8959) | E35: 2.4.3 | F35: =B35&D35 -> PREVCustos Diversos ‐ Escritório (B8959) | H35: ocupante x mês | I35: 19.2 | J35: 24 | K35: 24 | L35: 24 | M35: 24 | N35: 24 | O35: 24 | P35: 24 | Q35: 24 | R35: 24 | S35: 24 | T35: 24 | U35: 4.8 | V35: =SUM(I35:U35) -> 288 | W35: 153.25 | X35: =W35*V35 -> 44136
A36: 32 | B36: REAL | C36: 1.2.8 | D36: Custos Diversos ‐ Escritório (B8959) | E36: 2.4.3 | F36: =B36&D36 -> REALCustos Diversos ‐ Escritório (B8959) | G36: =Y36 -> 0.31666667 | H36: ocupante x mês | I36: 19.2 | J36: 24 | K36: 24 | L36: 24 | V36: =SUM(I36:U36) -> 91.2 | W36: 153.25 | X36: =W36*V36 -> 13976.4 | Y36: =X36/X35 -> 0.31666667
A37: 33 | B37: PREV | C37: 1.2.9 | D37: GPS de Navegação | E37: 2.4.4 | F37: =B37&D37 -> PREVGPS de Navegação | H37: und x mês | I37: 0.8 | J37: 1 | K37: 1 | L37: 1 | M37: 1 | N37: 1 | O37: 1 | P37: 1 | Q37: 1 | R37: 1 | S37: 1 | T37: 1 | U37: 0.2 | V37: =SUM(I37:U37) -> 12 | W37: 50.58 | X37: =W37*V37 -> 606.96
A38: 34 | B38: REAL | C38: 1.2.9 | D38: GPS de Navegação | E38: 2.4.4 | F38: =B38&D38 -> REALGPS de Navegação | G38: =Y38 -> 0.31666667 | H38: und x mês | I38: 0.8 | J38: 1 | K38: 1 | L38: 1 | V38: =SUM(I38:U38) -> 3.8 | W38: 50.58 | X38: =W38*V38 -> 192.204 | Y38: =X38/X37 -> 0.31666667 | Z38: 144
A39: 35 | B39: PREV | C39: 1.2.10 | D39: Câmera fotográfica | E39: 2.4.5 | F39: =B39&D39 -> PREVCâmera fotográfica | H39: und x mês | I39: 1.6 | J39: 2 | K39: 2 | L39: 2 | M39: 2 | N39: 2 | O39: 2 | P39: 2 | Q39: 2 | R39: 2 | S39: 2 | T39: 2 | U39: 0.4 | V39: =SUM(I39:U39) -> 24 | W39: 10.1 | X39: =W39*V39 -> 242.4
A40: 36 | B40: REAL | C40: 1.2.10 | D40: Câmera fotográfica | E40: 2.4.5 | F40: =B40&D40 -> REALCâmera fotográfica | G40: =Y40 -> 0.31666667 | H40: und x mês | I40: 1.6 | J40: 2 | K40: 2 | L40: 2 | V40: =SUM(I40:U40) -> 7.6 | W40: 10.1 | X40: =W40*V40 -> 76.76 | Y40: =X40/X39 -> 0.31666667 | Z40: 156
A41: 37 | B41: PREV | C41: 1.2.11 | D41: Viagens Aéreas ‐ 1 trecho (ida) | E41: 2.1.1 | F41: =B41&D41 -> PREVViagens Aéreas ‐ 1 trecho (ida) | H41: und | I41: 6.4 | J41: 8 | K41: 8 | L41: 8 | M41: 8 | N41: 8 | O41: 8 | P41: 8 | Q41: 8 | R41: 8 | S41: 8 | U41: 0 | V41: =SUM(I41:U41) -> 86.4 | W41: 693.79 | X41: =W41*V41 -> 59943.456
A42: 38 | B42: REAL | C42: 1.2.11 | D42: Viagens Aéreas ‐ 1 trecho (ida) | E42: 2.1.1 | F42: =B42&D42 -> REALViagens Aéreas ‐ 1 trecho (ida) | G42: =Y42 -> 0.011574074 | H42: und | I42: 0 | J42: 0 | K42: 1 | L42: 0 | V42: =SUM(I42:U42) -> 1 | W42: 693.79 | X42: =W42*V42 -> 693.79 | Y42: =X42/X41 -> 0.011574074
A43: 39 | B43: PREV | C43: 1.2.12 | D43: Viagens Aéreas ‐ 1 trecho (volta) | E43: 2.1.2 | F43: =B43&D43 -> PREVViagens Aéreas ‐ 1 trecho (volta) | H43: und | J43: 8 | K43: 8 | L43: 8 | M43: 8 | N43: 8 | O43: 8 | P43: 8 | Q43: 8 | R43: 8 | S43: 8 | T43: 10 | U43: 2 | V43: =SUM(I43:U43) -> 92 | W43: 693.79 | X43: =W43*V43 -> 63828.68
A44: 40 | B44: REAL | C44: 1.2.12 | D44: Viagens Aéreas ‐ 1 trecho (volta) | E44: 2.1.2 | F44: =B44&D44 -> REALViagens Aéreas ‐ 1 trecho (volta) | G44: =Y44 -> 0.010869565 | H44: und | I44: 0 | J44: 0 | K44: 1 | L44: 0 | V44: =SUM(I44:U44) -> 1 | W44: 693.79 | X44: =W44*V44 -> 693.79 | Y44: =X44/X43 -> 0.010869565
A45: 41 | B45: PREV | C45: 1.2.13 | D45: Viagens Terrestres ‐ 1 trecho (ida) | E45: 2.1.3 | F45: =B45&D45 -> PREVViagens Terrestres ‐ 1 trecho (ida) | H45: und x mês | I45: 1.6 | J45: 2 | K45: 73 | L45: 73 | M45: 73 | N45: 2 | O45: 2 | P45: 2 | Q45: 73 | R45: 2 | S45: 73 | T45: 0 | U45: 0 | V45: =SUM(I45:U45) -> 376.6 | W45: 183.09 | X45: =W45*V45 -> 68951.694
A46: 42 | B46: REAL | C46: 1.2.13 | D46: Viagens Terrestres ‐ 1 trecho (ida) | E46: 2.1.3 | F46: =B46&D46 -> REALViagens Terrestres ‐ 1 trecho (ida) | G46: =Y46 -> 0 | H46: und x mês | I46: 0 | J46: 0 | K46: 0 | L46: 0 | V46: =SUM(I46:U46) -> 0 | W46: 183.09 | X46: =W46*V46 -> 0 | Y46: =X46/X45 -> 0
A47: 43 | B47: PREV | C47: 1.2.14 | D47: Viagens Terrestres ‐ 1 trecho (volta) | E47: 2.1.4 | F47: =B47&D47 -> PREVViagens Terrestres ‐ 1 trecho (volta) | H47: und x mês | J47: 2 | K47: 73 | L47: 73 | M47: 73 | N47: 2 | O47: 2 | P47: 2 | Q47: 73 | R47: 2 | S47: 73 | T47: 71 | U47: 14.2 | V47: =SUM(I47:U47) -> 460.2 | W47: 183.09 | X47: =W47*V47 -> 84258.018
A48: 44 | B48: REAL | C48: 1.2.14 | D48: Viagens Terrestres ‐ 1 trecho (volta) | E48: 2.1.4 | F48: =B48&D48 -> REALViagens Terrestres ‐ 1 trecho (volta) | G48: =Y48 -> 0 | H48: und x mês | I48: 0 | J48: 0 | K48: 0 | L48: 0 | V48: =SUM(I48:U48) -> 0 | W48: 183.09 | X48: =W48*V48 -> 0 | Y48: =X48/X47 -> 0
A49: 45 | B49: PREV | C49: 1.2.15 | D49: Diárias Nacionais | E49: 2.1.5 | F49: =B49&D49 -> PREVDiárias Nacionais | H49: und x mês | I49: 24 | J49: 30 | K49: 30 | L49: 30 | M49: 30 | N49: 30 | O49: 30 | P49: 30 | Q49: 30 | R49: 30 | S49: 30 | T49: 30 | U49: 6 | V49: =SUM(I49:U49) -> 360 | W49: 260.62 | X49: =W49*V49 -> 93823.2
A50: 46 | B50: REAL | C50: 1.2.15 | D50: Diárias Nacionais | E50: 2.1.5 | F50: =B50&D50 -> REALDiárias Nacionais | G50: =Y50 -> 0.16944444 | H50: und x mês | I50: 8.5 | J50: 13 | K50: 23.5 | L50: 16 | V50: =SUM(I50:U50) -> 61 | W50: 260.62 | X50: =W50*V50 -> 15897.82 | Y50: =X50/X49 -> 0.16944444
A51: 47 | B51: PREV | C51: 1.2.16 | D51: Alojamento Nível Superior (aluguel de casa + mobiliário) | F51: =B51&D51 -> PREVAlojamento Nível Superior (aluguel de casa + mobiliário) | H51: und | V51: =SUM(I51:U51) -> 0 | W51: 0 | X51: =W51*V51 -> 0
A52: 48 | B52: REAL | C52: 1.2.16 | D52: Alojamento Nível Superior (aluguel de casa + mobiliário) | F52: =B52&D52 -> REALAlojamento Nível Superior (aluguel de casa + mobiliário) | G52: =Y52 -> 0 | H52: und | I52: 0 | J52: 0 | K52: 0 | L52: 0 | V52: =SUM(I52:U52) -> 0 | W52: 0 | X52: =W52*V52 -> 0
A53: 49 | B53: PREV | C53: 1.2.17 | D53: Imóvel Residencial (B8952) | E53: 2.6.1 | F53: =B53&D53 -> PREVImóvel Residencial (B8952) | H53: m² x mês | I53: 119.136 | J53: 148.92 | K53: 148.92 | L53: 148.92 | M53: 148.92 | N53: 148.92 | O53: 148.92 | P53: 148.92 | Q53: 148.92 | R53: 148.92 | S53: 148.92 | T53: 148.92 | U53: 29.784 | V53: =SUM(I53:U53) -> 1787.04 | W53: 32.57 | X53: =W53*V53 -> 58203.893
A54: 50 | B54: REAL | C54: 1.2.17 | D54: Imóvel Residencial (B8952) | E54: 2.6.1 | F54: =B54&D54 -> REALImóvel Residencial (B8952) | G54: =Y54 -> 0.31666667 | H54: m² x mês | I54: 119.136 | J54: 148.92 | K54: 148.92 | L54: 148.92 | V54: =SUM(I54:U54) -> 565.896 | W54: 32.57 | X54: =W54*V54 -> 18431.233 | Y54: =X54/X53 -> 0.31666667 | Z54: 12062.52
A55: 51 | B55: PREV | C55: 1.2.18 | D55: Mobiliário para Residência (B8954) | E55: 2.6.2 | F55: =B55&D55 -> PREVMobiliário para Residência (B8954) | H55: R$/m² x mês | I55: 9.6 | J55: 12 | K55: 12 | L55: 12 | M55: 12 | N55: 12 | O55: 12 | P55: 12 | Q55: 12 | R55: 12 | S55: 12 | T55: 12 | U55: 2.4 | V55: =SUM(I55:U55) -> 144 | W55: 42.9 | X55: =W55*V55 -> 6177.6
A56: 52 | B56: REAL | C56: 1.2.18 | D56: Mobiliário para Residência (B8954) | E56: 2.6.2 | F56: =B56&D56 -> REALMobiliário para Residência (B8954) | G56: =Y56 -> 0.31666667 | H56: R$/m² x mês | I56: 9.6 | J56: 12 | K56: 12 | L56: 12 | V56: =SUM(I56:U56) -> 45.6 | W56: 42.9 | X56: =W56*V56 -> 1956.24 | Y56: =X56/X55 -> 0.31666667 | Z56: 972
A57: 53 | B57: PREV | C57: 1.2.19 | D57: Custos Diversos ‐ Residência (B8960) | E57: 2.6.3 | F57: =B57&D57 -> PREVCustos Diversos ‐ Residência (B8960) | H57: R$ x ocupante/mês | I57: 9.6 | J57: 12 | K57: 12 | L57: 12 | M57: 12 | N57: 12 | O57: 12 | P57: 12 | Q57: 12 | R57: 12 | S57: 12 | T57: 12 | U57: 2.4 | V57: =SUM(I57:U57) -> 144 | W57: 257.86 | X57: =W57*V57 -> 37131.84
A58: 54 | B58: REAL | C58: 1.2.19 | D58: Custos Diversos ‐ Residência (B8960) | E58: 2.6.3 | F58: =B58&D58 -> REALCustos Diversos ‐ Residência (B8960) | G58: =Y58 -> 0.31666667 | H58: R$ x ocupante/mês | I58: 9.6 | J58: 12 | K58: 12 | L58: 12 | V58: =SUM(I58:U58) -> 45.6 | W58: 257.86 | X58: =W58*V58 -> 11758.416 | Y58: =X58/X57 -> 0.31666667 | Z58: 972
A59: 55 | B59: PREV | C59: 1.2.20 | D59: Alojamento Nível Médio (aluguel de república + mobiliário) | F59: =B59&D59 -> PREVAlojamento Nível Médio (aluguel de república + mobiliário) | V59: =SUM(I59:U59) -> 0 | W59: 0 | X59: =W59*V59 -> 0
A60: 56 | B60: REAL | C60: 1.2.20 | D60: Alojamento Nível Médio (aluguel de república + mobiliário) | F60: =B60&D60 -> REALAlojamento Nível Médio (aluguel de república + mobiliário) | G60: =Y60 -> 0 | I60: 0 | J60: 0 | K60: 0 | L60: 0 | V60: =SUM(I60:U60) -> 0 | W60: 0 | X60: =W60*V60 -> 0
A61: 57 | B61: PREV | C61: 1.2.21 | D61: Imóvel Residencial (B8952) | E61: 2.6.1 | F61: =B61&D61 -> PREVImóvel Residencial (B8952) | H61: m² x mês | I61: 685.032 | J61: 856.29 | K61: 856.29 | L61: 856.29 | M61: 856.29 | N61: 856.29 | O61: 856.29 | P61: 856.29 | Q61: 856.29 | R61: 856.29 | S61: 856.29 | T61: 856.29 | U61: 171.258 | V61: =SUM(I61:U61) -> 10275.48 | W61: 32.57 | X61: =W61*V61 -> 334672.38
A62: 58 | B62: REAL | C62: 1.2.21 | D62: Imóvel Residencial (B8952) | E62: 2.6.1 | F62: =B62&D62 -> REALImóvel Residencial (B8952) | G62: =Y62 -> 0.31670345 | H62: m² x mês | I62: 685.032 | J62: 856.29 | K62: 856.5 | L62: 856.458 | V62: =SUM(I62:U62) -> 3254.28 | W62: 32.57 | X62: =W62*V62 -> 105991.9 | Y62: =X62/X61 -> 0.31670345 | Z62: 12062.52
A63: 59 | B63: PREV | C63: 1.2.22 | D63: Mobiliário para Residência (B8954) | E63: 2.6.2 | F63: =B63&D63 -> PREVMobiliário para Residência (B8954) | H63: R$/m² x mês | I63: 55.2 | J63: 69 | K63: 69 | L63: 69 | M63: 69 | N63: 69 | O63: 69 | P63: 69 | Q63: 69 | R63: 69 | S63: 69 | T63: 69 | U63: 13.8 | V63: =SUM(I63:U63) -> 828 | W63: 42.9 | X63: =W63*V63 -> 35521.2
A64: 60 | B64: REAL | C64: 1.2.22 | D64: Mobiliário para Residência (B8954) | E64: 2.6.2 | F64: =B64&D64 -> REALMobiliário para Residência (B8954) | G64: =Y64 -> 0.31545894 | H64: R$/m² x mês | I64: 54.2 | J64: 69 | K64: 69 | L64: 69 | V64: =SUM(I64:U64) -> 261.2 | W64: 42.9 | X64: =W64*V64 -> 11205.48 | Y64: =X64/X63 -> 0.31545894 | Z64: 972
A65: 61 | B65: PREV | C65: 1.2.23 | D65: Custos Diversos ‐ Residência (B8960) | E65: 2.6.3 | F65: =B65&D65 -> PREVCustos Diversos ‐ Residência (B8960) | H65: R$ x ocupante/mês | I65: 55.2 | J65: 69 | K65: 69 | L65: 69 | M65: 69 | N65: 69 | O65: 69 | P65: 69 | Q65: 69 | R65: 69 | S65: 69 | T65: 69 | U65: 13.8 | V65: =SUM(I65:U65) -> 828 | W65: 257.86 | X65: =W65*V65 -> 213508.08
A66: 62 | B66: REAL | C66: 1.2.23 | D66: Custos Diversos ‐ Residência (B8960) | E66: 2.6.3 | F66: =B66&D66 -> REALCustos Diversos ‐ Residência (B8960) | G66: =Y66 -> 0.31545894 | H66: R$ x ocupante/mês | I66: 54.2 | J66: 69 | K66: 69 | L66: 69 | V66: =SUM(I66:U66) -> 261.2 | W66: 257.86 | X66: =W66*V66 -> 67353.032 | Y66: =X66/X65 -> 0.31545894 | Z66: 972
A67: 63 | B67: PREV | C67: 1.3 | D67: SISTEMA DE RÁDIO COMUNICAÇÃO | E67: 2.5 | V67: 0 | W67: 0 | X67: 0
A68: 64 | B68: REAL | C68: 1.3 | D68: SISTEMA DE RÁDIO COMUNICAÇÃO | E68: 2.5 | V68: 0 | W68: 0 | X68: 0
A69: 65 | B69: PREV | C69: 1.3.1 | D69: SISTEMA DE RÁDIO COMUNICAÇÃO ‐ EIXO NORTE | V69: 0 | W69: 0 | X69: =SUMIF(B71:B80,B69,X71:X80) -> 236359.39
A70: 66 | B70: REAL | C70: 1.3.1 | D70: SISTEMA DE RÁDIO COMUNICAÇÃO ‐ EIXO NORTE | V70: 0 | W70: 0 | X70: =SUMIF(B71:B80,B70,X71:X80) -> 60826.472 | Y70: =X70/X69 -> 0.25734739
A71: 67 | B71: PREV | C71: 1.3.1.1 | D71: Sistema de repetidoras VHF interligadas com link UHF ‐ 4 antenas | E71: 2.5.1 | F71: =B71&D71 -> PREVSistema de repetidoras VHF interligadas com link UHF ‐ 4 antenas | H71: mês | I71: 0.8 | J71: 1 | K71: 1 | L71: 1 | M71: 1 | N71: 1 | O71: 1 | P71: 1 | Q71: 1 | R71: 1 | S71: 1 | T71: 1 | U71: 0.2 | V71: =SUM(I71:U71) -> 12 | W71: 13317.48 | X71: =W71*V71 -> 159809.76
A72: 68 | B72: REAL | C72: 1.3.1.1 | D72: Sistema de repetidoras VHF interligadas com link UHF ‐ 4 antenas | E72: 2.5.1 | F72: =B72&D72 -> REALSistema de repetidoras VHF interligadas com link UHF ‐ 4 antenas | G72: =Y72 -> 0.16666667 | H72: mês | I72: 0 | J72: 0 | K72: 1 | L72: 1 | V72: =SUM(I72:U72) -> 2 | W72: 13317.48 | X72: =W72*V72 -> 26634.96 | Y72: =X72/X71 -> 0.16666667 | Z72: 24
A73: 69 | B73: PREV | C73: 1.3.1.2 | D73: Rádio VHF portátil EP 450 | E73: 2.5.3 | F73: =B73&D73 -> PREVRádio VHF portátil EP 450 | H73: und x mês | I73: 8 | J73: 10 | K73: 10 | L73: 10 | M73: 10 | N73: 10 | O73: 10 | P73: 10 | Q73: 10 | R73: 10 | S73: 10 | T73: 10 | U73: 2 | V73: =SUM(I73:U73) -> 120 | W73: 119.86 | X73: =W73*V73 -> 14383.2
A74: 70 | B74: REAL | C74: 1.3.1.2 | D74: Rádio VHF portátil EP 450 | E74: 2.5.3 | F74: =B74&D74 -> REALRádio VHF portátil EP 450 | G74: =Y74 -> 0.32333333 | H74: und x mês | I74: 8.8 | J74: 10 | K74: 10 | L74: 10 | V74: =SUM(I74:U74) -> 38.8 | W74: 119.86 | X74: =W74*V74 -> 4650.568 | Y74: =X74/X73 -> 0.32333333 | Z74: 240
A75: 71 | B75: PREV | C75: 1.3.1.3 | D75: Rádio VHF móvel digital para viatura (eixo norte) | E75: 2.5.4 | F75: =B75&D75 -> PREVRádio VHF móvel digital para viatura (eixo norte) | H75: und x mês | I75: 7.2 | J75: 9 | K75: 9 | L75: 9 | M75: 9 | N75: 9 | O75: 9 | P75: 9 | Q75: 9 | R75: 9 | S75: 9 | T75: 9 | U75: 1.8 | V75: =SUM(I75:U75) -> 108 | W75: 279.67 | X75: =W75*V75 -> 30204.36
A76: 72 | B76: REAL | C76: 1.3.1.3 | D76: Rádio VHF móvel digital para viatura (eixo norte) | E76: 2.5.4 | F76: =B76&D76 -> REALRádio VHF móvel digital para viatura (eixo norte) | G76: =Y76 -> 0.31666667 | H76: und x mês | I76: 7.2 | J76: 9 | K76: 9 | L76: 9 | V76: =SUM(I76:U76) -> 34.2 | W76: 279.67 | X76: =W76*V76 -> 9564.714 | Y76: =X76/X75 -> 0.31666667 | Z76: 228
A77: 73 | B77: PREV | C77: 1.3.1.4 | D77: Rádio VHF para instalação nas SEs, composto por rádio base e sistema irradiante | E77: 2.5.5 | F77: =B77&D77 -> PREVRádio VHF para instalação nas SEs, composto por rádio base e sistema irradiante | H77: und x mês | I77: 2.4 | J77: 3 | K77: 3 | L77: 3 | M77: 3 | N77: 3 | O77: 3 | P77: 3 | Q77: 3 | R77: 3 | S77: 3 | T77: 3 | U77: 0.6 | V77: =SUM(I77:U77) -> 36 | W77: 332.94 | X77: =W77*V77 -> 11985.84
A78: 74 | B78: REAL | C78: 1.3.1.4 | D78: Rádio VHF para instalação nas SEs, composto por rádio base e sistema irradiante | E78: 2.5.5 | F78: =B78&D78 -> REALRádio VHF para instalação nas SEs, composto por rádio base e sistema irradiante | G78: =Y78 -> 0 | H78: und x mês | I78: 0 | J78: 0 | K78: 0 | L78: 0 | V78: =SUM(I78:U78) -> 0 | W78: 332.94 | X78: =W78*V78 -> 0 | Y78: =X78/X77 -> 0 | Z78: 108
A79: 75 | B79: PREV | C79: 1.3.1.5 | D79: Serviço de instalação e configuração de sistema de repetidoras e infraestrutura ‐ 4 antenas | E79: 2.5.6 | F79: =B79&D79 -> PREVServiço de instalação e configuração de sistema de repetidoras e infraestrutura ‐ 4 antenas | H79: und | I79: 1 | V79: =SUM(I79:U79) -> 1 | W79: 19976.23 | X79: =W79*I79 -> 19976.23
A80: 76 | B80: REAL | C80: 1.3.1.5 | D80: Serviço de instalação e configuração de sistema de repetidoras e infraestrutura ‐ 4 antenas | E80: 2.5.6 | F80: =B80&D80 -> REALServiço de instalação e configuração de sistema de repetidoras e infraestrutura ‐ 4 antenas | G80: =Y80 -> 1 | H80: und | I80: 0 | J80: 0 | K80: 1 | L80: 0 | V80: =SUM(I80:U80) -> 1 | W80: 19976.23 | X80: =W80*V80 -> 19976.23 | Y80: =X80/X79 -> 1 | Z80: 2
A81: 77 | B81: PREV | C81: 1.3.2 | D81: SISTEMA DE RÁDIO COMUNICAÇÃO ‐ EIXO LESTE | V81: 0 | W81: 0 | X81: =SUMIF(B83:B96,B81,X83:X96) -> 342260.13
A82: 78 | B82: REAL | C82: 1.3.2 | D82: SISTEMA DE RÁDIO COMUNICAÇÃO ‐ EIXO LESTE | V82: 0 | W82: 0 | X82: =SUMIF(B83:B96,B82,X83:X96) -> 86968.694 | Y82: =X82/X81 -> 0.25410115
A83: 79 | B83: PREV | C83: 1.3.2.1 | D83: Sistema de repetidoras VHF interligadas com link UHF ‐ 4 antenas | E83: 2.5.1 | F83: =B83&D83 -> PREVSistema de repetidoras VHF interligadas com link UHF ‐ 4 antenas | H83: mês | I83: 0.8 | J83: 1 | K83: 1 | L83: 1 | M83: 1 | N83: 1 | O83: 1 | P83: 1 | Q83: 1 | R83: 1 | S83: 1 | T83: 1 | U83: 0.2 | V83: =SUM(I83:U83) -> 12 | W83: 13317.48 | X83: =W83*V83 -> 159809.76
A84: 80 | B84: REAL | C84: 1.3.2.1 | D84: Sistema de repetidoras VHF interligadas com link UHF ‐ 4 antenas | E84: 2.5.1 | F84: =B84&D84 -> REALSistema de repetidoras VHF interligadas com link UHF ‐ 4 antenas | G84: =Y84 -> 0.16666667 | H84: mês | I84: 0 | J84: 0 | K84: 1 | L84: 1 | V84: =SUM(I84:U84) -> 2 | W84: 13317.48 | X84: =W84*V84 -> 26634.96 | Y84: =X84/X83 -> 0.16666667 | Z84: 24
A85: 81 | B85: PREV | C85: 1.3.2.2 | D85: Sistema de repetidoras VHF interligadas com link UHF ‐ 2 antenas | E85: 2.5.2 | F85: =B85&D85 -> PREVSistema de repetidoras VHF interligadas com link UHF ‐ 2 antenas | H85: mês | I85: 0.8 | J85: 1 | K85: 1 | L85: 1 | M85: 1 | N85: 1 | O85: 1 | P85: 1 | Q85: 1 | R85: 1 | S85: 1 | T85: 1 | U85: 0.2 | V85: =SUM(I85:U85) -> 12 | W85: 6658.74 | X85: =W85*V85 -> 79904.88
A86: 82 | B86: REAL | C86: 1.3.2.2 | D86: Sistema de repetidoras VHF interligadas com link UHF ‐ 2 antenas | E86: 2.5.2 | F86: =B86&D86 -> REALSistema de repetidoras VHF interligadas com link UHF ‐ 2 antenas | G86: =Y86 -> 0.31666667 | H86: mês | I86: 0.8 | J86: 1 | K86: 1 | L86: 1 | V86: =SUM(I86:U86) -> 3.8 | W86: 6658.74 | X86: =W86*V86 -> 25303.212 | Y86: =X86/X85 -> 0.31666667
A87: 83 | B87: PREV | C87: 1.3.2.3 | D87: Rádio VHF portátil EP 450 | E87: 2.5.3 | F87: =B87&D87 -> PREVRádio VHF portátil EP 450 | H87: und x mês | I87: 8 | J87: 10 | K87: 10 | L87: 10 | M87: 10 | N87: 10 | O87: 10 | P87: 10 | Q87: 10 | R87: 10 | S87: 10 | T87: 10 | U87: 2 | V87: =SUM(I87:U87) -> 120 | W87: 119.86 | X87: =W87*V87 -> 14383.2
A88: 84 | B88: REAL | C88: 1.3.2.3 | D88: Rádio VHF portátil EP 450 | E88: 2.5.3 | F88: =B88&D88 -> REALRádio VHF portátil EP 450 | G88: =Y88 -> 0.32333333 | H88: und x mês | I88: 8.8 | J88: 10 | K88: 10 | L88: 10 | V88: =SUM(I88:U88) -> 38.8 | W88: 119.86 | X88: =W88*V88 -> 4650.568 | Y88: =X88/X87 -> 0.32333333 | Z88: 240
A89: 85 | B89: PREV | C89: 1.3.2.4 | D89: Rádio VHF móvel digital para viatura (eixo leste) | E89: 2.5.4 | F89: =B89&D89 -> PREVRádio VHF móvel digital para viatura (eixo leste) | H89: und x mês | I89: 8 | J89: 10 | K89: 10 | L89: 10 | M89: 10 | N89: 10 | O89: 10 | P89: 10 | Q89: 10 | R89: 10 | S89: 10 | T89: 10 | U89: 2 | V89: =SUM(I89:U89) -> 120 | W89: 279.67 | X89: =W89*V89 -> 33560.4
A90: 86 | B90: REAL | C90: 1.3.2.4 | D90: Rádio VHF móvel digital para viatura (eixo leste) | E90: 2.5.4 | F90: =B90&D90 -> REALRádio VHF móvel digital para viatura (eixo leste) | G90: =Y90 -> 0.31 | H90: und x mês | I90: 7.2 | J90: 10 | K90: 10 | L90: 10 | V90: =SUM(I90:U90) -> 37.2 | W90: 279.67 | X90: =W90*V90 -> 10403.724 | Y90: =X90/X89 -> 0.31 | Z90: 228
A91: 87 | B91: PREV | C91: 1.3.2.5 | D91: Rádio VHF para instalação nas EB's, composto por rádio base e sistema irradiante | E91: 2.5.5 | F91: =B91&D91 -> PREVRádio VHF para instalação nas EB's, composto por rádio base e sistema irradiante | H91: und x mês | I91: 4.8 | J91: 6 | K91: 6 | L91: 6 | M91: 6 | N91: 6 | O91: 6 | P91: 6 | Q91: 6 | R91: 6 | S91: 6 | T91: 6 | U91: 1.2 | V91: =SUM(I91:U91) -> 72 | W91: 332.94 | X91: =W91*V91 -> 23971.68
A92: 88 | B92: REAL | C92: 1.3.2.5 | D92: Rádio VHF para instalação nas EB's, composto por rádio base e sistema irradiante | E92: 2.5.5 | F92: =B92&D92 -> REALRádio VHF para instalação nas EB's, composto por rádio base e sistema irradiante | G92: =Y92 -> 0 | H92: und x mês | I92: 0 | J92: 0 | K92: 0 | L92: 0 | V92: =SUM(I92:U92) -> 0 | W92: 332.94 | X92: =W92*V92 -> 0 | Y92: =X92/X91 -> 0 | Z92: 108
A93: 89 | B93: PREV | C93: 1.3.2.6 | D93: Serviço de instalação e configuração de sistema de repetidoras e infraestrutura ‐ 4 antenas | E93: 2.5.6 | F93: =B93&D93 -> PREVServiço de instalação e configuração de sistema de repetidoras e infraestrutura ‐ 4 antenas | H93: und | I93: 1 | V93: =SUM(I93:U93) -> 1 | W93: 19976.23 | X93: =W93*V93 -> 19976.23
A94: 90 | B94: REAL | C94: 1.3.2.6 | E94: 2.5.6 | F94: =B94&D94 -> REAL | G94: =Y94 -> 1 | H94: und | I94: 0 | J94: 0 | K94: 1 | L94: 0 | V94: =SUM(I94:U94) -> 1 | W94: 19976.23 | X94: =W94*V94 -> 19976.23 | Y94: =X94/X93 -> 1 | Z94: 2
A95: 91 | B95: PREV | C95: 1.3.2.7 | D95: Serviço de instalação e configuração de sistema de repetidoras e infraestrutura ‐ 2 antenas | E95: 2.5.7 | F95: =B95&D95 -> PREVServiço de instalação e configuração de sistema de repetidoras e infraestrutura ‐ 2 antenas | H95: und | I95: 1 | V95: =SUM(I95:U95) -> 1 | W95: 10653.98 | X95: =W95*V95 -> 10653.98
A96: 92 | B96: REAL | C96: 1.3.2.7 | D96: Serviço de instalação e configuração de sistema de repetidoras e infraestrutura ‐ 2 antenas | E96: 2.5.7 | F96: =B96&D96 -> REALServiço de instalação e configuração de sistema de repetidoras e infraestrutura ‐ 2 antenas | G96: =Y96 -> 0 | H96: und | I96: 0 | J96: 0 | K96: 0 | L96: 0 | V96: =SUM(I96:U96) -> 0 | W96: 10653.98 | X96: =W96*V96 -> 0 | Y96: =X96/X95 -> 0
A97: 93 | B97: PREV | C97: SUBTOTAL - ITEM 1 | R97: 0 | U97: 0
A98: 94 | B98: REAL | C98: SUBTOTAL - ITEM 1
A99: 95 | B99: PREV | C99: 2 | D99: OPERAÇÃO SISTEMA ELÉTRICO | V99: 0 | W99: 0 | X99: 0
A100: 96 | B100: REAL | C100: 2 | D100: OPERAÇÃO SISTEMA ELÉTRICO | V100: 0 | W100: 0 | X100: 0
...

Sheet MÃO DE OBRA- P x R
C1: MODELO 11C - PLANILHA REFERENCIAL DE PREÇOS (COM DESONERAÇÃO)
C2: Item | D2: Descrição | E2: Classe | F2: Unidade | G2: Meses | T2: Quantidade | U2: Preço Unitário | V2: Total | W2: PERCENTUAL MEDIDO
G3: 24.1 | H3: 25 | I3: 26 | J3: 27 | K3: 28 | L3: 29 | M3: 30 | N3: 31 | O3: 32 | P3: 33 | Q3: 34 | R3: 35 | S3: 36
G4: jul | H4: ago | I4: set | J4: out | K4: nov | L4: dez | M4: jan | N4: fev | O4: mar | P4: abr | Q4: mai | R4: jun | S4: jul
A5: 1 | B5: PREV | C5: 1 | D5: GESTÃO DO CONTRATO
A6: 2 | B6: REAL | C6: 1 | D6: GESTÃO DO CONTRATO
A7: 3 | B7: PREV | C7: 1.1 | D7: Coordenação - Eixos Norte e Leste
A8: 4 | B8: REAL | C8: 1.1 | D8: Coordenação - Eixos Norte e Leste
A9: 5 | B9: PREV | C9: 1.1.1 | D9: Engenheiro Coordenador | E9: P9955 (*) | F9: pessoa x mês | G9: 0.8 | H9: 1 | I9: 1 | J9: 1 | K9: 1 | L9: 1 | M9: 1 | N9: 1 | O9: 1 | P9: 1 | Q9: 1 | R9: 1 | S9: 0.2 | T9: =SUM(G9:S9) -> 12 | U9: 32114.49 | V9: =U9*T9 -> 385373.88
A10: 6 | B10: REAL | C10: 1.1.1 | D10: Engenheiro Coordenador | E10: P9955 (*) | F10: pessoa x mês | G10: 0.8 | H10: 1 | I10: 1 | J10: 1 | T10: =SUM(G10:S10) -> 3.8 | U10: 32114.49 | V10: =U10*T10 -> 122035.06 | W10: =V10/V9 -> 0.31666667
A11: 7 | B11: PREV | C11: 1.1.2 | D11: Auxiliar Administrativo | E11: P9806 | F11: pessoa x mês | G11: 0.8 | H11: 1 | I11: 1 | J11: 1 | K11: 1 | L11: 1 | M11: 1 | N11: 1 | O11: 1 | P11: 1 | Q11: 1 | R11: 1 | S11: 0.2 | T11: =SUM(G11:S11) -> 12 | U11: 4487.35 | V11: =U11*T11 -> 53848.2
A12: 8 | B12: REAL | C12: 1.1.2 | D12: Auxiliar Administrativo | E12: P9806 | F12: pessoa x mês | G12: 0 | H12: 1 | I12: 1 | J12: 1 | T12: =SUM(G12:S12) -> 3 | U12: 4487.35 | V12: =U12*T12 -> 13462.05 | W12: =V12/V11 -> 0.25
A13: 9 | B13: PREV | C13: 1.1.3 | D13: Secretária | E13: P9878 | F13: pessoa x mês | G13: 0.8 | H13: 1 | I13: 1 | J13: 1 | K13: 1 | L13: 1 | M13: 0.7 | N13: 0.7 | O13: 1 | P13: 1 | Q13: 1 | R13: 1 | S13: 0.2 | T13: =SUM(G13:S13) -> 11.4 | U13: 6370.42 | V13: =U13*T13 -> 72622.788
A14: 10 | B14: REAL | C14: 1.1.3 | D14: Secretária | E14: P9878 | F14: pessoa x mês | G14: 0.8 | H14: 1 | I14: 0.5 | J14: 1 | T14: =SUM(G14:S14) -> 3.3 | U14: 6370.42 | V14: =U14*T14 -> 21022.386 | W14: =V14/V13 -> 0.28947368
A15: 11 | B15: PREV | C15: 1.2 | D15: Consultoria - Eixos Norte e Leste | T15: =SUM(G15:S15) -> 0 | V15: =U15*T15 -> 0
A16: 12 | B16: REAL | C16: 1.2 | D16: Consultoria - Eixos Norte e Leste | T16: =SUM(G16:S16) -> 0 | V16: =U16*T16 -> 0
A17: 13 | B17: PREV | C17: 1.2.1 | D17: Consultor Especializado | E17: P8060 | F17: pessoa x mês | G17: 0.4 | H17: 0.5 | I17: 0.5 | J17: 0.5 | K17: 0.5 | L17: 0.5 | M17: 0.5 | N17: 0.5 | O17: 0.5 | P17: 0.5 | Q17: 0.5 | R17: 0.5 | S17: 0.1 | T17: =SUM(G17:S17) -> 6 | U17: 24703.45 | V17: =U17*T17 -> 148220.7
A18: 14 | B18: REAL | C18: 1.2.1 | D18: Consultor Especializado | E18: P8060 | F18: pessoa x mês | G18: 0 | H18: 0 | I18: 0 | J18: 0 | T18: =SUM(G18:S18) -> 0 | U18: 24703.45 | V18: =U18*T18 -> 0 | W18: =V18/V17 -> 0
A19: 15 | B19: PREV | C19: 1.3 | D19: SESMT - Eixos Norte e Leste | T19: =SUM(G19:S19) -> 0 | V19: =U19*T19 -> 0
A20: 16 | B20: REAL | C20: 1.3 | D20: SESMT - Eixos Norte e Leste | T20: =SUM(G20:S20) -> 0 | V20: =U20*T20 -> 0
A21: 17 | B21: PREV | C21: 1.3.1 | D21: Engenheiro Pleno - Segurança do Trabalho | E21: P9864 (*) | F21: pessoa x mês | G21: 0.8 | H21: 1 | I21: 1 | J21: 1 | K21: 1 | L21: 1 | M21: 1 | N21: 1 | O21: 1 | P21: 1 | Q21: 1 | R21: 1 | S21: 0.2 | T21: =SUM(G21:S21) -> 12 | U21: 25688.39 | V21: =U21*T21 -> 308260.68
A22: 18 | B22: REAL | C22: 1.3.1 | D22: Engenheiro Pleno - Segurança do Trabalho | E22: P9864 (*) | F22: pessoa x mês | G22: 0.8 | H22: 1 | I22: 1 | J22: 0.5 | T22: =SUM(G22:S22) -> 3.3 | U22: 25688.39 | V22: =U22*T22 -> 84771.687 | W22: =V22/V21 -> 0.275
A23: 19 | B23: PREV | C23: 1.3.2 | D23: Médico | E23: P9851 | F23: pessoa x mês | G23: 0.8 | H23: 1 | I23: 1 | J23: 1 | K23: 1 | L23: 1 | M23: 1 | N23: 1 | O23: 1 | P23: 1 | Q23: 1 | R23: 1 | S23: 0.2 | T23: =SUM(G23:S23) -> 12 | U23: 19815.81 | V23: =U23*T23 -> 237789.72
A24: 20 | B24: REAL | C24: 1.3.2 | D24: Médico | E24: P9851 | F24: pessoa x mês | G24: 0.49823106 | H24: 0.62278882 | I24: 0.62278882 | J24: 0.62278882 | T24: =SUM(G24:S24) -> 2.3665975 | U24: 19815.81 | V24: =U24*T24 -> 46896.047 | W24: =V24/V23 -> 0.19721646
A25: 21 | B25: PREV | C25: 1.3.3 | D25: Técnico Sênior - Segurança | E25: P9876 (*) | F25: pessoa x mês | G25: 1.6 | H25: 2 | I25: 2 | J25: 2 | K25: 2 | L25: 2 | M25: 2 | N25: 2 | O25: 2 | P25: 2 | Q25: 2 | R25: 2 | S25: 0.4 | T25: =SUM(G25:S25) -> 24 | U25: 8433.02 | V25: =U25*T25 -> 202392.48
A26: 22 | B26: REAL | C26: 1.3.3 | D26: Técnico Sênior - Segurança | E26: P9876 (*) | F26: pessoa x mês | G26: 1.5333333 | H26: 1.5666667 | I26: 1.9333333 | J26: 1.2333333 | T26: =SUM(G26:S26) -> 6.2666667 | U26: 8433.02 | V26: =U26*T26 -> 52846.925 | W26: =V26/V25 -> 0.26111111
A27: 23 | B27: PREV | C27: 1.4 | D27: Logística, Infraestrutura, TI, Almoxarifados - Eixos Norte e Leste | T27: =SUM(G27:S27) -> 0 | V27: =U27*T27 -> 0
A28: 24 | B28: REAL | C28: 1.4 | D28: Logística, Infraestrutura, TI, Almoxarifados - Eixos Norte e Leste | T28: =SUM(G28:S28) -> 0 | V28: =U28*T28 -> 0
A29: 25 | B29: PREV | C29: 1.4.1 | D29: Chefe de Escritório | E29: P9883 | F29: pessoa x mês | G29: 1.6 | H29: 2 | I29: 2 | J29: 2 | K29: 2 | L29: 2 | M29: 2 | N29: 2 | O29: 2 | P29: 2 | Q29: 2 | R29: 2 | S29: 0.4 | T29: =SUM(G29:S29) -> 24 | U29: 7072.07 | V29: =U29*T29 -> 169729.68
A30: 26 | B30: REAL | C30: 1.4.1 | D30: Chefe de Escritório | E30: P9883 | F30: pessoa x mês | G30: 1.6 | H30: 2 | I30: 2 | J30: 1.6666667 | T30: =SUM(G30:S30) -> 7.2666667 | U30: 7072.07 | V30: =U30*T30 -> 51390.375 | W30: =V30/V29 -> 0.30277778
A31: 27 | B31: PREV | C31: 1.4.2 | D31: Técnico Administrativo | E31: P9809 | F31: pessoa x mês | G31: 1.6 | H31: 2 | I31: 2 | J31: 2 | K31: 2 | L31: 2 | M31: 2 | N31: 2 | O31: 2 | P31: 2 | Q31: 2 | R31: 2 | S31: 0.4 | T31: =SUM(G31:S31) -> 24 | U31: 7072.06 | V31: =U31*T31 -> 169729.44
A32: 28 | B32: REAL | C32: 1.4.2 | D32: Técnico Administrativo | E32: P9809 | F32: pessoa x mês | G32: 1.6 | H32: 1.6666667 | I32: 2 | J32: 2 | T32: =SUM(G32:S32) -> 7.2666667 | U32: 7072.06 | V32: =U32*T32 -> 51390.303 | W32: =V32/V31 -> 0.30277778
A33: 29 | B33: PREV | C33: 1.4.3 | D33: Técnico Sênior - TI | E33: P9867 | F33: pessoa x mês | G33: 1.6 | H33: 2 | I33: 2 | J33: 2 | K33: 2 | L33: 2 | M33: 2 | N33: 2 | O33: 2 | P33: 2 | Q33: 2 | R33: 2 | S33: 0.4 | T33: =SUM(G33:S33) -> 24 | U33: 6328.66 | V33: =U33*T33 -> 151887.84
A34: 30 | B34: REAL | C34: 1.4.3 | D34: Técnico Sênior - TI | E34: P9867 | F34: pessoa x mês | G34: 1.6 | H34: 2 | I34: 2 | J34: 2 | T34: =SUM(G34:S34) -> 7.6 | U34: 6328.66 | V34: =U34*T34 -> 48097.816 | W34: =V34/V33 -> 0.31666667
A35: 31 | B35: PREV | C35: 1.4.4 | D35: Almoxarife | E35: P9803 | F35: pessoa x mês | G35: 1.6 | H35: 2 | I35: 2 | J35: 2 | K35: 2 | L35: 2 | M35: 2 | N35: 2 | O35: 2 | P35: 2 | Q35: 2 | R35: 2 | S35: 0.4 | T35: =SUM(G35:S35) -> 24 | U35: 5580.99 | V35: =U35*T35 -> 133943.76
A36: 32 | B36: REAL | C36: 1.4.4 | D36: Almoxarife | E36: P9803 | F36: pessoa x mês | G36: 1.6 | H36: 2 | I36: 2 | J36: 1.5 | T36: =SUM(G36:S36) -> 7.1 | U36: 5580.99 | V36: =U36*T36 -> 39625.029 | W36: =V36/V35 -> 0.29583333
A37: 33 | B37: PREV | C37: 1.4.5 | D37: Comprador | E37: P9900 | F37: pessoa x mês | G37: 0.8 | H37: 1 | I37: 1 | J37: 1 | K37: 1 | L37: 1 | M37: 1 | N37: 1 | O37: 1 | P37: 1 | Q37: 1 | R37: 1 | S37: 0.2 | T37: =SUM(G37:S37) -> 12 | U37: 6365.63 | V37: =U37*T37 -> 76387.56
A38: 34 | B38: REAL | C38: 1.4.5 | D38: Comprador | E38: P9900 | F38: pessoa x mês | G38: 0.8 | H38: 1 | I38: 1 | J38: 1 | T38: =SUM(G38:S38) -> 3.8 | U38: 6365.63 | V38: =U38*T38 -> 24189.394 | W38: =V38/V37 -> 0.31666667
A39: 35 | B39: PREV | C39: 1.4.6 | D39: Motorista | E39: P9948 | F39: pessoa x mês | G39: 1.6 | H39: 2 | I39: 2 | J39: 2 | K39: 2 | L39: 2 | M39: 2 | N39: 2 | O39: 2 | P39: 2 | Q39: 2 | R39: 2 | S39: 0.4 | T39: =SUM(G39:S39) -> 24 | U39: 5099.23 | V39: =U39*T39 -> 122381.52
A40: 36 | B40: REAL | C40: 1.4.6 | D40: Motorista | E40: P9948 | F40: pessoa x mês | G40: 2.4 | H40: 3 | I40: 3 | J40: 3 | T40: =SUM(G40:S40) -> 11.4 | U40: 5099.23 | V40: =U40*T40 -> 58131.222 | W40: =V40/V39 -> 0.475
A41: 37 | B41: PREV | C41: 1.4.7 | D41: Servente | E41: P9954 | F41: pessoa x mês | G41: 1.6 | H41: 2 | I41: 2 | J41: 2 | K41: 2 | L41: 2 | M41: 2 | N41: 2 | O41: 2 | P41: 2 | Q41: 2 | R41: 2 | S41: 0.4 | T41: =SUM(G41:S41) -> 24 | U41: 3767.94 | V41: =U41*T41 -> 90430.56
A42: 38 | B42: REAL | C42: 1.4.7 | D42: Servente | E42: P9954 | F42: pessoa x mês | G42: 3.2 | H42: 2 | I42: 2 | J42: 1.5 | T42: =SUM(G42:S42) -> 8.7 | U42: 3767.94 | V42: =U42*T42 -> 32781.078 | W42: =V42/V41 -> 0.3625
A43: 39 | B43: PREV | C43: 1.4.8 | D43: Vigia (12X36) - Diurno | E43: P9827 | F43: pessoa x mês | G43: 9.6 | H43: 12 | I43: 12 | J43: 12 | K43: 12 | L43: 12 | M43: 12 | N43: 12 | O43: 12 | P43: 12 | Q43: 12 | R43: 12 | S43: 2.4 | T43: =SUM(G43:S43) -> 144 | U43: 4015.53 | V43: =U43*T43 -> 578236.32
A44: 40 | B44: REAL | C44: 1.4.8 | D44: Vigia (12X36) - Diurno | E44: P9827 | F44: pessoa x mês | G44: 1.6 | H44: 4 | I44: 5 | J44: 4 | T44: =SUM(G44:S44) -> 14.6 | U44: 4015.53 | V44: =U44*T44 -> 58626.738 | W44: =V44/V43 -> 0.10138889
A45: 41 | B45: PREV | C45: 1.4.9 | D45: Vigia (12x36) - Noturno | E45: P9827N | F45: pessoa x mês | G45: 9.6 | H45: 12 | I45: 12 | J45: 12 | K45: 12 | L45: 12 | M45: 12 | N45: 12 | O45: 12 | P45: 12 | Q45: 12 | R45: 12 | S45: 2.4 | T45: =SUM(G45:S45) -> 144 | U45: 5965.92 | V45: =U45*T45 -> 859092.48
A46: 42 | B46: REAL | C46: 1.4.9 | D46: Vigia (12x36) - Noturno | E46: P9827N | F46: pessoa x mês | G46: 1.6 | H46: 4 | I46: 3 | J46: 4 | T46: =SUM(G46:S46) -> 12.6 | U46: 5965.92 | V46: =U46*T46 -> 75170.592 | W46: =V46/V45 -> 0.0875
A47: 43 | B47: PREV | C47: 1.4.10 | D47: Zelador | E47: P9954 | F47: pessoa x mês | G47: 1.6 | H47: 2 | I47: 2 | J47: 2 | K47: 2 | L47: 2 | M47: 1 | N47: 1 | O47: 2 | P47: 2 | Q47: 2 | R47: 2 | S47: 0.4 | T47: =SUM(G47:S47) -> 22 | U47: 3767.94 | V47: =U47*T47 -> 82894.68
A48: 44 | B48: REAL | C48: 1.4.10 | D48: Zelador | E48: P9954 | F48: pessoa x mês | G48: 1.6 | H48: 2 | I48: 2 | J48: 2 | T48: =SUM(G48:S48) -> 7.6 | U48: 3767.94 | V48: =U48*T48 -> 28636.344 | W48: =V48/V47 -> 0.34545455
A49: 45 | B49: PREV | C49: SUBTOTAL - ITEM 1 | G49: 46.5 | H49: 46.5 | I49: 46.5 | J49: 46.5 | K49: 46.5 | L49: 46.5 | M49: 46.5 | N49: 46.5 | O49: 46.5 | P49: 46.5 | Q49: 46.5 | R49: 46.5 | S49: 46.5 | T49: 558 | V49: 3854580.4
A50: 46 | B50: REAL | C50: SUBTOTAL - ITEM 1 | G50: =SUMIF($B9:$B48,$B50,G9:G48) -> 22.031564 | H50: =SUMIF($B9:$B48,$B50,H9:H48) -> 29.856122 | I50: =SUMIF($B9:$B48,$B50,I9:I48) -> 30.056122 | J50: =SUMIF($B9:$B48,$B50,J9:J48) -> 28.022789 | K50: =SUMIF($B9:$B48,$B50,K9:K48) -> 0 | L50: =SUMIF($B9:$B48,$B50,L9:L48) -> 0 | M50: =SUMIF($B9:$B48,$B50,M9:M48) -> 0 | N50: =SUMIF($B9:$B48,$B50,N9:N48) -> 0 | ... S50: =SUMIF($B9:$B48,$B50,S9:S48) -> 0 | T50: =SUMIF($B$9:$B$48,$B50,T9:T48) -> 109.9666 | V50: =SUMIF($B$9:$B$48,$B50,V9:V48) -> 809073.05 | W50: =V50/V49 -> 0.20989912
A51: 47 | B51: PREV | C51: 2 | D51: OPERAÇÃO SISTEMA ELÉTRICO
A52: 48 | B52: REAL | C52: 2 | D52: OPERAÇÃO SISTEMA ELÉTRICO
A53: 49 | B53: PREV | C53: 2.1 | D53: Coordenação de Operação - Eixos Norte e Leste
A54: 50 | B54: REAL | C54: 2.1 | D54: Coordenação de Operação - Eixos Norte e Leste
A55: 51 | B55: PREV | C55: 2.1.1 | D55: Engenheiro Sênior - Eletricista - Coordenador | E55: P9819 (*) | F55: pessoa x mês | G55: 0.8 | H55: 1 | I55: 1 | J55: 1 | K55: 1 | L55: 1 | M55: 1 | N55: 1 | O55: 1 | P55: 1 | Q55: 1 | R55: 1 | S55: 0.2 | T55: =SUM(G55:S55) -> 12 | U55: 27.055,66 | V55: =U55*T55 -> 324667.92
A56: 52 | B56: REAL | C56: 2.1.1 | D56: Engenheiro Sênior - Eletricista - Coordenador | E56: P9819 (*) | F56: pessoa x mês | G56: 0 | H56: 0 | I56: 0 | J56: 0 | T56: =SUM(G56:S56) -> 0 | U56: 27.055,66 | V56: =U56*T56 -> 0 | W56: =V56/V55 -> 0
A57: 53 | B57: PREV | C57: 2.1.2 | D57: Engenheiro Júnior - Eletricista | E57: P9946 (*) | F57: pessoa x mês | G57: 0.8 | H57: 1 | I57: 1 | J57: 1 | K57: 1 | L57: 1 | M57: 1 | N57: 1 | O57: 1 | P57: 1 | Q57: 1 | R57: 1 | S57: 0.2 | T57: =SUM(G57:S57) -> 12 | U57: 25.568,86 | V57: =U57*T57 -> 306826.32
A58: 54 | B58: REAL | C58: 2.1.2 | D58: Engenheiro Júnior - Eletricista | E58: P9946 (*) | F58: pessoa x mês | G58: 0.8 | H58: 1 | I58: 0.5 | J58: 0.5 | T58: =SUM(G58:S58) -> 2.8 | U58: 25.568,86 | V58: =U58*T58 -> 71592.808 | W58: =V58/V57 -> 0.23333333
A59: 55 | B59: PREV | C59: 2.1.3 | D59: Técnico Sênior - Eletromecânico (12X36) - Diurno | E59: P9867 (*) | F59: pessoa x mês | G59: 1.6 | H59: 2 | I59: 2 | J59: 2 | K59: 2 | L59: 2 | M59: 2 | N59: 2 | O59: 2 | P59: 2 | Q59: 2 | R59: 2 | S59: 0.4 | T59: =SUM(G59:S59) -> 24 | U59: 8.227,26 | V59: =U59*T59 -> 197454.24
A60: 56 | B60: REAL | C60: 2.1.3 | D60: Técnico Sênior - Eletromecânico (12X36) - Diurno | E60: P9867 (*) | F60: pessoa x mês | G60: 0.6 | H60: 2 | I60: 2 | J60: 2 | T60: =SUM(G60:S60) -> 6.6 | U60: 8.227,26 | V60: =U60*T60 -> 54299.916 | W60: =V60/V59 -> 0.275
A61: 57 | B61: PREV | C61: 2.2 | D61: Operação do Sistema Elétrico no NPCO - SE , LT E LD - Eixos Norte e Leste | T61: =SUM(G61:S61) -> 0 | V61: =U61*T61 -> 0
A62: 58 | B62: REAL | C62: 2.2 | D62: Operação do Sistema Elétrico no NPCO - SE , LT E LD - Eixos Norte e Leste | T62: =SUM(G62:S62) -> 0 | V62: =U62*T62 -> 0
A63: 59 | B63: PREV | C63: 2.2.1 | D63: Técnico Sênior - Eletrotécnico (12X36) - Diurno | E63: P9867 (*) | F63: pessoa x mês | G63: 3.2 | H63: 4 | I63: 4 | J63: 4 | K63: 4 | L63: 4 | M63: 4 | N63: 4 | O63: 4 | P63: 4 | Q63: 4 | R63: 4 | S63: 0.8 | T63: =SUM(G63:S63) -> 48 | U63: 8.227,26 | V63: =U63*T63 -> 394908.48
A64: 60 | B64: REAL | C64: 2.2.1 | D64: Técnico Sênior - Eletrotécnico (12X36) - Diurno | E64: P9867 (*) | F64: pessoa x mês | G64: 2.4 | H64: 4 | I64: 4 | J64: 4 | T64: =SUM(G64:S64) -> 14.4 | U64: 8.227,26 | V64: =U64*T64 -> 118472.54 | W64: =V64/V63 -> 0.3
A65: 61 | B65: PREV | C65: 2.2.2 | D65: Técnico Sênior - Eletrotécnico (12X36) - Noturno | E65: P9867N (*) | F65: pessoa x mês | G65: 3.2 | H65: 4 | I65: 4 | J65: 4 | K65: 4 | L65: 4 | M65: 4 | N65: 4 | O65: 4 | P65: 4 | Q65: 4 | R65: 4 | S65: 0.8 | T65: =SUM(G65:S65) -> 48 | U65: 12.223,36 | V65: =U65*T65 -> 586721.28
A66: 62 | B66: REAL | C66: 2.2.2 | D66: Técnico Sênior - Eletrotécnico (12X36) - Noturno | E66: P9867N (*) | F66: pessoa x mês | G66: 3.2 | H66: 4 | I66: 4 | J66: 4 | T66: =SUM(G66:S66) -> 15.2 | U66: 12.223,36 | V66: =U66*T66 -> 185795.07 | W66: =V66/V65 -> 0.31666667
A67: 63 | B67: PREV | C67: 2.2.3 | D67: Motorista (12x36) - Diurno | E67: P9948 | F67: pessoa x mês | G67: 1.6 | H67: 2 | I67: 2 | J67: 2 | K67: 2 | L67: 2 | M67: 2 | N67: 2 | O67: 2 | P67: 2 | Q67: 2 | R67: 2 | S67: 0.4 | T67: =SUM(G67:S67) -> 24 | U67: 5.099,23 | V67: =U67*T67 -> 122381.52
A68: 64 | B68: REAL | C68: 2.2.3 | D68: Motorista (12x36) - Diurno | E68: P9948 | F68: pessoa x mês | G68: 1.6 | H68: 2 | I68: 2 | J68: 2 | T68: =SUM(G68:S68) -> 7.6 | U68: 5.099,23 | V68: =U68*T68 -> 38754.148 | W68: =V68/V67 -> 0.31666667
A69: 65 | B69: PREV | C69: 2.2.4 | D69: Motorista (12x36) - Noturno | E69: P9948N | F69: pessoa x mês | G69: 6.4 | H69: 8 | I69: 8 | J69: 8 | K69: 8 | L69: 8 | M69: 8 | N69: 8 | O69: 8 | P69: 8 | Q69: 8 | R69: 8 | S69: 1.6 | T69: =SUM(G69:S69) -> 96 | U69: 7.575,99 | V69: =U69*T69 -> 727295.04
A70: 66 | B70: REAL | C70: 2.2.4 | D70: Motorista (12x36) - Noturno | E70: P9948N | F70: pessoa x mês | G70: 6.4 | H70: 7.8 | I70: 8 | J70: 8 | T70: =SUM(G70:S70) -> 30.2 | U70: 7.575,99 | V70: =U70*T70 -> 228794.9 | W70: =V70/V69 -> 0.31458333
A71: 67 | B71: PREV | C71: 2.3 | D71: Operação Subestações - Eixo Norte (3 SE) | T71: =SUM(G71:S71) -> 0 | V71: =U71*T71 -> 0
A72: 68 | B72: REAL | C72: 2.3 | D72: Operação Subestações - Eixo Norte (3 SE) | T72: =SUM(G72:S72) -> 0 | V72: =U72*T72 -> 0
A73: 69 | B73: PREV | C73: 2.3.1 | D73: Técnico Sênior - Eletrotécnico (12X36) - Diurno | E73: P9867 (*) | F73: pessoa x mês | G73: 4.8 | H73: 6 | I73: 6 | J73: 6 | K73: 6 | L73: 6 | M73: 6 | N73: 6 | O73: 6 | P73: 6 | Q73: 6 | R73: 6 | S73: 1.2 | T73: =SUM(G73:S73) -> 72 | U73: 8.227,26 | V73: =U73*T73 -> 592362.72
A74: 70 | B74: REAL | C74: 2.3.1 | D74: Técnico Sênior - Eletrotécnico (12X36) - Diurno | E74: P9867 (*) | F74: pessoa x mês | G74: 4.0666667 | H74: 6 | I74: 6 | J74: 5 | T74: =SUM(G74:S74) -> 21.066667 | U74: 8.227,26 | V74: =U74*T74 -> 173320.94 | W74: =V74/V73 -> 0.29259259
A75: 71 | B75: PREV | C75: 2.3.2 | D75: Técnico Sênior - Eletromecânico (12X36) - Diurno | E75: P9867 (*) | F75: pessoa x mês | G75: 4.8 | H75: 6 | I75: 6 | J75: 6 | K75: 6 | L75: 6 | M75: 6 | N75: 6 | O75: 6 | P75: 6 | Q75: 6 | R75: 6 | S75: 1.2 | T75: =SUM(G75:S75) -> 72 | U75: 8.227,26 | V75: =U75*T75 -> 592362.72
A76: 72 | B76: REAL | C76: 2.3.2 | D76: Técnico Sênior - Eletromecânico (12X36) - Diurno | E76: P9867 (*) | F76: pessoa x mês | G76: 4.8 | H76: 6 | I76: 6 | J76: 6 | T76: =SUM(G76:S76) -> 22.8 | U76: 8.227,26 | V76: =U76*T76 -> 187581.53 | W76: =V76/V75 -> 0.31666667
A77: 73 | B77: PREV | C77: 2.3.3 | D77: Motorista (12X36) | E77: P9948 | F77: pessoa x mês | G77: 1.6 | H77: 2 | I77: 2 | J77: 2 | K77: 2 | L77: 2 | M77: 2 | N77: 2 | O77: 2 | P77: 2 | Q77: 2 | R77: 2 | S77: 0.4 | T77: =SUM(G77:S77) -> 24 | U77: 5.099,23 | V77: =U77*T77 -> 122381.52
A78: 74 | B78: REAL | C78: 2.3.3 | D78: Motorista (12X36) | E78: P9948 | F78: pessoa x mês | G78: 1.6 | H78: 2 | I78: 2 | J78: 1.0666667 | T78: =SUM(G78:S78) -> 6.6666667 | U78: 5.099,23 | V78: =U78*T78 -> 33994.867 | W78: =V78/V77 -> 0.27777778
A79: 75 | B79: PREV | C79: 2.4 | D79: Operação Subestações - Eixo Leste | T79: =SUM(G79:S79) -> 0 | V79: =U79*T79 -> 0
A80: 76 | B80: REAL | C80: 2.4 | D80: Operação Subestações - Eixo Leste | T80: =SUM(G80:S80) -> 0 | V80: =U80*T80 -> 0
A81: 77 | B81: PREV | C81: 2.4.1 | D81: Técnico Sênior - Eletrotécnico (12X36) - Diurno | E81: P9867 (*) | F81: pessoa x mês | G81: 12 | H81: 15 | I81: 15 | J81: 15 | K81: 15 | L81: 15 | M81: 15 | N81: 15 | O81: 15 | P81: 15 | Q81: 15 | R81: 15 | S81: 3 | T81: =SUM(G81:S81) -> 180 | U81: 8.227,26 | V81: =U81*T81 -> 1480906.8
A82: 78 | B82: REAL | C82: 2.4.1 | D82: Técnico Sênior - Eletrotécnico (12X36) - Diurno | E82: P9867 (*) | F82: pessoa x mês | G82: 10.4 | H82: 13 | I82: 13 | J82: 13.966667 | T82: =SUM(G82:S82) -> 50.366667 | U82: 8.227,26 | V82: =U82*T82 -> 414379.66 | W82: =V82/V81 -> 0.27981481
A83: 79 | B83: PREV | C83: 2.4.2 | D83: Técnico Sênior - Eletromecânico (12X36) - Diurno | E83: P9867 (*) | F83: pessoa x mês | G83: 12 | H83: 15 | I83: 15 | J83: 15 | K83: 15 | L83: 15 | M83: 15 | N83: 15 | O83: 15 | P83: 15 | Q83: 15 | R83: 15 | S83: 3 | T83: =SUM(G83:S83) -> 180 | U83: 8.227,26 | V83: =U83*T83 -> 1480906.8
A84: 80 | B84: REAL | C84: 2.4.2 | D84: Técnico Sênior - Eletromecânico (12X36) - Diurno | E84: P9867 (*) | F84: pessoa x mês | G84: 8.8 | H84: 9.8 | I84: 13 | J84: 13 | T84: =SUM(G84:S84) -> 44.6 | U84: 8.227,26 | V84: =U84*T84 -> 366935.8 | W84: =V84/V83 -> 0.24777778
A85: 81 | B85: PREV | C85: 2.4.3 | D85: Motorista (12X36) | E85: P9948 | F85: pessoa x mês | G85: 4.8 | H85: 6 | I85: 6 | J85: 6 | K85: 6 | L85: 6 | M85: 6 | N85: 6 | O85: 6 | P85: 6 | Q85: 6 | R85: 6 | S85: 1.2 | T85: =SUM(G85:S85) -> 72 | U85: 5.099,23 | V85: =U85*T85 -> 367144.56
A86: 82 | B86: REAL | C86: 2.4.3 | D86: Motorista (12X36) | E86: P9948 | F86: pessoa x mês | G86: 4.4666667 | H86: 4.7666667 | I86: 5.5666667 | J86: 5 | T86: =SUM(G86:S86) -> 19.8 | U86: 5.099,23 | V86: =U86*T86 -> 100964.75 | W86: =V86/V85 -> 0.275
A87: 83 | B87: PREV | C87: 2.5 | D87: Operação Subestações - Previsão de Horas de Sobreaviso e Horas Extras | T87: =SUM(G87:S87) -> 0 | V87: =U87*T87 -> 0
A88: 84 | B88: REAL | C88: 2.5 | D88: Operação Subestações - Previsão de Horas de Sobreaviso e Horas Extras | T88: =SUM(G88:S88) -> 0 | V88: =U88*T88 -> 0
A89: 85 | B89: PREV | C89: 2.5.1 | D89: Previsão de Horas Sobreaviso - Técnico Sênior Eletrotécnico | E89: P9867h | F89: pessoa x hora | G89: 812.04 | H89: 1015.05 | I89: 1015.05 | J89: 1015.05 | K89: 1015.05 | L89: 1015.05 | M89: 1015.05 | N89: 1015.05 | O89: 1015.05 | P89: 1015.05 | Q89: 1015.05 | R89: 1015.05 | S89: 203.01 | T89: =SUM(G89:S89) -> 12180.6 | U89: 11,43 | V89: =U89*T89 -> 139224.26
A90: 86 | B90: REAL | C90: 2.5.1 | D90: Previsão de Horas Sobreaviso - Técnico Sênior Eletrotécnico | E90: P9867h | F90: pessoa x hora | G90: 0 | H90: 0 | I90: 0 | J90: 0 | T90: =SUM(G90:S90) -> 0 | U90: 11,43 | V90: =U90*T90 -> 0 | W90: =V90/V89 -> 0
A91: 87 | B91: PREV | C91: 2.5.2 | D91: Previsão de Horas Sobreaviso - Técnico Sênior Eletromecânico | E91: P9867h | F91: pessoa x hora | G91: 812.04 | H91: 1015.05 | I91: 1015.05 | J91: 1015.05 | K91: 1015.05 | L91: 1015.05 | M91: 1015.05 | N91: 1015.05 | O91: 1015.05 | P91: 1015.05 | Q91: 1015.05 | R91: 1015.05 | S91: 203.01 | T91: =SUM(G91:S91) -> 12180.6 | U91: 11,43 | V91: =U91*T91 -> 139224.26
A92: 88 | B92: REAL | C92: 2.5.2 | D92: Previsão de Horas Sobreaviso - Técnico Sênior Eletromecânico | E92: P9867h | F92: pessoa x hora | G92: 0 | H92: 0 | I92: 0 | J92: 0 | T92: =SUM(G92:S92) -> 0 | U92: 11,43 | V92: =U92*T92 -> 0 | W92: =V92/V91 -> 0
A93: 89 | B93: PREV | C93: 2.5.3 | D93: Previsão de Horas Sobreaviso - Técnico Sênior Motorista | E93: P9870h | F93: pessoa x hora | G93: 812.04 | H93: 1015.05 | I93: 1015.05 | J93: 1015.05 | K93: 1015.05 | L93: 1015.05 | M93: 1015.05 | N93: 1015.05 | O93: 1015.05 | P93: 1015.05 | Q93: 1015.05 | R93: 1015.05 | S93: 203.01 | T93: =SUM(G93:S93) -> 12180.6 | U93: 9,22 | V93: =U93*T93 -> 112305.13
A94: 90 | B94: REAL | C94: 2.5.3 | D94: Previsão de Horas Sobreaviso - Técnico Sênior Motorista | E94: P9870h | F94: pessoa x hora | G94: 0 | H94: 0 | I94: 0 | J94: 0 | T94: =SUM(G94:S94) -> 0 | U94: 9,22 | V94: =U94*T94 -> 0 | W94: =V94/V93 -> 0
A95: 91 | B95: PREV | C95: 2.5.4 | D95: Previsão de Horas Extras - Técnico Sênior Eletrotécnico | E95: P9867Nh (*) | F95: pessoa x hora | G95: 25.984 | H95: 32.48 | I95: 32.48 | J95: 32.48 | K95: 32.48 | L95: 32.48 | M95: 32.48 | N95: 32.48 | O95: 32.48 | P95: 32.48 | Q95: 32.48 | R95: 32.48 | S95: 6.496 | T95: =SUM(G95:S95) -> 389.76 | U95: 99,39 | V95: =U95*T95 -> 38738.246
A96: 92 | B96: REAL | C96: 2.5.4 | D96: Previsão de Horas Extras - Técnico Sênior Eletrotécnico | E96: P9867Nh (*) | F96: pessoa x hora | G96: 0 | H96: 0 | I96: 0 | J96: 0 | T96: =SUM(G96:S96) -> 0 | U96: 99,39 | V96: =U96*T96 -> 0 | W96: =V96/V95 -> 0
A97: 93 | B97: PREV | C97: 2.5.5 | D97: Previsão de Horas Extras - Técnico Sênior Eletrotécnico | E97: P9867h (*) | F97: pessoa x hora | G97: 25.984 | H97: 32.48 | I97: 32.48 | J97: 32.48 | K97: 32.48 | L97: 32.48 | M97: 32.48 | N97: 32.48 | O97: 32.48 | P97: 32.48 | Q97: 32.48 | R97: 32.48 | S97: 6.496 | T97: =SUM(G97:S97) -> 389.76 | U97: 66,90 | V97: =U97*T97 -> 26074.944
A98: 94 | B98: REAL | C98: 2.5.5 | D98: Previsão de Horas Extras - Técnico Sênior Eletrotécnico | E98: P9867h (*) | F98: pessoa x hora | G98: 0 | H98: 0 | I98: 0 | J98: 0 | T98: =SUM(G98:S98) -> 0 | U98: 66,90 | V98: =U98*T98 -> 0 | W98: =V98/V97 -> 0
A99: 95 | B99: PREV | C99: 2.5.6 | D99: Previsão de Horas Extras - Técnico Sênior Eletromecânico | E99: P9867Nh (*) | F99: pessoa x hora | G99: 25.984 | H99: 32.48 | I99: 32.48 | J99: 32.48 | K99: 32.48 | L99: 32.48 | M99: 32.48 | N99: 32.48 | O99: 32.48 | P99: 32.48 | Q99: 32.48 | R99: 32.48 | S99: 6.496 | T99: =SUM(G99:S99) -> 389.76 | U99: 99,39 | V99: =U99*T99 -> 38738.246
A100: 96 | B100: REAL | C100: 2.5.6 | D100: Previsão de Horas Extras - Técnico Sênior Eletromecânico | E100: P9867Nh (*) | F100: pessoa x hora | G100: 0 | H100: 0 | I100: 0 | J100: 0 | T100: =SUM(G100:S100) -> 0 | U100: 99,39 | V100: =U100*T100 -> 0 | W100: =V100/V99 -> 0
...
